Workbook
Name Slicer_Brand: #N/A
Name Slicer_Category: #N/A
Name Slicer_Clean_Payment_Mode: #N/A
Name Slicer_Membership: #N/A
Name Slicer_Month: #N/A
Name Slicer_Region: #N/A
Name Slicer_Sales_Channel: #N/A

Sheet slicer
A3: Row Labels | B3: Sum of Sales Amount
A4: Accessories | B4: 166486.52
A5: Belts | B5: 179789.99
A6: Footwear | B6: 521388.97
A7: Handbags | B7: 994021.98
A8: Jewellery | B8: 850930.2
A9: Kids Wear | B9: 184043.76
A10: Men Ethnic | B10: 508021.06
A11: Men Jeans | B11: 277306.93
A12: Men Shirts | B12: 184667.23
A13: Men Trousers | B13: 206033.29
A14: Men T-Shirts | B14: 312534.72
A15: Sportswear | B15: 259644.52
... A24: Grand Total | B24: 9227180

Sheet Dashboard

Sheet kpi
A1: kpi | B1: values
A2: Total Sales | B2: =SUM(Sales_Transactions!M:M) -> 9227180
A3: Total Profit | B3: =SUM(Sales_Transactions!O:O) -> 1804518.5
A4: Total Quantity | B4: =SUM(Sales_Transactions!G:G) -> 6118
A5: Profit Margin % | B5: =SUM(Sales_Transactions!O:O)/SUM(Sales_Transactions!M:M) -> 0.19556555
A6: Total Customers | B6: =COUNTA(_xlfn.UNIQUE(Sales_Transactions!B2:B2924)) -> 364
A7: Total Cost | B7: =SUM(tblSales[Cost Amount]) -> 6596441.1
A8: Total Transactions | B8: =COUNTA(_xlfn.UNIQUE(tblSales[Invoice No])) -> 2995

Sheet monthly
A3: Row Labels | B3: Sum of Sales Amount | C3: Sum of Profit
A4: 2024 | B4: 7613439.2 | C4: 1489359.7
A5: Apr | B5: 683356.93 | C5: 132559.46
A6: May | B6: 715370.42 | C6: 143214.56
A7: Jun | B7: 706442.99 | C7: 126683.88
A8: Jul | B8: 575940.09 | C8: 110065.95
A9: Aug | B9: 624765.64 | C9: 122773.23
A10: Sep | B10: 842808.66 | C10: 177387.37
A11: Oct | B11: 1519147.1 | C11: 301165.34
A12: Nov | B12: 1054251.4 | C12: 194655.84
A13: Dec | B13: 891356.08 | C13: 180854.07
A14: 2025 | B14: 1613740.7 | C14: 315158.84
A15: Jan | B15: 305174.24 | C15: 54860.77
... A18: Grand Total | B18: 9227180 | C18: 1804518.5

Sheet sales
A3: Row Labels | B3: Sum of Sales Amount | C3: Sum of Profit
A4: Accessories | B4: 166486.52 | C4: 56077.74
A5: Belts | B5: 179789.99 | C5: 37446.83
A6: Footwear | B6: 521388.97 | C6: 89384.64
A7: Handbags | B7: 994021.98 | C7: 213991.74
A8: Jewellery | B8: 850930.2 | C8: 150422.21
A9: Kids Wear | B9: 184043.76 | C9: 33376.6
A10: Men Ethnic | B10: 508021.06 | C10: 96328.01
A11: Men Jeans | B11: 277306.93 | C11: 41174.84
A12: Men Shirts | B12: 184667.23 | C12: 35427.94
A13: Men Trousers | B13: 206033.29 | C13: 42136.12
A14: Men T-Shirts | B14: 312534.72 | C14: 94494.79
A15: Sportswear | B15: 259644.52 | C15: 49595.82
... A24: Grand Total | B24: 9227180 | C24: 1804518.5
A44: Row Labels | B44: Sum of Sales Amount
A45: Cash | B45: 3843.11
A46: Credit Card | B46: 3025.98
A47: Debit Card | B47: 3864
A48: UPI | B48: 2027.41
A49: Cash | B49: 1759609.4
A50: Credit Card | B50: 2017983.7
A51: Debit Card | B51: 1875839.6
A52: EMI | B52: 343465.97
A53: Net Banking | B53: 600470.11
A54: UPI | B54: 2617050.7
A55: Grand Total | B55: 9227180

Sheet product sales
A3: Row Labels | B3: Sum of Sales Amount | C3: Sum of Profit
A4: GRT Jewellers Sling Bag Olive | B4: 483225.47 | C4: 114878.08
A5: Aurelia Earrings Sky Blue | B5: 243671.75 | C5: 31775.83
A6: Global Desi Earrings Green | B6: 207013.85 | C6: 40366.38
A7: Max Fashion Printed Saree Brown | B7: 197082.8 | C7: 44505.57
A8: Nike Earrings Teal | B8: 173911.74 | C8: 32108.45
A9: Westside Straight Fit Charcoal | B9: 147220.91 | C9: 35120.92
A10: Max Fashion Georgette Saree Brown | B10: 138420.26 | C10: 26849.36
A11: Global Desi Analog Watch Cream | B11: 133863.46 | C11: 24220.3
A12: Wrangler Ring White | B12: 121803.88 | C12: 32689.22
A13: Aurelia Analog Watch Purple | B13: 111670.81 | C13: 18835.72
A14: Grand Total | B14: 1957884.9 | C14: 401349.83

Sheet region
A3: Row Labels | B3: Sum of Sales Amount | C3: Sum of Profit
A4: South Zone 1 | B4: 4463451.9 | C4: 866892.49
A5: South Zone 2 | B5: 2554815.9 | C5: 493806.97
A6: South Zone 3 | B6: 2208912.1 | C6: 443819.08
A7: Grand Total | B7: 9227180 | C7: 1804518.5
A25: Row Labels | B25: Sum of Sales Amount
A26: Cash | B26: 1763452.5
A27: Credit Card | B27: 2021009.7
A28: Debit Card | B28: 1879703.6
A29: EMI | B29: 343465.97
A30: Net Banking | B30: 600470.11
A31: UPI | B31: 2619078.1
A32: Grand Total | B32: 9227180

Sheet channel
A3: Row Labels | B3: Sum of Sales Amount
A4: Offline | B4: 6048775.9
A5: Online | B5: 3178404
A6: Grand Total | B6: 9227180

Sheet discount return analysis
A3: Row Labels | B3: Average of Discount % | C3: Average of Profit Margin
A4: 0-5% | B4: 1.5014164 | C4: 0.27543022
A5: 10-15% | B5: 15 | C5: 0.17266696
A6: 15-20% | B6: 20 | C6: 0.12893568
A7: 20%+ | B7: 27.503618 | C7: 0.050592098
A8: 5-10% | B8: 10 | C8: 0.2190196
A9: Grand Total | B9: 12.57 | C9: 0.1861443

Sheet Return status
A3: Row Labels | B3: Count of Invoice No
A4: Not Returned | B4: 2855
A5: Returned | B5: 145
A6: Grand Total | B6: 3000

Sheet Sales_Transactions
A1: Invoice No | B1: Invoice Date | C1: Customer_ID | D1: Product_ID | E1: Store_ID | F1: Employee_ID | G1: Quantity | H1: Unit Price | I1: Discount % | J1: Discount Amount | K1: GST % | L1: GST Amount | M1: Sales Amount | N1: Cost Amount | O1: Profit | P1: Payment Mode | Q1: Clean Payment Mode | R1: Sales Channel | S1: Return Status | T1: Order Time | U1: Day Type | V1: Month | W1: Month No | X1: Year | Y1: Month Year | Z1: Category | AA1: Subcategory | AB1: Brand | AC1: Store Name | AD1: Region | AE1: Customer Name | AF1: Membership | AG1: Employee Name | AH1: Month Sort | AI1: Month Start | AJ1: Product Name | AK1: Profit Margin | AL1: Discount Band
A2: INV100001 | B2: 45642 | C2: CUST0052 | D2: PRD0200 | E2: STR037 | F2: EMP0276 | G2: 1 | H2: 749.84 | I2: 10 | J2: 74.98 | K2: 5 | L2: 33.74 | M2: 708.6 | N2: 496.67 | O2: =(M2-N2-L2) -> 178.19 | P2: UPI | Q2: =TRIM(CLEAN(P2)) -> UPI | R2: Offline | S2: Not Returned | T2: 18:16 | U2: Weekday | V2: =TEXT(tblSales[[#This Row],[Invoice Date]],"mmm") -> Dec | W2: =MONTH(tblSales[[#This Row],[Invoice Date]]) -> 12 | X2: =YEAR(tblSales[[#This Row],[Invoice Date]]) -> 2024 | Y2: =TEXT(tblSales[[#This Row],[Invoice Date]],"mmm-yyyy") -> Dec-2024 | Z2: =_xlfn.XLOOKUP(tblSales[[#This Row],[Product_ID]],Products!$A:$A,Products!$C:$C,"Women Dresses") -> Women Kurtis | AA2: =_xlfn.XLOOKUP(tblSales[[#This Row],[Product_ID]],Products!$A:$A,Products!$D:$D,"Unknown") -> A-Line Kurti | AB2: =_xlfn.XLOOKUP(tblSales[[#This Row],[Product_ID]],Products!$A:$A,Products!$E:$E,"Unknown") -> Pepe Jeans | AC2: =_xlfn.XLOOKUP(tblSales[[#This Row],[Store_ID]],Stores!$A:$A,Stores!$B:$B,"Unknown") -> TrendMart Vijayawada High Street | AD2: =_xlfn.XLOOKUP(tblSales[[#This Row],[Store_ID]],Stores!$A:$A,Stores!$E:$E,"Unknown") -> South Zone 3 | AE2: =_xlfn.XLOOKUP(tblSales[[#This Row],[Customer_ID]],Customers!$A:$A,Customers!$B:$B,"Unknown") -> Dhruv Achari | AF2: =_xlfn.XLOOKUP(tblSales[[#This Row],[Customer_ID]],Customers!$A:$A,Customers!$J:$J,"Unknown") -> Regular | AG2: =_xlfn.XLOOKUP(tblSales[[#This Row],[Employee_ID]],Employees!$A:$A,Employees!$B:$B,"Unknown") -> Manoj Ramachandran | AH2: =IF(MONTH(tblSales[[#This Row],[Invoice Date]])>=4,MONTH(tblSales[[#This Row],[Invoice Date]]),MONTH(tblSales[[#This Row],[Invoice Date]])+12) -> 12 | AI2: =DATE(YEAR(tblSales[[#This Row],[Invoice Date]]),MONTH(tblSales[[#This Row],[Invoice Date]]),1) -> 45627 | AJ2: =_xlfn.XLOOKUP(tblSales[[#This Row],[Product_ID]],Products!$A:$A,Products!$B:$B,"Unknown") -> Pepe Jeans A-Line Kurti White | AK2: =IFERROR(tblSales[[#This Row],[Profit]]/tblSales[[#This Row],[Sales Amount]],0) -> 0.25146768 | AL2: =IF(tblSales[[#This Row],[Discount %]]<=5,"0-5%", IF(tblSales[[#This Row],[Discount %]]<=10,"5-10%", IF(tblSales[[#This Row],[Discount %]]<=15,"10-15%", IF(tblSales[[#This Row],[Discount %]]<=20,"15-20%","20%+")))) -> 5-10%
A3: INV100002 | B3: 45578 | C3: CUST0463 | D3: PRD0245 | E3: STR102 | F3: EMP0156 | G3: 2 | H3: 909.55 | I3: 25 | J3: 454.77 | K3: 5 | L3: 68.22 | M3: 1432.55 | N3: 984.22 | O3: =(M3-N3-L3) -> 380.11 | P3: Debit Card | Q3: =TRIM(CLEAN(P3)) -> Debit Card | R3: Online | S3: Not Returned | T3: 13:25 | U3: Weekend | V3: =TEXT(tblSales[[#This Row],[Invoice Date]],"mmm") -> Oct | W3: =MONTH(tblSales[[#This Row],[Invoice Date]]) -> 10 | X3: =YEAR(tblSales[[#This Row],[Invoice Date]]) -> 2024 | Y3: =TEXT(tblSales[[#This Row],[Invoice Date]],"mmm-yyyy") -> Oct-2024 | Z3: =_xlfn.XLOOKUP(tblSales[[#This Row],[Product_ID]],Products!$A:$A,Products!$C:$C,"Women Dresses") -> Men T-Shirts | AA3: =_xlfn.XLOOKUP(tblSales[[#This Row],[Product_ID]],Products!$A:$A,Products!$D:$D,"Unknown") -> Round Neck | AB3: =_xlfn.XLOOKUP(tblSales[[#This Row],[Product_ID]],Products!$A:$A,Products!$E:$E,"Unknown") -> Reebok | AC3: =_xlfn.XLOOKUP(tblSales[[#This Row],[Store_ID]],Stores!$A:$A,Stores!$B:$B,"Unknown") -> TrendMart Tirunelveli High Street | AD3: =_xlfn.XLOOKUP(tblSales[[#This Row],[Store_ID]],Stores!$A:$A,Stores!$E:$E,"Unknown") -> South Zone 1 | AE3: =_xlfn.XLOOKUP(tblSales[[#This Row],[Customer_ID]],Customers!$A:$A,Customers!$B:$B,"Unknown") -> Ashok Menon | AF3: =_xlfn.XLOOKUP(tblSales[[#This Row],[Customer_ID]],Customers!$A:$A,Customers!$J:$J,"Unknown") -> Regular | AG3: =_xlfn.XLOOKUP(tblSales[[#This Row],[Employee_ID]],Employees!$A:$A,Employees!$B:$B,"Unknown") -> Deepthi Iyengar | AH3: =IF(MONTH(tblSales[[#This Row],[Invoice Date]])>=4,MONTH(tblSales[[#This Row],[Invoice Date]]),MONTH(tblSales[[#This Row],[Invoice Date]])+12) -> 10 | AI3: =DATE(YEAR(tblSales[[#This Row],[Invoice Date]]),MONTH(tblSales[[#This Row],[Invoice Date]]),1) -> 45566 | AJ3: =_xlfn.XLOOKUP(tblSales[[#This Row],[Product_ID]],Products!$A:$A,Products!$B:$B,"Unknown") -> Reebok Round Neck Sky Blue | AK3: =IFERROR(tblSales[[#This Row],[Profit]]/tblSales[[#This Row],[Sales Amount]],0) -> 0.26533803 | AL3: =IF(tblSales[[#This Row],[Discount %]]<=5,"0-5%", IF(tblSales[[#This Row],[Discount %]]<=10,"5-10%", IF(tblSales[[#This Row],[Discount %]]<=15,"10-15%", IF(tblSales[[#This Row],[Discount %]]<=20,"15-20%","20%+")))) -> 20%+
A4: INV100003 | B4: 45657 | C4: CUST0711 | D4: PRD0065 | E4: STR011 | F4: EMP0223 | G4: 2 | H4: 3872.21 | I4: 0 | J4: 0 | K4: 12 | L4: 929.33 | M4: 8673.75 | N4: 5267.12 | O4: =(M4-N4-L4) -> 2477.3 | P4: Debit Card | Q4: =TRIM(CLEAN(P4)) -> Debit Card | R4: Online | S4: Not Returned | T4: 21:10 | U4: Weekday | V4: =TEXT(tblSales[[#This Row],[Invoice Date]],"mmm") -> Dec | W4: =MONTH(tblSales[[#This Row],[Invoice Date]]) -> 12 | X4: =YEAR(tblSales[[#This Row],[Invoice Date]]) -> 2024 | Y4: =TEXT(tblSales[[#This Row],[Invoice Date]],"mmm-yyyy") -> Dec-2024 | Z4: =_xlfn.XLOOKUP(tblSales[[#This Row],[Product_ID]],Products!$A:$A,Products!$C:$C,"Women Dresses") -> Women Sarees | AA4: =_xlfn.XLOOKUP(tblSales[[#This Row],[Product_ID]],Products!$A:$A,Products!$D:$D,"Unknown") -> Georgette Saree | AB4: =_xlfn.XLOOKUP(tblSales[[#This Row],[Product_ID]],Products!$A:$A,Products!$E:$E,"Unknown") -> Westside | AC4: =_xlfn.XLOOKUP(tblSales[[#This Row],[Store_ID]],Stores!$A:$A,Stores!$B:$B,"Unknown") -> TrendMart Tirupati Standard | AD4: =_xlfn.XLOOKUP(tblSales[[#This Row],[Store_ID]],Stores!$A:$A,Stores!$E:$E,"Unknown") -> South Zone 3 | AE4: =_xlfn.XLOOKUP(tblSales[[#This Row],[Customer_ID]],Customers!$A:$A,Customers!$B:$B,"Unknown") -> Deepthi Sundaram | AF4: =_xlfn.XLOOKUP(tblSales[[#This Row],[Customer_ID]],Customers!$A:$A,Customers!$J:$J,"Unknown") -> Silver | AG4: =_xlfn.XLOOKUP(tblSales[[#This Row],[Employee_ID]],Employees!$A:$A,Employees!$B:$B,"Unknown") -> Meena Krishnan | AH4: =IF(MONTH(tblSales[[#This Row],[Invoice Date]])>=4,MONTH(tblSales[[#This Row],[Invoice Date]]),MONTH(tblSales[[#This Row],[Invoice Date]])+12) -> 12 | AI4: =DATE(YEAR(tblSales[[#This Row],[Invoice Date]]),MONTH(tblSales[[#This Row],[Invoice Date]]),1) -> 45627 | AJ4: =_xlfn.XLOOKUP(tblSales[[#This Row],[Product_ID]],Products!$A:$A,Products!$B:$B,"Unknown") -> Westside Georgette Saree White | AK4: =IFERROR(tblSales[[#This Row],[Profit]]/tblSales[[#This Row],[Sales Amount]],0) -> 0.28560888 | AL4: =IF(tblSales[[#This Row],[Discount %]]<=5,"0-5%", IF(tblSales[[#This Row],[Discount %]]<=10,"5-10%", IF(tblSales[[#This Row],[Discount %]]<=15,"10-15%", IF(tblSales[[#This Row],[Discount %]]<=20,"15-20%","20%+")))) -> 0-5%
A5: INV100004 | B5: 45437 | C5: CUST0466 | D5: PRD0224 | E5: STR078 | F5: EMP0170 | G5: 4 | H5: 4857.75 | I5: 20 | J5: 3886.2 | K5: 12 | L5: 1865.38 | M5: 17410.18 | N5: 13483.2 | O5: =(M5-N5-L5) -> 2061.6 | P5: UPI | Q5: =TRIM(CLEAN(P5)) -> UPI | R5: Online | S5: Not Returned | T5: 13:45 | U5: Weekend | V5: =TEXT(tblSales[[#This Row],[Invoice Date]],"mmm") -> May | W5: =MONTH(tblSales[[#This Row],[Invoice Date]]) -> 5 | X5: =YEAR(tblSales[[#This Row],[Invoice Date]]) -> 2024 | Y5: =TEXT(tblSales[[#This Row],[Invoice Date]],"mmm-yyyy") -> May-2024 | Z5: =_xlfn.XLOOKUP(tblSales[[#This Row],[Product_ID]],Products!$A:$A,Products!$C:$C,"Women Dresses") -> Women Sarees | AA5: =_xlfn.XLOOKUP(tblSales[[#This Row],[Product_ID]],Products!$A:$A,Products!$D:$D,"Unknown") -> Printed Saree | AB5: =_xlfn.XLOOKUP(tblSales[[#This Row],[Product_ID]],Products!$A:$A,Products!$E:$E,"Unknown") -> Max Fashion | AC5: =_xlfn.XLOOKUP(tblSales[[#This Row],[Store_ID]],Stores!$A:$A,Stores!$B:$B,"Unknown") -> TrendMart Vellore Standard | AD5: =_xlfn.XLOOKUP(tblSales[[#This Row],[Store_ID]],Stores!$A:$A,Stores!$E:$E,"Unknown") -> South Zone 1 | AE5: =_xlfn.XLOOKUP(tblSales[[#This Row],[Customer_ID]],Customers!$A:$A,Customers!$B:$B,"Unknown") -> Manoj Varma | AF5: =_xlfn.XLOOKUP(tblSales[[#This Row],[Customer_ID]],Customers!$A:$A,Customers!$J:$J,"Unknown") -> Regular | AG5: =_xlfn.XLOOKUP(tblSales[[#This Row],[Employee_ID]],Employees!$A:$A,Employees!$B:$B,"Unknown") -> Jyothi Prasad | AH5: =IF(MONTH(tblSales[[#This Row],[Invoice Date]])>=4,MONTH(tblSales[[#This Row],[Invoice Date]]),MONTH(tblSales[[#This Row],[Invoice Date]])+12) -> 5 | AI5: =DATE(YEAR(tblSales[[#This Row],[Invoice Date]]),MONTH(tblSales[[#This Row],[Invoice Date]]),1) -> 45413 | AJ5: =_xlfn.XLOOKUP(tblSales[[#This Row],[Product_ID]],Products!$A:$A,Products!$B:$B,"Unknown") -> Max Fashion Printed Saree Brown | AK5: =IFERROR(tblSales[[#This Row],[Profit]]/tblSales[[#This Row],[Sales Amount]],0) -> 0.11841348 | AL5: =IF(tblSales[[#This Row],[Discount %]]<=5,"0-5%", IF(tblSales[[#This Row],[Discount %]]<=10,"5-10%", IF(tblSales[[#This Row],[Discount %]]<=15,"10-15%", IF(tblSales[[#This Row],[Discount %]]<=20,"15-20%","20%+")))) -> 15-20%
A6: INV100005 | B6: 45487 | C6: CUST0406 | D6: PRD0035 | E6: STR058 | F6: EMP0090 | G6: 1 | H6: 874.25 | I6: 0 | J6: 0 | K6: 5 | L6: 43.71 | M6: 917.96 | N6: 539.76 | O6: =(M6-N6-L6) -> 334.49 | P6: Credit Card | Q6: =TRIM(CLEAN(P6)) -> Credit Card | R6: Offline | S6: Not Returned | T6: 21:11 | U6: Weekend | V6: =TEXT(tblSales[[#This Row],[Invoice Date]],"mmm") -> Jul | W6: =MONTH(tblSales[[#This Row],[Invoice Date]]) -> 7 | X6: =YEAR(tblSales[[#This Row],[Invoice Date]]) -> 2024 | Y6: =TEXT(tblSales[[#This Row],[Invoice Date]],"mmm-yyyy") -> Jul-2024 | Z6: =_xlfn.XLOOKUP(tblSales[[#This Row],[Product_ID]],Products!$A:$A,Products!$C:$C,"Women Dresses") -> Women Kurtis | AA6: =_xlfn.XLOOKUP(tblSales[[#This Row],[Product_ID]],Products!$A:$A,Products!$D:$D,"Unknown") -> Printed Kurti | AB6: =_xlfn.XLOOKUP(tblSales[[#This Row],[Product_ID]],Products!$A:$A,Products!$E:$E,"Unknown") -> Reebok | AC6: =_xlfn.XLOOKUP(tblSales[[#This Row],[Store_ID]],Stores!$A:$A,Stores!$B:$B,"Unknown") -> TrendMart Thoothukudi Flagship | AD6: =_xlfn.XLOOKUP(tblSales[[#This Row],[Store_ID]],Stores!$A:$A,Stores!$E:$E,"Unknown") -> South Zone 1 | AE6: =_xlfn.XLOOKUP(tblSales[[#This Row],[Customer_ID]],Customers!$A:$A,Customers!$B:$B,"Unknown") -> Gayathri Srinivasan | AF6: =_xlfn.XLOOKUP(tblSales[[#This Row],[Customer_ID]],Customers!$A:$A,Customers!$J:$J,"Unknown") -> Regular | AG6: =_xlfn.XLOOKUP(tblSales[[#This Row],[Employee_ID]],Employees!$A:$A,Employees!$B:$B,"Unknown") -> Padma Gounder | AH6: =IF(MONTH(tblSales[[#This Row],[Invoice Date]])>=4,MONTH(tblSales[[#This Row],[Invoice Date]]),MONTH(tblSales[[#This Row],[Invoice Date]])+12) -> 7 | AI6: =DATE(YEAR(tblSales[[#This Row],[Invoice Date]]),MONTH(tblSales[[#This Row],[Invoice Date]]),1) -> 45474 | AJ6: =_xlfn.XLOOKUP(tblSales[[#This Row],[Product_ID]],Products!$A:$A,Products!$B:$B,"Unknown") -> Reebok Printed Kurti Wine | AK6: =IFERROR(tblSales[[#This Row],[Profit]]/tblSales[[#This Row],[Sales Amount]],0) -> 0.36438407 | AL6: =IF(tblSales[[#This Row],[Discount %]]<=5,"0-5%", IF(tblSales[[#This Row],[Discount %]]<=10,"5-10%", IF(tblSales[[#This Row],[Discount %]]<=15,"10-15%", IF(tblSales[[#This Row],[Discount %]]<=20,"15-20%","20%+")))) -> 0-5%
A7: INV100006 | B7: 45704 | C7: CUST0084 | D7: PRD0199 | E7: STR074 | F7: EMP0204 | G7: 2 | H7: 3390.61 | I7: 30 | J7: 2034.37 | K7: 12 | L7: 569.62 | M7: 5316.47 | N7: 4849.24 | O7: =(M7-N7-L7) -> -102.39 | P7: Credit Card | Q7: =TRIM(CLEAN(P7)) -> Credit Card | R7: Offline | S7: Not Returned | T7: 10:24 | U7: Weekend | V7: =TEXT(tblSales[[#This Row],[Invoice Date]],"mmm") -> Feb | W7: =MONTH(tblSales[[#This Row],[Invoice Date]]) -> 2 | X7: =YEAR(tblSales[[#This Row],[Invoice Date]]) -> 2025 | Y7: =TEXT(tblSales[[#This Row],[Invoice Date]],"mmm-yyyy") -> Feb-2025 | Z7: =_xlfn.XLOOKUP(tblSales[[#This Row],[Product_ID]],Products!$A:$A,Products!$C:$C,"Women Dresses") -> Footwear | AA7: =_xlfn.XLOOKUP(tblSales[[#This Row],[Product_ID]],Products!$A:$A,Products!$D:$D,"Unknown") -> Formal Shoes | AB7: =_xlfn.XLOOKUP(tblSales[[#This Row],[Product_ID]],Products!$A:$A,Products!$E:$E,"Unknown") -> US Polo Assn | AC7: =_xlfn.XLOOKUP(tblSales[[#This Row],[Store_ID]],Stores!$A:$A,Stores!$B:$B,"Unknown") -> TrendMart Kurnool High Street | AD7: =_xlfn.XLOOKUP(tblSales[[#This Row],[Store_ID]],Stores!$A:$A,Stores!$E:$E,"Unknown") -> South Zone 3 | AE7: =_xlfn.XLOOKUP(tblSales[[#This Row],[Customer_ID]],Customers!$A:$A,Customers!$B:$B,"Unknown") -> Hari Kamath | AF7: =_xlfn.XLOOKUP(tblSales[[#This Row],[Customer_ID]],Customers!$A:$A,Customers!$J:$J,"Unknown") -> Platinum | AG7: =_xlfn.XLOOKUP(tblSales[[#This Row],[Employee_ID]],Employees!$A:$A,Employees!$B:$B,"Unknown") -> Rahul Krishnan | AH7: =IF(MONTH(tblSales[[#This Row],[Invoice Date]])>=4,MONTH(tblSales[[#This Row],[Invoice Date]]),MONTH(tblSales[[#This Row],[Invoice Date]])+12) -> 14 | AI7: =DATE(YEAR(tblSales[[#This Row],[Invoice Date]]),MONTH(tblSales[[#This Row],[Invoice Date]]),1) -> 45689 | AJ7: =_xlfn.XLOOKUP(tblSales[[#This Row],[Product_ID]],Products!$A:$A,Products!$B:$B,"Unknown") -> US Polo Assn Formal Shoes Red | AK7: =IFERROR(tblSales[[#This Row],[Profit]]/tblSales[[#This Row],[Sales Amount]],0) -> -0.01925902 | AL7: =IF(tblSales[[#This Row],[Discount %]]<=5,"0-5%", IF(tblSales[[#This Row],[Discount %]]<=10,"5-10%", IF(tblSales[[#This Row],[Discount %]]<=15,"10-15%", IF(tblSales[[#This Row],[Discount %]]<=20,"15-20%","20%+")))) -> 20%+
A8: INV100007 | B8: 45457 | C8: CUST0714 | D8: PRD0040 | E8: STR062 | F8: EMP0215 | G8: 4 | H8: 1474.99 | I8: 0 | J8: 0 | K8: 12 | L8: 708 | M8: 6607.96 | N8: 4594.64 | O8: =(M8-N8-L8) -> 1305.32 | P8: Cash | Q8: =TRIM(CLEAN(P8)) -> Cash | R8: Offline | S8: Not Returned | T8: 20:20 | U8: Weekday | V8: =TEXT(tblSales[[#This Row],[Invoice Date]],"mmm") -> Jun | W8: =MONTH(tblSales[[#This Row],[Invoice Date]]) -> 6 | X8: =YEAR(tblSales[[#This Row],[Invoice Date]]) -> 2024 | Y8: =TEXT(tblSales[[#This Row],[Invoice Date]],"mmm-yyyy") -> Jun-2024 | Z8: =_xlfn.XLOOKUP(tblSales[[#This Row],[Product_ID]],Products!$A:$A,Products!$C:$C,"Women Dresses") -> Sportswear | AA8: =_xlfn.XLOOKUP(tblSales[[#This Row],[Product_ID]],Products!$A:$A,Products!$D:$D,"Unknown") -> Track Suit | AB8: =_xlfn.XLOOKUP(tblSales[[#This Row],[Product_ID]],Products!$A:$A,Products!$E:$E,"Unknown") -> US Polo Assn | AC8: =_xlfn.XLOOKUP(tblSales[[#This Row],[Store_ID]],Stores!$A:$A,Stores!$B:$B,"Unknown") -> TrendMart Vijayawada Standard | AD8: =_xlfn.XLOOKUP(tblSales[[#This Row],[Store_ID]],Stores!$A:$A,Stores!$E:$E,"Unknown") -> South Zone 3 | AE8: =_xlfn.XLOOKUP(tblSales[[#This Row],[Customer_ID]],Customers!$A:$A,Customers!$B:$B,"Unknown") -> Yamini Srinivasan | AF8: =_xlfn.XLOOKUP(tblSales[[#This Row],[Customer_ID]],Customers!$A:$A,Customers!$J:$J,"Unknown") -> Silver | AG8: =_xlfn.XLOOKUP(tblSales[[#This Row],[Employee_ID]],Employees!$A:$A,Employees!$B:$B,"Unknown") -> Praveen Gupta | AH8: =IF(MONTH(tblSales[[#This Row],[Invoice Date]])>=4,MONTH(tblSales[[#This Row],[Invoice Date]]),MONTH(tblSales[[#This Row],[Invoice Date]])+12) -> 6 | AI8: =DATE(YEAR(tblSales[[#This Row],[Invoice Date]]),MONTH(tblSales[[#This Row],[Invoice Date]]),1) -> 45444 | AJ8: =_xlfn.XLOOKUP(tblSales[[#This Row],[Product_ID]],Products!$A:$A,Products!$B:$B,"Unknown") -> US Polo Assn Track Suit Maroon | AK8: =IFERROR(tblSales[[#This Row],[Profit]]/tblSales[[#This Row],[Sales Amount]],0) -> 0.19753752 | AL8: =IF(tblSales[[#This Row],[Discount %]]<=5,"0-5%", IF(tblSales[[#This Row],[Discount %]]<=10,"5-10%", IF(tblSales[[#This Row],[Discount %]]<=15,"10-15%", IF(tblSales[[#This Row],[Discount %]]<=20,"15-20%","20%+")))) -> 0-5%
A9: INV100008 | B9: 45678 | C9: CUST0121 | D9: PRD0196 | E9: STR084 | F9: EMP0285 | G9: 1 | H9: 1407.12 | I9: 0 | J9: 0 | K9: 12 | L9: 168.85 | M9: 1575.97 | N9: 1067.72 | O9: =(M9-N9-L9) -> 339.4 | P9: UPI | Q9: =TRIM(CLEAN(P9)) -> UPI | R9: Offline | S9: Not Returned | T9: 21:28 | U9: Weekday | V9: =TEXT(tblSales[[#This Row],[Invoice Date]],"mmm") -> Jan | W9: =MONTH(tblSales[[#This Row],[Invoice Date]]) -> 1 | X9: =YEAR(tblSales[[#This Row],[Invoice Date]]) -> 2025 | Y9: =TEXT(tblSales[[#This Row],[Invoice Date]],"mmm-yyyy") -> Jan-2025 | Z9: =_xlfn.XLOOKUP(tblSales[[#This Row],[Product_ID]],Products!$A:$A,Products!$C:$C,"Women Dresses") -> Men Jeans | AA9: =_xlfn.XLOOKUP(tblSales[[#This Row],[Product_ID]],Products!$A:$A,Products!$D:$D,"Unknown") -> Slim Fit | AB9: =_xlfn.XLOOKUP(tblSales[[#This Row],[Product_ID]],Products!$A:$A,Products!$E:$E,"Unknown") -> Metro Shoes | AC9: =_xlfn.XLOOKUP(tblSales[[#This Row],[Store_ID]],Stores!$A:$A,Stores!$B:$B,"Unknown") -> TrendMart Tirupati High Street | AD9: =_xlfn.XLOOKUP(tblSales[[#This Row],[Store_ID]],Stores!$A:$A,Stores!$E:$E,"Unknown") -> South Zone 3 | AE9: =_xlfn.XLOOKUP(tblSales[[#This Row],[Customer_ID]],Customers!$A:$A,Customers!$B:$B,"Unknown") -> Srinivas Prasad | AF9: =_xlfn.XLOOKUP(tblSales[[#This Row],[Customer_ID]],Customers!$A:$A,Customers!$J:$J,"Unknown") -> Silver | AG9: =_xlfn.XLOOKUP(tblSales[[#This Row],[Employee_ID]],Employees!$A:$A,Employees!$B:$B,"Unknown") -> Chandran Krishnan | AH9: =IF(MONTH(tblSales[[#This Row],[Invoice Date]])>=4,MONTH(tblSales[[#This Row],[Invoice Date]]),MONTH(tblSales[[#This Row],[Invoice Date]])+12) -> 13 | AI9: =DATE(YEAR(tblSales[[#This Row],[Invoice Date]]),MONTH(tblSales[[#This Row],[Invoice Date]]),1) -> 45658 | AJ9: =_xlfn.XLOOKUP(tblSales[[#This Row],[Product_ID]],Products!$A:$A,Products!$B:$B,"Unknown") -> Metro Shoes Slim Fit Wine | AK9: =IFERROR(tblSales[[#This Row],[Profit]]/tblSales[[#This Row],[Sales Amount]],0) -> 0.21535943 | AL9: =IF(tblSales[[#This Row],[Discount %]]<=5,"0-5%", IF(tblSales[[#This Row],[Discount %]]<=10,"5-10%", IF(tblSales[[#This Row],[Discount %]]<=15,"10-15%", IF(tblSales[[#This Row],[Discount %]]<=20,"15-20%","20%+")))) -> 0-5%
A10: INV100009 | B10: 45541 | C10: CUST0782 | D10: PRD0114 | E10: STR021 | F10: EMP0001 | G10: 5 | H10: 851.61 | I10: 5 | J10: 212.9 | K10: 5 | L10: 202.26 | M10: 4247.41 | N10: 2443 | O10: =(M10-N10-L10) -> 1602.15 | P10: Debit Card | Q10: =TRIM(CLEAN(P10)) -> Debit Card | R10: Offline | S10: Not Returned | T10: 19:05 | U10: Weekday | V10: =TEXT(tblSales[[#This Row],[Invoice Date]],"mmm") -> Sep | W10: =MONTH(tblSales[[#This Row],[Invoice Date]]) -> 9 | X10: =YEAR(tblSales[[#This Row],[Invoice Date]]) -> 2024 | Y10: =TEXT(tblSales[[#This Row],[Invoice Date]],"mmm-yyyy") -> Sep-2024 | Z10: =_xlfn.XLOOKUP(tblSales[[#This Row],[Product_ID]],Products!$A:$A,Products!$C:$C,"Women Dresses") -> Accessories | AA10: =_xlfn.XLOOKUP(tblSales[[#This Row],[Product_ID]],Products!$A:$A,Products!$D:$D,"Unknown") -> Sunglasses | AB10: =_xlfn.XLOOKUP(tblSales[[#This Row],[Product_ID]],Products!$A:$A,Products!$E:$E,"Unknown") -> Arrow | AC10: =_xlfn.XLOOKUP(tblSales[[#This Row],[Store_ID]],Stores!$A:$A,Stores!$B:$B,"Unknown") -> TrendMart Kozhikode Standard | AD10: =_xlfn.XLOOKUP(tblSales[[#This Row],[Store_ID]],Stores!$A:$A,Stores!$E:$E,"Unknown") -> South Zone 1 | AE10: =_xlfn.XLOOKUP(tblSales[[#This Row],[Customer_ID]],Customers!$A:$A,Customers!$B:$B,"Unknown") -> Rahul Yadav | AF10: =_xlfn.XLOOKUP(tblSales[[#This Row],[Customer_ID]],Customers!$A:$A,Customers!$J:$J,"Unknown") -> Gold | AG10: =_xlfn.XLOOKUP(tblSales[[#This Row],[Employee_ID]],Employees!$A:$A,Employees!$B:$B,"Unknown") -> Charulatha Kumar | AH10: =IF(MONTH(tblSales[[#This Row],[Invoice Date]])>=4,MONTH(tblSales[[#This Row],[Invoice Date]]),MONTH(tblSales[[#This Row],[Invoice Date]])+12) -> 9 | AI10: =DATE(YEAR(tblSales[[#This Row],[Invoice Date]]),MONTH(tblSales[[#This Row],[Invoice Date]]),1) -> 45536 | AJ10: =_xlfn.XLOOKUP(tblSales[[#This Row],[Product_ID]],Products!$A:$A,Products!$B:$B,"Unknown") -> Arrow Sunglasses Red | AK10: =IFERROR(tblSales[[#This Row],[Profit]]/tblSales[[#This Row],[Sales Amount]],0) -> 0.37720634 | AL10: =IF(tblSales[[#This Row],[Discount %]]<=5,"0-5%", IF(tblSales[[#This Row],[Discount %]]<=10,"5-10%", IF(tblSales[[#This Row],[Discount %]]<=15,"10-15%", IF(tblSales[[#This Row],[Discount %]]<=20,"15-20%","20%+")))) -> 0-5%
A11: INV100010 | B11: 45583 | C11: CUST0429 | D11: PRD0075 | E11: STR085 | F11: EMP0090 | G11: 1 | H11: 1041.15 | I11: 0 | J11: 0 | K11: 12 | L11: 124.94 | M11: 1166.09 | N11: 692.53 | O11: =(M11-N11-L11) -> 348.62 | P11: Credit Card | Q11: =TRIM(CLEAN(P11)) -> Credit Card | R11: Offline | S11: Not Returned | T11: 10:34 | U11: Weekday | V11: =TEXT(tblSales[[#This Row],[Invoice Date]],"mmm") -> Oct | W11: =MONTH(tblSales[[#This Row],[Invoice Date]]) -> 10 | X11: =YEAR(tblSales[[#This Row],[Invoice Date]]) -> 2024 | Y11: =TEXT(tblSales[[#This Row],[Invoice Date]],"mmm-yyyy") -> Oct-2024 | Z11: =_xlfn.XLOOKUP(tblSales[[#This Row],[Product_ID]],Products!$A:$A,Products!$C:$C,"Women Dresses") -> Women Jeans | AA11: =_xlfn.XLOOKUP(tblSales[[#This Row],[Product_ID]],Products!$A:$A,Products!$D:$D,"Unknown") -> Bootcut | AB11: =_xlfn.XLOOKUP(tblSales[[#This Row],[Product_ID]],Products!$A:$A,Products!$E:$E,"Unknown") -> Sonata | AC11: =_xlfn.XLOOKUP(tblSales[[#This Row],[Store_ID]],Stores!$A:$A,Stores!$B:$B,"Unknown") -> TrendMart Nizamabad Outlet | AD11: =_xlfn.XLOOKUP(tblSales[[#This Row],[Store_ID]],Stores!$A:$A,Stores!$E:$E,"Unknown") -> South Zone 2 | AE11: =_xlfn.XLOOKUP(tblSales[[#This Row],[Customer_ID]],Customers!$A:$A,Customers!$B:$B,"Unknown") -> Nandini Gopalakrishnan | AF11: =_xlfn.XLOOKUP(tblSales[[#This Row],[Customer_ID]],Customers!$A:$A,Customers!$J:$J,"Unknown") -> Regular | AG11: =_xlfn.XLOOKUP(tblSales[[#This Row],[Employee_ID]],Employees!$A:$A,Employees!$B:$B,"Unknown") -> Padma Gounder | AH11: =IF(MONTH(tblSales[[#This Row],[Invoice Date]])>=4,MONTH(tblSales[[#This Row],[Invoice Date]]),MONTH(tblSales[[#This Row],[Invoice Date]])+12) -> 10 | AI11: =DATE(YEAR(tblSales[[#This Row],[Invoice Date]]),MONTH(tblSales[[#This Row],[Invoice Date]]),1) -> 45566 | AJ11: =_xlfn.XLOOKUP(tblSales[[#This Row],[Product_ID]],Products!$A:$A,Products!$B:$B,"Unknown") -> Sonata Bootcut Navy Blue | AK11: =IFERROR(tblSales[[#This Row],[Profit]]/tblSales[[#This Row],[Sales Amount]],0) -> 0.29896492 | AL11: =IF(tblSales[[#This Row],[Discount %]]<=5,"0-5%", IF(tblSales[[#This Row],[Discount %]]<=10,"5-10%", IF(tblSales[[#This Row],[Discount %]]<=15,"10-15%", IF(tblSales[[#This Row],[Discount %]]<=20,"15-20%","20%+")))) -> 0-5%
A12: INV100011 | B12: 45677 | C12: CUST0162 | D12: PRD0117 | E12: STR004 | F12: EMP0258 | G12: 4 | H12: 1761.12 | I12: 10 | J12: 704.45 | K12: 12 | L12: 760.8 | M12: 7100.83 | N12: 5599.4 | O12: =(M12-N12-L12) -> 740.63 | P12: Credit Card | Q12: =TRIM(CLEAN(P12)) -> Credit Card | R12: Offline | S12: Not Returned | T12: 13:20 | U12: Weekday | V12: =TEXT(tblSales[[#This Row],[Invoice Date]],"mmm") -> Jan | W12: =MONTH(tblSales[[#This Row],[Invoice Date]]) -> 1 | X12: =YEAR(tblSales[[#This Row],[Invoice Date]]) -> 2025 | Y12: =TEXT(tblSales[[#This Row],[Invoice Date]],"mmm-yyyy") -> Jan-2025 | Z12: =_xlfn.XLOOKUP(tblSales[[#This Row],[Product_ID]],Products!$A:$A,Products!$C:$C,"Women Dresses") -> Women Dresses | AA12: =_xlfn.XLOOKUP(tblSales[[#This Row],[Product_ID]],Products!$A:$A,Products!$D:$D,"Unknown") -> Shirt Dress | AB12: =_xlfn.XLOOKUP(tblSales[[#This Row],[Product_ID]],Products!$A:$A,Products!$E:$E,"Unknown") -> Nike | AC12: =_xlfn.XLOOKUP(tblSales[[#This Row],[Store_ID]],Stores!$A:$A,Stores!$B:$B,"Unknown") -> TrendMart Kalaburagi Mall Kiosk | AD12: =_xlfn.XLOOKUP(tblSales[[#This Row],[Store_ID]],Stores!$A:$A,Stores!$E:$E,"Unknown") -> South Zone 2 | AE12: =_xlfn.XLOOKUP(tblSales[[#This Row],[Customer_ID]],Customers!$A:$A,Customers!$B:$B,"Unknown") -> Tanvi Balasubramaniam | AF12: =_xlfn.XLOOKUP(tblSales[[#This Row],[Customer_ID]],Customers!$A:$A,Customers!$J:$J,"Unknown") -> Silver | AG12: =_xlfn.XLOOKUP(tblSales[[#This Row],[Employee_ID]],Employees!$A:$A,Employees!$B:$B,"Unknown") -> Preethi Singh | AH12: =IF(MONTH(tblSales[[#This Row],[Invoice Date]])>=4,MONTH(tblSales[[#This Row],[Invoice Date]]),MONTH(tblSales[[#This Row],[Invoice Date]])+12) -> 13 | AI12: =DATE(YEAR(tblSales[[#This Row],[Invoice Date]]),MONTH(tblSales[[#This Row],[Invoice Date]]),1) -> 45658 | AJ12: =_xlfn.XLOOKUP(tblSales[[#This Row],[Product_ID]],Products!$A:$A,Products!$B:$B,"Unknown") -> Nike Shirt Dress Peach | AK12: =IFERROR(tblSales[[#This Row],[Profit]]/tblSales[[#This Row],[Sales Amount]],0) -> 0.10430189 | AL12: =IF(tblSales[[#This Row],[Discount %]]<=5,"0-5%", IF(tblSales[[#This Row],[Discount %]]<=10,"5-10%", IF(tblSales[[#This Row],[Discount %]]<=15,"10-15%", IF(tblSales[[#This Row],[Discount %]]<=20,"15-20%","20%+")))) -> 5-10%
A13: INV100012 | B13: 45736 | C13: CUST0794 | D13: PRD0078 | E13: STR068 | F13: EMP0204 | G13: 1 | H13: 1019.42 | I13: 5 | J13: 50.97 | K13: 12 | L13: 116.21 | M13: 1084.66 | N13: 828.44 | O13: =(M13-N13-L13) -> 140.01 | P13: UPI | Q13: =TRIM(CLEAN(P13)) -> UPI | R13: Online | S13: Not Returned | T13: 18:28 | U13: Weekday | V13: =TEXT(tblSales[[#This Row],[Invoice Date]],"mmm") -> Mar | W13: =MONTH(tblSales[[#This Row],[Invoice Date]]) -> 3 | X13: =YEAR(tblSales[[#This Row],[Invoice Date]]) -> 2025 | Y13: =TEXT(tblSales[[#This Row],[Invoice Date]],"mmm-yyyy") -> Mar-2025 | Z13: =_xlfn.XLOOKUP(tblSales[[#This Row],[Product_ID]],Products!$A:$A,Products!$C:$C,"Women Dresses") -> Men Jeans | AA13: =_xlfn.XLOOKUP(tblSales[[#This Row],[Product_ID]],Products!$A:$A,Products!$D:$D,"Unknown") -> Regular Fit | AB13: =_xlfn.XLOOKUP(tblSales[[#This Row],[Product_ID]],Products!$A:$A,Products!$E:$E,"Unknown") -> Metro Shoes | AC13: =_xlfn.XLOOKUP(tblSales[[#This Row],[Store_ID]],Stores!$A:$A,Stores!$B:$B,"Unknown") -> TrendMart Madurai Mall Kiosk | AD13: =_xlfn.XLOOKUP(tblSales[[#This Row],[Store_ID]],Stores!$A:$A,Stores!$E:$E,"Unknown") -> South Zone 1 | AE13: =_xlfn.XLOOKUP(tblSales[[#This Row],[Customer_ID]],Customers!$A:$A,Customers!$B:$B,"Unknown") -> Rahul Gupta | AF13: =_xlfn.XLOOKUP(tblSales[[#This Row],[Customer_ID]],Customers!$A:$A,Customers!$J:$J,"Unknown") -> Silver | AG13: =_xlfn.XLOOKUP(tblSales[[#This Row],[Employee_ID]],Employees!$A:$A,Employees!$B:$B,"Unknown") -> Rahul Krishnan | AH13: =IF(MONTH(tblSales[[#This Row],[Invoice Date]])>=4,MONTH(tblSales[[#This Row],[Invoice Date]]),MONTH(tblSales[[#This Row],[Invoice Date]])+12) -> 15 | AI13: =DATE(YEAR(tblSales[[#This Row],[Invoice Date]]),MONTH(tblSales[[#This Row],[Invoice Date]]),1) -> 45717 | AJ13: =_xlfn.XLOOKUP(tblSales[[#This Row],[Product_ID]],Products!$A:$A,Products!$B:$B,"Unknown") -> Metro Shoes Regular Fit Charcoal | AK13: =IFERROR(tblSales[[#This Row],[Profit]]/tblSales[[#This Row],[Sales Amount]],0) -> 0.12908192 | AL13: =IF(tblSales[[#This Row],[Discount %]]<=5,"0-5%", IF(tblSales[[#This Row],[Discount %]]<=10,"5-10%", IF(tblSales[[#This Row],[Discount %]]<=15,"10-15%", IF(tblSales[[#This Row],[Discount %]]<=20,"15-20%","20%+")))) -> 0-5%
... A68: INV100067 | B68: 45622 | C68: CUST0746 | D68: PRD0019 | E68: STR100 | F68: EMP0141 | G68: 1 | H68: 640.02 | I68: 25 | J68: 160 | K68: 5 | L68: 24 | M68: 504.02 | N68: 413.39 | O68: =(M68-N68-L68) -> 66.63 | P68: Cash | Q68: =TRIM(CLEAN(P68)) -> Cash | R68: Online | S68: Not Returned | T68: 16:30 | U68: Weekday | V68: =TEXT(tblSales[[#This Row],[Invoice Date]],"mmm") -> Nov | W68: =MONTH(tblSales[[#This Row],[Invoice Date]]) -> 11 | X68: =YEAR(tblSales[[#This Row],[Invoice Date]]) -> 2024 | Y68: =TEXT(tblSales[[#This Row],[Invoice Date]],"mmm-yyyy") -> Nov-2024 | Z68: =_xlfn.XLOOKUP(tblSales[[#This Row],[Product_ID]],Products!$A:$A,Products!$C:$C,"Women Dresses") -> Kids Wear | AA68: =_xlfn.XLOOKUP(tblSales[[#This Row],[Product_ID]],Products!$A:$A,Products!$D:$D,"Unknown") -> Kids T-Shirt | AB68: =_xlfn.XLOOKUP(tblSales[[#This Row],[Product_ID]],Products!$A:$A,Products!$E:$E,"Unknown") -> Jack & Jones | AC68: =_xlfn.XLOOKUP(tblSales[[#This Row],[Store_ID]],Stores!$A:$A,Stores!$B:$B,"Unknown") -> TrendMart Hubballi Standard | AD68: =_xlfn.XLOOKUP(tblSales[[#This Row],[Store_ID]],Stores!$A:$A,Stores!$E:$E,"Unknown") -> South Zone 2 | AE68: =_xlfn.XLOOKUP(tblSales[[#This Row],[Customer_ID]],Customers!$A:$A,Customers!$B:$B,"Unknown") -> Pandian Venkatesan | AF68: =_xlfn.XLOOKUP(tblSales[[#This Row],[Customer_ID]],Customers!$A:$A,Customers!$J:$J,"Unknown") -> Silver | AG68: =_xlfn.XLOOKUP(tblSales[[#This Row],[Employee_ID]],Employees!$A:$A,Employees!$B:$B,"Unknown") -> Dhruv Mishra | AH68: =IF(MONTH(tblSales[[#This Row],[Invoice Date]])>=4,MONTH(tblSales[[#This Row],[Invoice Date]]),MONTH(tblSales[[#This Row],[Invoice Date]])+12) -> 11 | AI68: =DATE(YEAR(tblSales[[#This Row],[Invoice Date]]),MONTH(tblSales[[#This Row],[Invoice Date]]),1) -> 45597 | AJ68: =_xlfn.XLOOKUP(tblSales[[#This Row],[Product_ID]],Products!$A:$A,Products!$B:$B,"Unknown") -> Sonata Girls Frock Cream | AK68: =IFERROR(tblSales[[#This Row],[Profit]]/tblSales[[#This Row],[Sales Amount]],0) -> 0.13219714 | AL68: =IF(tblSales[[#This Row],[Discount %]]<=5,"0-5%", IF(tblSales[[#This Row],[Discount %]]<=10,"5-10%", IF(tblSales[[#This Row],[Discount %]]<=15,"10-15%", IF(tblSales[[#This Row],[Discount %]]<=20,"15-20%","20%+")))) -> 20%+
A69: INV100068 | B69: 45541 | C69: CUST0583 | D69: PRD0134 | E69: STR112 | F69: EMP0203 | G69: 0 | H69: 924.29 | I69: 0 | J69: 0 | K69: 5 | L69: 0 | M69: 0 | N69: 0 | O69: 0 | P69: EMI | Q69: =TRIM(CLEAN(P69)) -> EMI | R69: Online | S69: Not Returned | T69: 18:42 | U69: Weekday | V69: =TEXT(tblSales[[#This Row],[Invoice Date]],"mmm") -> Sep | W69: =MONTH(tblSales[[#This Row],[Invoice Date]]) -> 9 | X69: =YEAR(tblSales[[#This Row],[Invoice Date]]) -> 2024 | Y69: =TEXT(tblSales[[#This Row],[Invoice Date]],"mmm-yyyy") -> Sep-2024 | Z69: =_xlfn.XLOOKUP(tblSales[[#This Row],[Product_ID]],Products!$A:$A,Products!$C:$C,"Women Dresses") -> Women Dresses | AA69: =_xlfn.XLOOKUP(tblSales[[#This Row],[Product_ID]],Products!$A:$A,Products!$D:$D,"Unknown") -> Maxi Dress | AB69: =_xlfn.XLOOKUP(tblSales[[#This Row],[Product_ID]],Products!$A:$A,Products!$E:$E,"Unknown") -> Jack & Jones | AC69: =_xlfn.XLOOKUP(tblSales[[#This Row],[Store_ID]],Stores!$A:$A,Stores!$B:$B,"Unknown") -> TrendMart Guntur Outlet | AD69: =_xlfn.XLOOKUP(tblSales[[#This Row],[Store_ID]],Stores!$A:$A,Stores!$E:$E,"Unknown") -> South Zone 3 | AE69: =_xlfn.XLOOKUP(tblSales[[#This Row],[Customer_ID]],Customers!$A:$A,Customers!$B:$B,"Unknown") -> Feroz Naicker | AF69: =_xlfn.XLOOKUP(tblSales[[#This Row],[Customer_ID]],Customers!$A:$A,Customers!$J:$J,"Unknown") -> Silver | AG69: =_xlfn.XLOOKUP(tblSales[[#This Row],[Employee_ID]],Employees!$A:$A,Employees!$B:$B,"Unknown") -> Rani Mishra | AH69: =IF(MONTH(tblSales[[#This Row],[Invoice Date]])>=4,MONTH(tblSales[[#This Row],[Invoice Date]]),MONTH(tblSales[[#This Row],[Invoice Date]])+12) -> 9 | AI69: =DATE(YEAR(tblSales[[#This Row],[Invoice Date]]),MONTH(tblSales[[#This Row],[Invoice Date]]),1) -> 45536 | AJ69: =_xlfn.XLOOKUP(tblSales[[#This Row],[Product_ID]],Products!$A:$A,Products!$B:$B,"Unknown") -> Jack & Jones Maxi Dress Maroon | AK69: =IFERROR(tblSales[[#This Row],[Profit]]/tblSales[[#This Row],[Sales Amount]],0) -> 0 | AL69: =IF(tblSales[[#This Row],[Discount %]]<=5,"0-5%", IF(tblSales[[#This Row],[Discount %]]<=10,"5-10%", IF(tblSales[[#This Row],[Discount %]]<=15,"10-15%", IF(tblSales[[#This Row],[Discount %]]<=20,"15-20%","20%+")))) -> 0-5%
A70: INV100069 | B70: 45622 | C70: CUST0422 | D70: PRD0117 | E70: STR088 | F70: EMP0204 | G70: 2 | H70: 1714.04 | I70: 10 | J70: 342.81 | K70: 12 | L70: 370.23 | M70: 3455.5 | N70: 2799.7 | O70: =(M70-N70-L70) -> 285.57 | P70: Cash | Q70: =TRIM(CLEAN(P70)) -> Cash | R70: Online | S70: Not Returned | T70: 19:44 | U70: Weekday | V70: =TEXT(tblSales[[#This Row],[Invoice Date]],"mmm") -> Nov | W70: =MONTH(tblSales[[#This Row],[Invoice Date]]) -> 11 | X70: =YEAR(tblSales[[#This Row],[Invoice Date]]) -> 2024 | Y70: =TEXT(tblSales[[#This Row],[Invoice Date]],"mmm-yyyy") -> Nov-2024 | Z70: =_xlfn.XLOOKUP(tblSales[[#This Row],[Product_ID]],Products!$A:$A,Products!$C:$C,"Women Dresses") -> Women Dresses | AA70: =_xlfn.XLOOKUP(tblSales[[#This Row],[Product_ID]],Products!$A:$A,Products!$D:$D,"Unknown") -> Shirt Dress | AB70: =_xlfn.XLOOKUP(tblSales[[#This Row],[Product_ID]],Products!$A:$A,Products!$E:$E,"Unknown") -> Nike | AC70: =_xlfn.XLOOKUP(tblSales[[#This Row],[Store_ID]],Stores!$A:$A,Stores!$B:$B,"Unknown") -> TrendMart Warangal High Street | AD70: =_xlfn.XLOOKUP(tblSales[[#This Row],[Store_ID]],Stores!$A:$A,Stores!$E:$E,"Unknown") -> South Zone 2 | AE70: =_xlfn.XLOOKUP(tblSales[[#This Row],[Customer_ID]],Customers!$A:$A,Customers!$B:$B,"Unknown") -> Malathi Shetty | AF70: =_xlfn.XLOOKUP(tblSales[[#This Row],[Customer_ID]],Customers!$A:$A,Customers!$J:$J,"Unknown") -> Silver | AG70: =_xlfn.XLOOKUP(tblSales[[#This Row],[Employee_ID]],Employees!$A:$A,Employees!$B:$B,"Unknown") -> Rahul Krishnan | AH70: =IF(MONTH(tblSales[[#This Row],[Invoice Date]])>=4,MONTH(tblSales[[#This Row],[Invoice Date]]),MONTH(tblSales[[#This Row],[Invoice Date]])+12) -> 11 | AI70: =DATE(YEAR(tblSales[[#This Row],[Invoice Date]]),MONTH(tblSales[[#This Row],[Invoice Date]]),1) -> 45597 | AJ70: =_xlfn.XLOOKUP(tblSales[[#This Row],[Product_ID]],Products!$A:$A,Products!$B:$B,"Unknown") -> Nike Shirt Dress Peach | AK70: =IFERROR(tblSales[[#This Row],[Profit]]/tblSales[[#This Row],[Sales Amount]],0) -> 0.082642165 | AL70: =IF(tblSales[[#This Row],[Discount %]]<=5,"0-5%", IF(tblSales[[#This Row],[Discount %]]<=10,"5-10%", IF(tblSales[[#This Row],[Discount %]]<=15,"10-15%", IF(tblSales[[#This Row],[Discount %]]<=20,"15-20%","20%+")))) -> 5-10%
A71: INV100070 | B71: 45620 | C71: CUST0613 | D71: PRD0116 | E71: STR096 | F71: EMP0215 | G71: 3 | H71: 1579.45 | I71: 15 | J71: 710.75 | K71: 12 | L71: 483.31 | M71: 4510.91 | N71: 3146.13 | O71: =(M71-N71-L71) -> 881.47 | P71: Debit Card | Q71: =TRIM(CLEAN(P71)) -> Debit Card | R71: Online | S71: Not Returned | T71: 21:51 | U71: Weekend | V71: =TEXT(tblSales[[#This Row],[Invoice Date]],"mmm") -> Nov | W71: =MONTH(tblSales[[#This Row],[Invoice Date]]) -> 11 | X71: =YEAR(tblSales[[#This Row],[Invoice Date]]) -> 2024 | Y71: =TEXT(tblSales[[#This Row],[Invoice Date]],"mmm-yyyy") -> Nov-2024 | Z71: =_xlfn.XLOOKUP(tblSales[[#This Row],[Product_ID]],Products!$A:$A,Products!$C:$C,"Women Dresses") -> Women Jeans | AA71: =_xlfn.XLOOKUP(tblSales[[#This Row],[Product_ID]],Products!$A:$A,Products!$D:$D,"Unknown") -> Bootcut | AB71: =_xlfn.XLOOKUP(tblSales[[#This Row],[Product_ID]],Products!$A:$A,Products!$E:$E,"Unknown") -> Woodland | AC71: =_xlfn.XLOOKUP(tblSales[[#This Row],[Store_ID]],Stores!$A:$A,Stores!$B:$B,"Unknown") -> TrendMart Mangaluru Mall Kiosk | AD71: =_xlfn.XLOOKUP(tblSales[[#This Row],[Store_ID]],Stores!$A:$A,Stores!$E:$E,"Unknown") -> South Zone 2 | AE71: =_xlfn.XLOOKUP(tblSales[[#This Row],[Customer_ID]],Customers!$A:$A,Customers!$B:$B,"Unknown") -> Usha Krishnan | AF71: =_xlfn.XLOOKUP(tblSales[[#This Row],[Customer_ID]],Customers!$A:$A,Customers!$J:$J,"Unknown") -> Gold | AG71: =_xlfn.XLOOKUP(tblSales[[#This Row],[Employee_ID]],Employees!$A:$A,Employees!$B:$B,"Unknown") -> Praveen Gupta | AH71: =IF(MONTH(tblSales[[#This Row],[Invoice Date]])>=4,MONTH(tblSales[[#This Row],[Invoice Date]]),MONTH(tblSales[[#This Row],[Invoice Date]])+12) -> 11 | AI71: =DATE(YEAR(tblSales[[#This Row],[Invoice Date]]),MONTH(tblSales[[#This Row],[Invoice Date]]),1) -> 45597 | AJ71: =_xlfn.XLOOKUP(tblSales[[#This Row],[Product_ID]],Products!$A:$A,Products!$B:$B,"Unknown") -> Woodland Bootcut Peach | AK71: =IFERROR(tblSales[[#This Row],[Profit]]/tblSales[[#This Row],[Sales Amount]],0) -> 0.19540847 | AL71: =IF(tblSales[[#This Row],[Discount %]]<=5,"0-5%", IF(tblSales[[#This Row],[Discount %]]<=10,"5-10%", IF(tblSales[[#This Row],[Discount %]]<=15,"10-15%", IF(tblSales[[#This Row],[Discount %]]<=20,"15-20%","20%+")))) -> 10-15%
A72: INV100071 | B72: 45426 | C72: CUST0131 | D72: PRD0115 | E72: STR016 | F72: EMP0258 | G72: 1 | H72: 1632.35 | I72: 5 | J72: 81.62 | K72: 12 | L72: 186.09 | M72: 1736.82 | N72: 1140.9 | O72: =(M72-N72-L72) -> 409.83 | P72: Net Banking | Q72: =TRIM(CLEAN(P72)) -> Net Banking | R72: Online | S72: Not Returned | T72: 19:45 | U72: Weekday | V72: =TEXT(tblSales[[#This Row],[Invoice Date]],"mmm") -> May | W72: =MONTH(tblSales[[#This Row],[Invoice Date]]) -> 5 | X72: =YEAR(tblSales[[#This Row],[Invoice Date]]) -> 2024 | Y72: =TEXT(tblSales[[#This Row],[Invoice Date]],"mmm-yyyy") -> May-2024 | Z72: =_xlfn.XLOOKUP(tblSales[[#This Row],[Product_ID]],Products!$A:$A,Products!$C:$C,"Women Dresses") -> Women Dresses | AA72: =_xlfn.XLOOKUP(tblSales[[#This Row],[Product_ID]],Products!$A:$A,Products!$D:$D,"Unknown") -> Bodycon Dress | AB72: =_xlfn.XLOOKUP(tblSales[[#This Row],[Product_ID]],Products!$A:$A,Products!$E:$E,"Unknown") -> Reebok | AC72: =_xlfn.XLOOKUP(tblSales[[#This Row],[Store_ID]],Stores!$A:$A,Stores!$B:$B,"Unknown") -> TrendMart Visakhapatnam Flagship | AD72: =_xlfn.XLOOKUP(tblSales[[#This Row],[Store_ID]],Stores!$A:$A,Stores!$E:$E,"Unknown") -> South Zone 3 | AE72: =_xlfn.XLOOKUP(tblSales[[#This Row],[Customer_ID]],Customers!$A:$A,Customers!$B:$B,"Unknown") -> Jyothi Achari | AF72: =_xlfn.XLOOKUP(tblSales[[#This Row],[Customer_ID]],Customers!$A:$A,Customers!$J:$J,"Unknown") -> Regular | AG72: =_xlfn.XLOOKUP(tblSales[[#This Row],[Employee_ID]],Employees!$A:$A,Employees!$B:$B,"Unknown") -> Preethi Singh | AH72: =IF(MONTH(tblSales[[#This Row],[Invoice Date]])>=4,MONTH(tblSales[[#This Row],[Invoice Date]]),MONTH(tblSales[[#This Row],[Invoice Date]])+12) -> 5 | AI72: =DATE(YEAR(tblSales[[#This Row],[Invoice Date]]),MONTH(tblSales[[#This Row],[Invoice Date]]),1) -> 45413 | AJ72: =_xlfn.XLOOKUP(tblSales[[#This Row],[Product_ID]],Products!$A:$A,Products!$B:$B,"Unknown") -> Reebok Bodycon Dress Navy Blue | AK72: =IFERROR(tblSales[[#This Row],[Profit]]/tblSales[[#This Row],[Sales Amount]],0) -> 0.23596573 | AL72: =IF(tblSales[[#This Row],[Discount %]]<=5,"0-5%", IF(tblSales[[#This Row],[Discount %]]<=10,"5-10%", IF(tblSales[[#This Row],[Discount %]]<=15,"10-15%", IF(tblSales[[#This Row],[Discount %]]<=20,"15-20%","20%+")))) -> 0-5%
A73: INV100072 | B73: 45586 | C73: CUST0338 | D73: PRD0034 | E73: STR074 | F73: EMP0149 | G73: 0 | H73: 413.58 | I73: 0 | J73: 0 | K73: 5 | L73: 0 | M73: 0 | N73: 0 | O73: 0 | P73: EMI | Q73: =TRIM(CLEAN(P73)) -> EMI | R73: Online | S73: Not Returned | T73: 21:44 | U73: Weekday | V73: =TEXT(tblSales[[#This Row],[Invoice Date]],"mmm") -> Oct | W73: =MONTH(tblSales[[#This Row],[Invoice Date]]) -> 10 | X73: =YEAR(tblSales[[#This Row],[Invoice Date]]) -> 2024 | Y73: =TEXT(tblSales[[#This Row],[Invoice Date]],"mmm-yyyy") -> Oct-2024 | Z73: =_xlfn.XLOOKUP(tblSales[[#This Row],[Product_ID]],Products!$A:$A,Products!$C:$C,"Women Dresses") -> Belts | AA73: =_xlfn.XLOOKUP(tblSales[[#This Row],[Product_ID]],Products!$A:$A,Products!$D:$D,"Unknown") -> Casual Belt | AB73: =_xlfn.XLOOKUP(tblSales[[#This Row],[Product_ID]],Products!$A:$A,Products!$E:$E,"Unknown") -> Nike | AC73: =_xlfn.XLOOKUP(tblSales[[#This Row],[Store_ID]],Stores!$A:$A,Stores!$B:$B,"Unknown") -> TrendMart Kurnool High Street | AD73: =_xlfn.XLOOKUP(tblSales[[#This Row],[Store_ID]],Stores!$A:$A,Stores!$E:$E,"Unknown") -> South Zone 3 | AE73: =_xlfn.XLOOKUP(tblSales[[#This Row],[Customer_ID]],Customers!$A:$A,Customers!$B:$B,"Unknown") -> Vijay Prasad | AF73: =_xlfn.XLOOKUP(tblSales[[#This Row],[Customer_ID]],Customers!$A:$A,Customers!$J:$J,"Unknown") -> Silver | AG73: =_xlfn.XLOOKUP(tblSales[[#This Row],[Employee_ID]],Employees!$A:$A,Employees!$B:$B,"Unknown") -> Vasanthi Kamath | AH73: =IF(MONTH(tblSales[[#This Row],[Invoice Date]])>=4,MONTH(tblSales[[#This Row],[Invoice Date]]),MONTH(tblSales[[#This Row],[Invoice Date]])+12) -> 10 | AI73: =DATE(YEAR(tblSales[[#This Row],[Invoice Date]]),MONTH(tblSales[[#This Row],[Invoice Date]]),1) -> 45566 | AJ73: =_xlfn.XLOOKUP(tblSales[[#This Row],[Product_ID]],Products!$A:$A,Products!$B:$B,"Unknown") -> Nike Casual Belt Olive | AK73: =IFERROR(tblSales[[#This Row],[Profit]]/tblSales[[#This Row],[Sales Amount]],0) -> 0 | AL73: =IF(tblSales[[#This Row],[Discount %]]<=5,"0-5%", IF(tblSales[[#This Row],[Discount %]]<=10,"5-10%", IF(tblSales[[#This Row],[Discount %]]<=15,"10-15%", IF(tblSales[[#This Row],[Discount %]]<=20,"15-20%","20%+")))) -> 0-5%
A74: INV100073 | B74: 45693 | C74: CUST0721 | D74: PRD0082 | E74: STR110 | F74: EMP0141 | G74: 3 | H74: 2846.44 | I74: 5 | J74: 426.97 | K74: 12 | L74: 973.48 | M74: 9085.83 | N74: 6454.02 | O74: =(M74-N74-L74) -> 1658.33 | P74: Debit Card | Q74: =TRIM(CLEAN(P74)) -> Debit Card | R74: Online | S74: Not Returned | T74: 21:32 | U74: Weekday | V74: =TEXT(tblSales[[#This Row],[Invoice Date]],"mmm") -> Feb | W74: =MONTH(tblSales[[#This Row],[Invoice Date]]) -> 2 | X74: =YEAR(tblSales[[#This Row],[Invoice Date]]) -> 2025 | Y74: =TEXT(tblSales[[#This Row],[Invoice Date]],"mmm-yyyy") -> Feb-2025 | Z74: =_xlfn.XLOOKUP(tblSales[[#This Row],[Product_ID]],Products!$A:$A,Products!$C:$C,"Women Dresses") -> Handbags | AA74: =_xlfn.XLOOKUP(tblSales[[#This Row],[Product_ID]],Products!$A:$A,Products!$D:$D,"Unknown") -> Sling Bag | AB74: =_xlfn.XLOOKUP(tblSales[[#This Row],[Product_ID]],Products!$A:$A,Products!$E:$E,"Unknown") -> Libas | AC74: =_xlfn.XLOOKUP(tblSales[[#This Row],[Store_ID]],Stores!$A:$A,Stores!$B:$B,"Unknown") -> TrendMart Thoothukudi Outlet | AD74: =_xlfn.XLOOKUP(tblSales[[#This Row],[Store_ID]],Stores!$A:$A,Stores!$E:$E,"Unknown") -> South Zone 1 | AE74: =_xlfn.XLOOKUP(tblSales[[#This Row],[Customer_ID]],Customers!$A:$A,Customers!$B:$B,"Unknown") -> Kavya Singh | AF74: =_xlfn.XLOOKUP(tblSales[[#This Row],[Customer_ID]],Customers!$A:$A,Customers!$J:$J,"Unknown") -> Regular | AG74: =_xlfn.XLOOKUP(tblSales[[#This Row],[Employee_ID]],Employees!$A:$A,Employees!$B:$B,"Unknown") -> Dhruv Mishra | AH74: =IF(MONTH(tblSales[[#This Row],[Invoice Date]])>=4,MONTH(tblSales[[#This Row],[Invoice Date]]),MONTH(tblSales[[#This Row],[Invoice Date]])+12) -> 14 | AI74: =DATE(YEAR(tblSales[[#This Row],[Invoice Date]]),MONTH(tblSales[[#This Row],[Invoice Date]]),1) -> 45689 | AJ74: =_xlfn.XLOOKUP(tblSales[[#This Row],[Product_ID]],Products!$A:$A,Products!$B:$B,"Unknown") -> Libas Sling Bag Green | AK74: =IFERROR(tblSales[[#This Row],[Profit]]/tblSales[[#This Row],[Sales Amount]],0) -> 0.18251827 | AL74: =IF(tblSales[[#This Row],[Discount %]]<=5,"0-5%", IF(tblSales[[#This Row],[Discount %]]<=10,"5-10%", IF(tblSales[[#This Row],[Discount %]]<=15,"10-15%", IF(tblSales[[#This Row],[Discount %]]<=20,"15-20%","20%+")))) -> 0-5%
A75: INV100074 | B75: 45399 | C75: CUST0210 | D75: PRD0075 | E75: STR055 | F75: EMP0285 | G75: 1 | H75: 1011.81 | I75: 30 | J75: 303.54 | K75: 12 | L75: 84.99 | M75: 793.26 | N75: 692.53 | O75: =(M75-N75-L75) -> 15.74 | P75: UPI | Q75: =TRIM(CLEAN(P75)) -> UPI | R75: Offline | S75: Not Returned | T75: 16:33 | U75: Weekday | V75: =TEXT(tblSales[[#This Row],[Invoice Date]],"mmm") -> Apr | W75: =MONTH(tblSales[[#This Row],[Invoice Date]]) -> 4 | X75: =YEAR(tblSales[[#This Row],[Invoice Date]]) -> 2024 | Y75: =TEXT(tblSales[[#This Row],[Invoice Date]],"mmm-yyyy") -> Apr-2024 | Z75: =_xlfn.XLOOKUP(tblSales[[#This Row],[Product_ID]],Products!$A:$A,Products!$C:$C,"Women Dresses") -> Women Jeans | AA75: =_xlfn.XLOOKUP(tblSales[[#This Row],[Product_ID]],Products!$A:$A,Products!$D:$D,"Unknown") -> Bootcut | AB75: =_xlfn.XLOOKUP(tblSales[[#This Row],[Product_ID]],Products!$A:$A,Products!$E:$E,"Unknown") -> Sonata | AC75: =_xlfn.XLOOKUP(tblSales[[#This Row],[Store_ID]],Stores!$A:$A,Stores!$B:$B,"Unknown") -> TrendMart Nellore High Street | AD75: =_xlfn.XLOOKUP(tblSales[[#This Row],[Store_ID]],Stores!$A:$A,Stores!$E:$E,"Unknown") -> South Zone 3 | AE75: =_xlfn.XLOOKUP(tblSales[[#This Row],[Customer_ID]],Customers!$A:$A,Customers!$B:$B,"Unknown") -> Priya Pandian | AF75: =_xlfn.XLOOKUP(tblSales[[#This Row],[Customer_ID]],Customers!$A:$A,Customers!$J:$J,"Unknown") -> Regular | AG75: =_xlfn.XLOOKUP(tblSales[[#This Row],[Employee_ID]],Employees!$A:$A,Employees!$B:$B,"Unknown") -> Chandran Krishnan | AH75: =IF(MONTH(tblSales[[#This Row],[Invoice Date]])>=4,MONTH(tblSales[[#This Row],[Invoice Date]]),MONTH(tblSales[[#This Row],[Invoice Date]])+12) -> 4 | AI75: =DATE(YEAR(tblSales[[#This Row],[Invoice Date]]),MONTH(tblSales[[#This Row],[Invoice Date]]),1) -> 45383 | AJ75: =_xlfn.XLOOKUP(tblSales[[#This Row],[Product_ID]],Products!$A:$A,Products!$B:$B,"Unknown") -> Sonata Bootcut Navy Blue | AK75: =IFERROR(tblSales[[#This Row],[Profit]]/tblSales[[#This Row],[Sales Amount]],0) -> 0.01984217 | AL75: =IF(tblSales[[#This Row],[Discount %]]<=5,"0-5%", IF(tblSales[[#This Row],[Discount %]]<=10,"5-10%", IF(tblSales[[#This Row],[Discount %]]<=15,"10-15%", IF(tblSales[[#This Row],[Discount %]]<=20,"15-20%","20%+")))) -> 20%+
A76: INV100075 | B76: 45620 | C76: CUST0658 | D76: PRD0203 | E76: STR045 | F76: EMP0255 | G76: 5 | H76: 1268.61 | I76: 15 | J76: 951.46 | K76: 12 | L76: 646.99 | M76: 6038.58 | N76: 4573.6 | O76: =(M76-N76-L76) -> 817.99 | P76: Debit Card | Q76: =TRIM(CLEAN(P76)) -> Debit Card | R76: Offline | S76: Not Returned | T76: 19:17 | U76: Weekend | V76: =TEXT(tblSales[[#This Row],[Invoice Date]],"mmm") -> Nov | W76: =MONTH(tblSales[[#This Row],[Invoice Date]]) -> 11 | X76: =YEAR(tblSales[[#This Row],[Invoice Date]]) -> 2024 | Y76: =TEXT(tblSales[[#This Row],[Invoice Date]],"mmm-yyyy") -> Nov-2024 | Z76: =_xlfn.XLOOKUP(tblSales[[#This Row],[Product_ID]],Products!$A:$A,Products!$C:$C,"Women Dresses") -> Sportswear | AA76: =_xlfn.XLOOKUP(tblSales[[#This Row],[Product_ID]],Products!$A:$A,Products!$D:$D,"Unknown") -> Sports T-Shirt | AB76: =_xlfn.XLOOKUP(tblSales[[#This Row],[Product_ID]],Products!$A:$A,Products!$E:$E,"Unknown") -> Liberty | AC76: =_xlfn.XLOOKUP(tblSales[[#This Row],[Store_ID]],Stores!$A:$A,Stores!$B:$B,"Unknown") -> TrendMart Khammam Standard | AD76: =_xlfn.XLOOKUP(tblSales[[#This Row],[Store_ID]],Stores!$A:$A,Stores!$E:$E,"Unknown") -> South Zone 2 | AE76: =_xlfn.XLOOKUP(tblSales[[#This Row],[Customer_ID]],Customers!$A:$A,Customers!$B:$B,"Unknown") -> Kiran Gupta | AF76: =_xlfn.XLOOKUP(tblSales[[#This Row],[Customer_ID]],Customers!$A:$A,Customers!$J:$J,"Unknown") -> Gold | AG76: =_xlfn.XLOOKUP(tblSales[[#This Row],[Employee_ID]],Employees!$A:$A,Employees!$B:$B,"Unknown") -> Venkat Sharma | AH76: =IF(MONTH(tblSales[[#This Row],[Invoice Date]])>=4,MONTH(tblSales[[#This Row],[Invoice Date]]),MONTH(tblSales[[#This Row],[Invoice Date]])+12) -> 11 | AI76: =DATE(YEAR(tblSales[[#This Row],[Invoice Date]]),MONTH(tblSales[[#This Row],[Invoice Date]]),1) -> 45597 | AJ76: =_xlfn.XLOOKUP(tblSales[[#This Row],[Product_ID]],Products!$A:$A,Products!$B:$B,"Unknown") -> Liberty Sports T-Shirt Peach | AK76: =IFERROR(tblSales[[#This Row],[Profit]]/tblSales[[#This Row],[Sales Amount]],0) -> 0.13546065 | AL76: =IF(tblSales[[#This Row],[Discount %]]<=5,"0-5%", IF(tblSales[[#This Row],[Discount %]]<=10,"5-10%", IF(tblSales[[#This Row],[Discount %]]<=15,"10-15%", IF(tblSales[[#This Row],[Discount %]]<=20,"15-20%","20%+")))) -> 10-15%
A77: INV100076 | B77: 45633 | C77: CUST0636 | D77: PRD0022 | E77: STR104 | F77: EMP0086 | G77: 1 | H77: 1323.12 | I77: 0 | J77: 0 | K77: 12 | L77: 158.77 | M77: 1481.89 | N77: 767.83 | O77: =(M77-N77-L77) -> 555.29 | P77: Credit Card | Q77: =TRIM(CLEAN(P77)) -> Credit Card | R77: Offline | S77: Not Returned | T77: 11:24 | U77: Weekend | V77: =TEXT(tblSales[[#This Row],[Invoice Date]],"mmm") -> Dec | W77: =MONTH(tblSales[[#This Row],[Invoice Date]]) -> 12 | X77: =YEAR(tblSales[[#This Row],[Invoice Date]]) -> 2024 | Y77: =TEXT(tblSales[[#This Row],[Invoice Date]],"mmm-yyyy") -> Dec-2024 | Z77: =_xlfn.XLOOKUP(tblSales[[#This Row],[Product_ID]],Products!$A:$A,Products!$C:$C,"Women Dresses") -> Women Jeans | AA77: =_xlfn.XLOOKUP(tblSales[[#This Row],[Product_ID]],Products!$A:$A,Products!$D:$D,"Unknown") -> Skinny Fit | AB77: =_xlfn.XLOOKUP(tblSales[[#This Row],[Product_ID]],Products!$A:$A,Products!$E:$E,"Unknown") -> Being Human | AC77: =_xlfn.XLOOKUP(tblSales[[#This Row],[Store_ID]],Stores!$A:$A,Stores!$B:$B,"Unknown") -> TrendMart Kochi High Street | AD77: =_xlfn.XLOOKUP(tblSales[[#This Row],[Store_ID]],Stores!$A:$A,Stores!$E:$E,"Unknown") -> South Zone 1 | AE77: =_xlfn.XLOOKUP(tblSales[[#This Row],[Customer_ID]],Customers!$A:$A,Customers!$B:$B,"Unknown") -> Gayathri Gowda | AF77: =_xlfn.XLOOKUP(tblSales[[#This Row],[Customer_ID]],Customers!$A:$A,Customers!$J:$J,"Unknown") -> Regular | AG77: =_xlfn.XLOOKUP(tblSales[[#This Row],[Employee_ID]],Employees!$A:$A,Employees!$B:$B,"Unknown") -> Anil Reddy | AH77: =IF(MONTH(tblSales[[#This Row],[Invoice Date]])>=4,MONTH(tblSales[[#This Row],[Invoice Date]]),MONTH(tblSales[[#This Row],[Invoice Date]])+12) -> 12 | AI77: =DATE(YEAR(tblSales[[#This Row],[Invoice Date]]),MONTH(tblSales[[#This Row],[Invoice Date]]),1) -> 45627 | AJ77: =_xlfn.XLOOKUP(tblSales[[#This Row],[Product_ID]],Products!$A:$A,Products!$B:$B,"Unknown") -> Being Human Skinny Fit Charcoal | AK77: =IFERROR(tblSales[[#This Row],[Profit]]/tblSales[[#This Row],[Sales Amount]],0) -> 0.37471742 | AL77: =IF(tblSales[[#This Row],[Discount %]]<=5,"0-5%", IF(tblSales[[#This Row],[Discount %]]<=10,"5-10%", IF(tblSales[[#This Row],[Discount %]]<=15,"10-15%", IF(tblSales[[#This Row],[Discount %]]<=20,"15-20%","20%+")))) -> 0-5%
A78: INV100077 | B78: 45396 | C78: CUST0461 | D78: PRD0228 | E78: STR082 | F78: EMP0127 | G78: 2 | H78: 1419.26 | I78: 20 | J78: 567.7 | K78: 12 | L78: 272.5 | M78: 2543.32 | N78: 1806.6 | O78: =(M78-N78-L78) -> 464.22 | P78: Credit Card | Q78: =TRIM(CLEAN(P78)) -> Credit Card | R78: Online | S78: Not Returned | T78: 15:56 | U78: Weekend | V78: =TEXT(tblSales[[#This Row],[Invoice Date]],"mmm") -> Apr | W78: =MONTH(tblSales[[#This Row],[Invoice Date]]) -> 4 | X78: =YEAR(tblSales[[#This Row],[Invoice Date]]) -> 2024 | Y78: =TEXT(tblSales[[#This Row],[Invoice Date]],"mmm-yyyy") -> Apr-2024 | Z78: =_xlfn.XLOOKUP(tblSales[[#This Row],[Product_ID]],Products!$A:$A,Products!$C:$C,"Women Dresses") -> Wallets | AA78: =_xlfn.XLOOKUP(tblSales[[#This Row],[Product_ID]],Products!$A:$A,Products!$D:$D,"Unknown") -> Bifold Wallet | AB78: =_xlfn.XLOOKUP(tblSales[[#This Row],[Product_ID]],Products!$A:$A,Products!$E:$E,"Unknown") -> Nike | AC78: =_xlfn.XLOOKUP(tblSales[[#This Row],[Store_ID]],Stores!$A:$A,Stores!$B:$B,"Unknown") -> TrendMart Tirupati Standard | AD78: =_xlfn.XLOOKUP(tblSales[[#This Row],[Store_ID]],Stores!$A:$A,Stores!$E:$E,"Unknown") -> South Zone 3 | AE78: =_xlfn.XLOOKUP(tblSales[[#This Row],[Customer_ID]],Customers!$A:$A,Customers!$B:$B,"Unknown") -> Bindu Mishra | AF78: =_xlfn.XLOOKUP(tblSales[[#This Row],[Customer_ID]],Customers!$A:$A,Customers!$J:$J,"Unknown") -> Regular | AG78: =_xlfn.XLOOKUP(tblSales[[#This Row],[Employee_ID]],Employees!$A:$A,Employees!$B:$B,"Unknown") -> Chandra Reddy | AH78: =IF(MONTH(tblSales[[#This Row],[Invoice Date]])>=4,MONTH(tblSales[[#This Row],[Invoice Date]]),MONTH(tblSales[[#This Row],[Invoice Date]])+12) -> 4 | AI78: =DATE(YEAR(tblSales[[#This Row],[Invoice Date]]),MONTH(tblSales[[#This Row],[Invoice Date]]),1) -> 45383 | AJ78: =_xlfn.XLOOKUP(tblSales[[#This Row],[Product_ID]],Products!$A:$A,Products!$B:$B,"Unknown") -> Nike Bifold Wallet Navy Blue | AK78: =IFERROR(tblSales[[#This Row],[Profit]]/tblSales[[#This Row],[Sales Amount]],0) -> 0.1825252 | AL78: =IF(tblSales[[#This Row],[Discount %]]<=5,"0-5%", IF(tblSales[[#This Row],[Discount %]]<=10,"5-10%", IF(tblSales[[#This Row],[Discount %]]<=15,"10-15%", IF(tblSales[[#This Row],[Discount %]]<=20,"15-20%","20%+")))) -> 15-20%
A79: INV100078 | B79: 45443 | C79: CUST0006 | D79: PRD0141 | E79: STR001 | F79: EMP0204 | G79: 4 | H79: 713.19 | I79: 30 | J79: 855.83 | K79: 5 | L79: 99.85 | M79: 2096.78 | N79: 2190.68 | O79: =(M79-N79-L79) -> -193.75 | P79: UPI | Q79: =TRIM(CLEAN(P79)) -> UPI | R79: Offline | S79: Not Returned | T79: 10:22 | U79: Weekday | V79: =TEXT(tblSales[[#This Row],[Invoice Date]],"mmm") -> May | W79: =MONTH(tblSales[[#This Row],[Invoice Date]]) -> 5 | X79: =YEAR(tblSales[[#This Row],[Invoice Date]]) -> 2024 | Y79: =TEXT(tblSales[[#This Row],[Invoice Date]],"mmm-yyyy") -> May-2024 | Z79: =_xlfn.XLOOKUP(tblSales[[#This Row],[Product_ID]],Products!$A:$A,Products!$C:$C,"Women Dresses") -> Women Tops | AA79: =_xlfn.XLOOKUP(tblSales[[#This Row],[Product_ID]],Products!$A:$A,Products!$D:$D,"Unknown") -> Formal Top | AB79: =_xlfn.XLOOKUP(tblSales[[#This Row],[Product_ID]],Products!$A:$A,Products!$E:$E,"Unknown") -> Indian Terrain | AC79: =_xlfn.XLOOKUP(tblSales[[#This Row],[Store_ID]],Stores!$A:$A,Stores!$B:$B,"Unknown") -> TrendMart Kollam Standard | AD79: =_xlfn.XLOOKUP(tblSales[[#This Row],[Store_ID]],Stores!$A:$A,Stores!$E:$E,"Unknown") -> South Zone 1 | AE79: =_xlfn.XLOOKUP(tblSales[[#This Row],[Customer_ID]],Customers!$A:$A,Customers!$B:$B,"Unknown") -> Rajesh Gopalakrishnan | AF79: =_xlfn.XLOOKUP(tblSales[[#This Row],[Customer_ID]],Customers!$A:$A,Customers!$J:$J,"Unknown") -> Gold | AG79: =_xlfn.XLOOKUP(tblSales[[#This Row],[Employee_ID]],Employees!$A:$A,Employees!$B:$B,"Unknown") -> Rahul Krishnan | AH79: =IF(MONTH(tblSales[[#This Row],[Invoice Date]])>=4,MONTH(tblSales[[#This Row],[Invoice Date]]),MONTH(tblSales[[#This Row],[Invoice Date]])+12) -> 5 | AI79: =DATE(YEAR(tblSales[[#This Row],[Invoice Date]]),MONTH(tblSales[[#This Row],[Invoice Date]]),1) -> 45413 | AJ79: =_xlfn.XLOOKUP(tblSales[[#This Row],[Product_ID]],Products!$A:$A,Products!$B:$B,"Unknown") -> Indian Terrain Formal Top Maroon | AK79: =IFERROR(tblSales[[#This Row],[Profit]]/tblSales[[#This Row],[Sales Amount]],0) -> -0.09240359 | AL79: =IF(tblSales[[#This Row],[Discount %]]<=5,"0-5%", IF(tblSales[[#This Row],[Discount %]]<=10,"5-10%", IF(tblSales[[#This Row],[Discount %]]<=15,"10-15%", IF(tblSales[[#This Row],[Discount %]]<=20,"15-20%","20%+")))) -> 20%+
A80: INV100079 | B80: 45544 | C80: CUST0310 | D80: PRD0138 | E80: STR032 | F80: EMP0258 | G80: 4 | H80: 1255.49 | I80: 0 | J80: 0 | K80: 12 | L80: 602.64 | M80: 5624.6 | N80: 3647.36 | O80: =(M80-N80-L80) -> 1374.6 | P80: Debit Card | Q80: =TRIM(CLEAN(P80)) -> Debit Card | R80: Online | S80: Not Returned | T80: 13:12 | U80: Weekday | V80: =TEXT(tblSales[[#This Row],[Invoice Date]],"mmm") -> Sep | W80: =MONTH(tblSales[[#This Row],[Invoice Date]]) -> 9 | X80: =YEAR(tblSales[[#This Row],[Invoice Date]]) -> 2024 | Y80: =TEXT(tblSales[[#This Row],[Invoice Date]],"mmm-yyyy") -> Sep-2024 | Z80: =_xlfn.XLOOKUP(tblSales[[#This Row],[Product_ID]],Products!$A:$A,Products!$C:$C,"Women Dresses") -> Men Trousers | AA80: =_xlfn.XLOOKUP(tblSales[[#This Row],[Product_ID]],Products!$A:$A,Products!$D:$D,"Unknown") -> Formal Trouser | AB80: =_xlfn.XLOOKUP(tblSales[[#This Row],[Product_ID]],Products!$A:$A,Products!$E:$E,"Unknown") -> Louis Philippe | AC80: =_xlfn.XLOOKUP(tblSales[[#This Row],[Store_ID]],Stores!$A:$A,Stores!$B:$B,"Unknown") -> TrendMart Kochi Standard | AD80: =_xlfn.XLOOKUP(tblSales[[#This Row],[Store_ID]],Stores!$A:$A,Stores!$E:$E,"Unknown") -> South Zone 1 | AE80: =_xlfn.XLOOKUP(tblSales[[#This Row],[Customer_ID]],Customers!$A:$A,Customers!$B:$B,"Unknown") -> Nithya Yadav | AF80: =_xlfn.XLOOKUP(tblSales[[#This Row],[Customer_ID]],Customers!$A:$A,Customers!$J:$J,"Unknown") -> Silver | AG80: =_xlfn.XLOOKUP(tblSales[[#This Row],[Employee_ID]],Employees!$A:$A,Employees!$B:$B,"Unknown") -> Preethi Singh | AH80: =IF(MONTH(tblSales[[#This Row],[Invoice Date]])>=4,MONTH(tblSales[[#This Row],[Invoice Date]]),MONTH(tblSales[[#This Row],[Invoice Date]])+12) -> 9 | AI80: =DATE(YEAR(tblSales[[#This Row],[Invoice Date]]),MONTH(tblSales[[#This Row],[Invoice Date]]),1) -> 45536 | AJ80: =_xlfn.XLOOKUP(tblSales[[#This Row],[Product_ID]],Products!$A:$A,Products!$B:$B,"Unknown") -> Louis Philippe Formal Trouser Olive | AK80: =IFERROR(tblSales[[#This Row],[Profit]]/tblSales[[#This Row],[Sales Amount]],0) -> 0.24439071 | AL80: =IF(tblSales[[#This Row],[Discount %]]<=5,"0-5%", IF(tblSales[[#This Row],[Discount %]]<=10,"5-10%", IF(tblSales[[#This Row],[Discount %]]<=15,"10-15%", IF(tblSales[[#This Row],[Discount %]]<=20,"15-20%","20%+")))) -> 0-5%
A81: INV100080 | B81: 45702 | C81: CUST0795 | D81: PRD0043 | E81: STR029 | F81: EMP0206 | G81: 2 | H81: 3188.24 | I81: 25 | J81: 1594.12 | K81: 12 | L81: 573.88 | M81: 5356.24 | N81: 4068.02 | O81: =(M81-N81-L81) -> 714.34 | P81: Cash | Q81: =TRIM(CLEAN(P81)) -> Cash | R81: Online | S81: Returned | T81: 13:02 | U81: Weekday | V81: =TEXT(tblSales[[#This Row],[Invoice Date]],"mmm") -> Feb | W81: =MONTH(tblSales[[#This Row],[Invoice Date]]) -> 2 | X81: =YEAR(tblSales[[#This Row],[Invoice Date]]) -> 2025 | Y81: =TEXT(tblSales[[#This Row],[Invoice Date]],"mmm-yyyy") -> Feb-2025 | Z81: =_xlfn.XLOOKUP(tblSales[[#This Row],[Product_ID]],Products!$A:$A,Products!$C:$C,"Women Dresses") -> Handbags | AA81: =_xlfn.XLOOKUP(tblSales[[#This Row],[Product_ID]],Products!$A:$A,Products!$D:$D,"Unknown") -> Sling Bag | AB81: =_xlfn.XLOOKUP(tblSales[[#This Row],[Product_ID]],Products!$A:$A,Products!$E:$E,"Unknown") -> GRT Jewellers | AC81: =_xlfn.XLOOKUP(tblSales[[#This Row],[Store_ID]],Stores!$A:$A,Stores!$B:$B,"Unknown") -> TrendMart Davanagere High Street | AD81: =_xlfn.XLOOKUP(tblSales[[#This Row],[Store_ID]],Stores!$A:$A,Stores!$E:$E,"Unknown") -> South Zone 2 | AE81: =_xlfn.XLOOKUP(tblSales[[#This Row],[Customer_ID]],Customers!$A:$A,Customers!$B:$B,"Unknown") -> Deepa Iyer | AF81: =_xlfn.XLOOKUP(tblSales[[#This Row],[Customer_ID]],Customers!$A:$A,Customers!$J:$J,"Unknown") -> Regular | AG81: =_xlfn.XLOOKUP(tblSales[[#This Row],[Employee_ID]],Employees!$A:$A,Employees!$B:$B,"Unknown") -> Arjun Krishnan | AH81: =IF(MONTH(tblSales[[#This Row],[Invoice Date]])>=4,MONTH(tblSales[[#This Row],[Invoice Date]]),MONTH(tblSales[[#This Row],[Invoice Date]])+12) -> 14 | AI81: =DATE(YEAR(tblSales[[#This Row],[Invoice Date]]),MONTH(tblSales[[#This Row],[Invoice Date]]),1) -> 45689 | AJ81: =_xlfn.XLOOKUP(tblSales[[#This Row],[Product_ID]],Products!$A:$A,Products!$B:$B,"Unknown") -> GRT Jewellers Sling Bag Olive | AK81: =IFERROR(tblSales[[#This Row],[Profit]]/tblSales[[#This Row],[Sales Amount]],0) -> 0.13336594 | AL81: =IF(tblSales[[#This Row],[Discount %]]<=5,"0-5%", IF(tblSales[[#This Row],[Discount %]]<=10,"5-10%", IF(tblSales[[#This Row],[Discount %]]<=15,"10-15%", IF(tblSales[[#This Row],[Discount %]]<=20,"15-20%","20%+")))) -> 20%+
A82: INV100081 | B82: 45534 | C82: CUST0659 | D82: PRD0178 | E82: STR050 | F82: EMP0149 | G82: 3 | H82: 565.59 | I82: 30 | J82: 509.03 | K82: 5 | L82: 59.39 | M82: 1247.13 | N82: 1072.35 | O82: =(M82-N82-L82) -> 115.39 | P82: UPI | Q82: =TRIM(CLEAN(P82)) -> UPI | R82: Online | S82: Not Returned | T82: 14:47 | U82: Weekday | V82: =TEXT(tblSales[[#This Row],[Invoice Date]],"mmm") -> Aug | W82: =MONTH(tblSales[[#This Row],[Invoice Date]]) -> 8 | X82: =YEAR(tblSales[[#This Row],[Invoice Date]]) -> 2024 | Y82: =TEXT(tblSales[[#This Row],[Invoice Date]],"mmm-yyyy") -> Aug-2024 | Z82: =_xlfn.XLOOKUP(tblSales[[#This Row],[Product_ID]],Products!$A:$A,Products!$C:$C,"Women Dresses") -> Wallets | AA82: =_xlfn.XLOOKUP(tblSales[[#This Row],[Product_ID]],Products!$A:$A,Products!$D:$D,"Unknown") -> Zip Wallet | AB82: =_xlfn.XLOOKUP(tblSales[[#This Row],[Product_ID]],Products!$A:$A,Products!$E:$E,"Unknown") -> Aurelia | AC82: =_xlfn.XLOOKUP(tblSales[[#This Row],[Store_ID]],Stores!$A:$A,Stores!$B:$B,"Unknown") -> TrendMart Thrissur High Street | AD82: =_xlfn.XLOOKUP(tblSales[[#This Row],[Store_ID]],Stores!$A:$A,Stores!$E:$E,"Unknown") -> South Zone 1 | AE82: =_xlfn.XLOOKUP(tblSales[[#This Row],[Customer_ID]],Customers!$A:$A,Customers!$B:$B,"Unknown") -> Nandini Natarajan | AF82: =_xlfn.XLOOKUP(tblSales[[#This Row],[Customer_ID]],Customers!$A:$A,Customers!$J:$J,"Unknown") -> Gold | AG82: =_xlfn.XLOOKUP(tblSales[[#This Row],[Employee_ID]],Employees!$A:$A,Employees!$B:$B,"Unknown") -> Vasanthi Kamath | AH82: =IF(MONTH(tblSales[[#This Row],[Invoice Date]])>=4,MONTH(tblSales[[#This Row],[Invoice Date]]),MONTH(tblSales[[#This Row],[Invoice Date]])+12) -> 8 | AI82: =DATE(YEAR(tblSales[[#This Row],[Invoice Date]]),MONTH(tblSales[[#This Row],[Invoice Date]]),1) -> 45505 | AJ82: =_xlfn.XLOOKUP(tblSales[[#This Row],[Product_ID]],Products!$A:$A,Products!$B:$B,"Unknown") -> Aurelia Zip Wallet Red | AK82: =IFERROR(tblSales[[#This Row],[Profit]]/tblSales[[#This Row],[Sales Amount]],0) -> 0.092524436 | AL82: =IF(tblSales[[#This Row],[Discount %]]<=5,"0-5%", IF(tblSales[[#This Row],[Discount %]]<=10,"5-10%", IF(tblSales[[#This Row],[Discount %]]<=15,"10-15%", IF(tblSales[[#This Row],[Discount %]]<=20,"15-20%","20%+")))) -> 20%+
A83: INV100082 | B83: 45492 | C83: CUST0789 | D83: PRD0043 | E83: STR053 | F83: EMP0260 | G83: 3 | H83: 3067.81 | I83: 25 | J83: 2300.86 | K83: 12 | L83: 828.31 | M83: 7730.88 | N83: 6102.03 | O83: =(M83-N83-L83) -> 800.54 | P83: UPI | Q83: =TRIM(CLEAN(P83)) -> UPI | R83: Online | S83: Returned | T83: 12:35 | U83: Weekday | V83: =TEXT(tblSales[[#This Row],[Invoice Date]],"mmm") -> Jul | W83: =MONTH(tblSales[[#This Row],[Invoice Date]]) -> 7 | X83: =YEAR(tblSales[[#This Row],[Invoice Date]]) -> 2024 | Y83: =TEXT(tblSales[[#This Row],[Invoice Date]],"mmm-yyyy") -> Jul-2024 | Z83: =_xlfn.XLOOKUP(tblSales[[#This Row],[Product_ID]],Products!$A:$A,Products!$C:$C,"Women Dresses") -> Handbags | AA83: =_xlfn.XLOOKUP(tblSales[[#This Row],[Product_ID]],Products!$A:$A,Products!$D:$D,"Unknown") -> Sling Bag | AB83: =_xlfn.XLOOKUP(tblSales[[#This Row],[Product_ID]],Products!$A:$A,Products!$E:$E,"Unknown") -> GRT Jewellers | AC83: =_xlfn.XLOOKUP(tblSales[[#This Row],[Store_ID]],Stores!$A:$A,Stores!$B:$B,"Unknown") -> TrendMart Kochi Standard | AD83: =_xlfn.XLOOKUP(tblSales[[#This Row],[Store_ID]],Stores!$A:$A,Stores!$E:$E,"Unknown") -> South Zone 1 | AE83: =_xlfn.XLOOKUP(tblSales[[#This Row],[Customer_ID]],Customers!$A:$A,Customers!$B:$B,"Unknown") -> Rohit Gupta | AF83: =_xlfn.XLOOKUP(tblSales[[#This Row],[Customer_ID]],Customers!$A:$A,Customers!$J:$J,"Unknown") -> Gold | AG83: =_xlfn.XLOOKUP(tblSales[[#This Row],[Employee_ID]],Employees!$A:$A,Employees!$B:$B,"Unknown") -> Malathi Varma | AH83: =IF(MONTH(tblSales[[#This Row],[Invoice Date]])>=4,MONTH(tblSales[[#This Row],[Invoice Date]]),MONTH(tblSales[[#This Row],[Invoice Date]])+12) -> 7 | AI83: =DATE(YEAR(tblSales[[#This Row],[Invoice Date]]),MONTH(tblSales[[#This Row],[Invoice Date]]),1) -> 45474 | AJ83: =_xlfn.XLOOKUP(tblSales[[#This Row],[Product_ID]],Products!$A:$A,Products!$B:$B,"Unknown") -> GRT Jewellers Sling Bag Olive | AK83: =IFERROR(tblSales[[#This Row],[Profit]]/tblSales[[#This Row],[Sales Amount]],0) -> 0.10355095 | AL83: =IF(tblSales[[#This Row],[Discount %]]<=5,"0-5%", IF(tblSales[[#This Row],[Discount %]]<=10,"5-10%", IF(tblSales[[#This Row],[Discount %]]<=15,"10-15%", IF(tblSales[[#This Row],[Discount %]]<=20,"15-20%","20%+")))) -> 20%+
A84: INV100083 | B84: 45456 | C84: CUST0326 | D84: PRD0151 | E84: STR110 | F84: EMP0156 | G84: 1 | H84: 1325.53 | I84: 25 | J84: 331.38 | K84: 12 | L84: 119.3 | M84: 1113.45 | N84: 834.96 | O84: =(M84-N84-L84) -> 159.19 | P84: Credit Card | Q84: =TRIM(CLEAN(P84)) -> Credit Card | R84: Online | S84: Not Returned | T84: 10:36 | U84: Weekday | V84: =TEXT(tblSales[[#This Row],[Invoice Date]],"mmm") -> Jun | W84: =MONTH(tblSales[[#This Row],[Invoice Date]]) -> 6 | X84: =YEAR(tblSales[[#This Row],[Invoice Date]]) -> 2024 | Y84: =TEXT(tblSales[[#This Row],[Invoice Date]],"mmm-yyyy") -> Jun-2024 | Z84: =_xlfn.XLOOKUP(tblSales[[#This Row],[Product_ID]],Products!$A:$A,Products!$C:$C,"Women Dresses") -> Women Jeans | AA84: =_xlfn.XLOOKUP(tblSales[[#This Row],[Product_ID]],Products!$A:$A,Products!$D:$D,"Unknown") -> Bootcut | AB84: =_xlfn.XLOOKUP(tblSales[[#This Row],[Product_ID]],Products!$A:$A,Products!$E:$E,"Unknown") -> US Polo Assn | AC84: =_xlfn.XLOOKUP(tblSales[[#This Row],[Store_ID]],Stores!$A:$A,Stores!$B:$B,"Unknown") -> TrendMart Thoothukudi Outlet | AD84: =_xlfn.XLOOKUP(tblSales[[#This Row],[Store_ID]],Stores!$A:$A,Stores!$E:$E,"Unknown") -> South Zone 1 | AE84: =_xlfn.XLOOKUP(tblSales[[#This Row],[Customer_ID]],Customers!$A:$A,Customers!$B:$B,"Unknown") -> Deepa Prasad | AF84: =_xlfn.XLOOKUP(tblSales[[#This Row],[Customer_ID]],Customers!$A:$A,Customers!$J:$J,"Unknown") -> Platinum | AG84: =_xlfn.XLOOKUP(tblSales[[#This Row],[Employee_ID]],Employees!$A:$A,Employees!$B:$B,"Unknown") -> Deepthi Iyengar | AH84: =IF(MONTH(tblSales[[#This Row],[Invoice Date]])>=4,MONTH(tblSales[[#This Row],[Invoice Date]]),MONTH(tblSales[[#This Row],[Invoice Date]])+12) -> 6 | AI84: =DATE(YEAR(tblSales[[#This Row],[Invoice Date]]),MONTH(tblSales[[#This Row],[Invoice Date]]),1) -> 45444 | AJ84: =_xlfn.XLOOKUP(tblSales[[#This Row],[Product_ID]],Products!$A:$A,Products!$B:$B,"Unknown") -> US Polo Assn Bootcut Black | AK84: =IFERROR(tblSales[[#This Row],[Profit]]/tblSales[[#This Row],[Sales Amount]],0) -> 0.14297005 | AL84: =IF(tblSales[[#This Row],[Discount %]]<=5,"0-5%", IF(tblSales[[#This Row],[Discount %]]<=10,"5-10%", IF(tblSales[[#This Row],[Discount %]]<=15,"10-15%", IF(tblSales[[#This Row],[Discount %]]<=20,"15-20%","20%+")))) -> 20%+
A85: INV100084 | B85: 45604 | C85: CUST0345 | D85: PRD0220 | E85: STR071 | F85: EMP0240 | G85: 2 | H85: 1187.06 | I85: 20 | J85: 474.82 | K85: 12 | L85: 227.92 | M85: 2127.22 | N85: 1709.7 | O85: =(M85-N85-L85) -> 189.6 | P85: UPI | Q85: =TRIM(CLEAN(P85)) -> UPI | R85: Online | S85: Not Returned | T85: 14:17 | U85: Weekday | V85: =TEXT(tblSales[[#This Row],[Invoice Date]],"mmm") -> Nov | W85: =MONTH(tblSales[[#This Row],[Invoice Date]]) -> 11 | X85: =YEAR(tblSales[[#This Row],[Invoice Date]]) -> 2024 | Y85: =TEXT(tblSales[[#This Row],[Invoice Date]],"mmm-yyyy") -> Nov-2024 | Z85: =_xlfn.XLOOKUP(tblSales[[#This Row],[Product_ID]],Products!$A:$A,Products!$C:$C,"Women Dresses") -> Footwear | AA85: =_xlfn.XLOOKUP(tblSales[[#This Row],[Product_ID]],Products!$A:$A,Products!$D:$D,"Unknown") -> Sandals | AB85: =_xlfn.XLOOKUP(tblSales[[#This Row],[Product_ID]],Products!$A:$A,Products!$E:$E,"Unknown") -> Joyalukkas | AC85: =_xlfn.XLOOKUP(tblSales[[#This Row],[Store_ID]],Stores!$A:$A,Stores!$B:$B,"Unknown") -> TrendMart Kannur Standard | AD85: =_xlfn.XLOOKUP(tblSales[[#This Row],[Store_ID]],Stores!$A:$A,Stores!$E:$E,"Unknown") -> South Zone 1 | AE85: =_xlfn.XLOOKUP(tblSales[[#This Row],[Customer_ID]],Customers!$A:$A,Customers!$B:$B,"Unknown") -> Sunita Subramaniam | AF85: =_xlfn.XLOOKUP(tblSales[[#This Row],[Customer_ID]],Customers!$A:$A,Customers!$J:$J,"Unknown") -> Regular | AG85: =_xlfn.XLOOKUP(tblSales[[#This Row],[Employee_ID]],Employees!$A:$A,Employees!$B:$B,"Unknown") -> Gopal Prasad | AH85: =IF(MONTH(tblSales[[#This Row],[Invoice Date]])>=4,MONTH(tblSales[[#This Row],[Invoice Date]]),MONTH(tblSales[[#This Row],[Invoice Date]])+12) -> 11 | AI85: =DATE(YEAR(tblSales[[#This Row],[Invoice Date]]),MONTH(tblSales[[#This Row],[Invoice Date]]),1) -> 45597 | AJ85: =_xlfn.XLOOKUP(tblSales[[#This Row],[Product_ID]],Products!$A:$A,Products!$B:$B,"Unknown") -> Joyalukkas Sandals Beige | AK85: =IFERROR(tblSales[[#This Row],[Profit]]/tblSales[[#This Row],[Sales Amount]],0) -> 0.089130414 | AL85: =IF(tblSales[[#This Row],[Discount %]]<=5,"0-5%", IF(tblSales[[#This Row],[Discount %]]<=10,"5-10%", IF(tblSales[[#This Row],[Discount %]]<=15,"10-15%", IF(tblSales[[#This Row],[Discount %]]<=20,"15-20%","20%+")))) -> 15-20%
... A143: INV100142 | B143: 45615 | C143: CUST0103 | D143: PRD0192 | E143: STR026 | F143: EMP0009 | G143: 4 | H143: 394.94 | I143: 0 | J143: 0 | K143: 5 | L143: 78.99 | M143: 1658.75 | N143: 1048.24 | O143: =(M143-N143-L143) -> 531.52 | P143: UPI | Q143: =TRIM(CLEAN(P143)) -> UPI | R143: Offline | S143: Not Returned | T143: 17:07 | U143: Weekday | V143: =TEXT(tblSales[[#This Row],[Invoice Date]],"mmm") -> Nov | W143: =MONTH(tblSales[[#This Row],[Invoice Date]]) -> 11 | X143: =YEAR(tblSales[[#This Row],[Invoice Date]]) -> 2024 | Y143: =TEXT(tblSales[[#This Row],[Invoice Date]],"mmm-yyyy") -> Nov-2024 | Z143: =_xlfn.XLOOKUP(tblSales[[#This Row],[Product_ID]],Products!$A:$A,Products!$C:$C,"Women Dresses") -> Men T-Shirts | AA143: =_xlfn.XLOOKUP(tblSales[[#This Row],[Product_ID]],Products!$A:$A,Products!$D:$D,"Unknown") -> Round Neck | AB143: =_xlfn.XLOOKUP(tblSales[[#This Row],[Product_ID]],Products!$A:$A,Products!$E:$E,"Unknown") -> Skechers | AC143: =_xlfn.XLOOKUP(tblSales[[#This Row],[Store_ID]],Stores!$A:$A,Stores!$B:$B,"Unknown") -> TrendMart Guntur Standard | AD143: =_xlfn.XLOOKUP(tblSales[[#This Row],[Store_ID]],Stores!$A:$A,Stores!$E:$E,"Unknown") -> South Zone 3 | AE143: =_xlfn.XLOOKUP(tblSales[[#This Row],[Customer_ID]],Customers!$A:$A,Customers!$B:$B,"Unknown") -> Yogesh Venkatesan | AF143: =_xlfn.XLOOKUP(tblSales[[#This Row],[Customer_ID]],Customers!$A:$A,Customers!$J:$J,"Unknown") -> Regular | AG143: =_xlfn.XLOOKUP(tblSales[[#This Row],[Employee_ID]],Employees!$A:$A,Employees!$B:$B,"Unknown") -> Vinod Hegde | AH143: =IF(MONTH(tblSales[[#This Row],[Invoice Date]])>=4,MONTH(tblSales[[#This Row],[Invoice Date]]),MONTH(tblSales[[#This Row],[Invoice Date]])+12) -> 11 | AI143: =DATE(YEAR(tblSales[[#This Row],[Invoice Date]]),MONTH(tblSales[[#This Row],[Invoice Date]]),1) -> 45597 | AJ143: =_xlfn.XLOOKUP(tblSales[[#This Row],[Product_ID]],Products!$A:$A,Products!$B:$B,"Unknown") -> Skechers Round Neck Red | AK143: =IFERROR(tblSales[[#This Row],[Profit]]/tblSales[[#This Row],[Sales Amount]],0) -> 0.32043406 | AL143: =IF(tblSales[[#This Row],[Discount %]]<=5,"0-5%", IF(tblSales[[#This Row],[Discount %]]<=10,"5-10%", IF(tblSales[[#This Row],[Discount %]]<=15,"10-15%", IF(tblSales[[#This Row],[Discount %]]<=20,"15-20%","20%+")))) -> 0-5%
A144: INV100143 | B144: 45435 | C144: CUST0837 | D144: PRD0241 | E144: STR002 | F144: EMP0205 | G144: 0 | H144: 1601.15 | I144: 30 | J144: 0 | K144: 12 | L144: 0 | M144: 0 | N144: 0 | O144: 0 | P144: UPI | Q144: =TRIM(CLEAN(P144)) -> UPI | R144: Offline | S144: Not Returned | T144: 14:05 | U144: Weekday | V144: =TEXT(tblSales[[#This Row],[Invoice Date]],"mmm") -> May | W144: =MONTH(tblSales[[#This Row],[Invoice Date]]) -> 5 | X144: =YEAR(tblSales[[#This Row],[Invoice Date]]) -> 2024 | Y144: =TEXT(tblSales[[#This Row],[Invoice Date]],"mmm-yyyy") -> May-2024 | Z144: =_xlfn.XLOOKUP(tblSales[[#This Row],[Product_ID]],Products!$A:$A,Products!$C:$C,"Women Dresses") -> Sportswear | AA144: =_xlfn.XLOOKUP(tblSales[[#This Row],[Product_ID]],Products!$A:$A,Products!$D:$D,"Unknown") -> Sports T-Shirt | AB144: =_xlfn.XLOOKUP(tblSales[[#This Row],[Product_ID]],Products!$A:$A,Products!$E:$E,"Unknown") -> Allen Solly | AC144: =_xlfn.XLOOKUP(tblSales[[#This Row],[Store_ID]],Stores!$A:$A,Stores!$B:$B,"Unknown") -> TrendMart Thrissur Standard | AD144: =_xlfn.XLOOKUP(tblSales[[#This Row],[Store_ID]],Stores!$A:$A,Stores!$E:$E,"Unknown") -> South Zone 1 | AE144: =_xlfn.XLOOKUP(tblSales[[#This Row],[Customer_ID]],Customers!$A:$A,Customers!$B:$B,"Unknown") -> Deepthi Shetty | AF144: =_xlfn.XLOOKUP(tblSales[[#This Row],[Customer_ID]],Customers!$A:$A,Customers!$J:$J,"Unknown") -> Regular | AG144: =_xlfn.XLOOKUP(tblSales[[#This Row],[Employee_ID]],Employees!$A:$A,Employees!$B:$B,"Unknown") -> Malini Gowda | AH144: =IF(MONTH(tblSales[[#This Row],[Invoice Date]])>=4,MONTH(tblSales[[#This Row],[Invoice Date]]),MONTH(tblSales[[#This Row],[Invoice Date]])+12) -> 5 | AI144: =DATE(YEAR(tblSales[[#This Row],[Invoice Date]]),MONTH(tblSales[[#This Row],[Invoice Date]]),1) -> 45413 | AJ144: =_xlfn.XLOOKUP(tblSales[[#This Row],[Product_ID]],Products!$A:$A,Products!$B:$B,"Unknown") -> Allen Solly Sports T-Shirt Cream | AK144: =IFERROR(tblSales[[#This Row],[Profit]]/tblSales[[#This Row],[Sales Amount]],0) -> 0 | AL144: =IF(tblSales[[#This Row],[Discount %]]<=5,"0-5%", IF(tblSales[[#This Row],[Discount %]]<=10,"5-10%", IF(tblSales[[#This Row],[Discount %]]<=15,"10-15%", IF(tblSales[[#This Row],[Discount %]]<=20,"15-20%","20%+")))) -> 20%+
A145: INV100144 | B145: 45672 | C145: CUST0497 | D145: PRD0033 | E145: STR113 | F145: EMP0260 | G145: 1 | H145: 3398.79 | I145: 30 | J145: 1019.64 | K145: 12 | L145: 285.5 | M145: 2664.65 | N145: 2710.05 | O145: =(M145-N145-L145) -> -330.9 | P145: Debit Card | Q145: =TRIM(CLEAN(P145)) -> Debit Card | R145: Offline | S145: Not Returned | T145: 16:12 | U145: Weekday | V145: =TEXT(tblSales[[#This Row],[Invoice Date]],"mmm") -> Jan | W145: =MONTH(tblSales[[#This Row],[Invoice Date]]) -> 1 | X145: =YEAR(tblSales[[#This Row],[Invoice Date]]) -> 2025 | Y145: =TEXT(tblSales[[#This Row],[Invoice Date]],"mmm-yyyy") -> Jan-2025 | Z145: =_xlfn.XLOOKUP(tblSales[[#This Row],[Product_ID]],Products!$A:$A,Products!$C:$C,"Women Dresses") -> Women Sarees | AA145: =_xlfn.XLOOKUP(tblSales[[#This Row],[Product_ID]],Products!$A:$A,Products!$D:$D,"Unknown") -> Cotton Saree | AB145: =_xlfn.XLOOKUP(tblSales[[#This Row],[Product_ID]],Products!$A:$A,Products!$E:$E,"Unknown") -> Bata | AC145: =_xlfn.XLOOKUP(tblSales[[#This Row],[Store_ID]],Stores!$A:$A,Stores!$B:$B,"Unknown") -> TrendMart Mangaluru High Street | AD145: =_xlfn.XLOOKUP(tblSales[[#This Row],[Store_ID]],Stores!$A:$A,Stores!$E:$E,"Unknown") -> South Zone 2 | AE145: =_xlfn.XLOOKUP(tblSales[[#This Row],[Customer_ID]],Customers!$A:$A,Customers!$B:$B,"Unknown") -> Naveen Subramaniam | AF145: =_xlfn.XLOOKUP(tblSales[[#This Row],[Customer_ID]],Customers!$A:$A,Customers!$J:$J,"Unknown") -> Regular | AG145: =_xlfn.XLOOKUP(tblSales[[#This Row],[Employee_ID]],Employees!$A:$A,Employees!$B:$B,"Unknown") -> Malathi Varma | AH145: =IF(MONTH(tblSales[[#This Row],[Invoice Date]])>=4,MONTH(tblSales[[#This Row],[Invoice Date]]),MONTH(tblSales[[#This Row],[Invoice Date]])+12) -> 13 | AI145: =DATE(YEAR(tblSales[[#This Row],[Invoice Date]]),MONTH(tblSales[[#This Row],[Invoice Date]]),1) -> 45658 | AJ145: =_xlfn.XLOOKUP(tblSales[[#This Row],[Product_ID]],Products!$A:$A,Products!$B:$B,"Unknown") -> Bata Cotton Saree Mustard | AK145: =IFERROR(tblSales[[#This Row],[Profit]]/tblSales[[#This Row],[Sales Amount]],0) -> -0.12418141 | AL145: =IF(tblSales[[#This Row],[Discount %]]<=5,"0-5%", IF(tblSales[[#This Row],[Discount %]]<=10,"5-10%", IF(tblSales[[#This Row],[Discount %]]<=15,"10-15%", IF(tblSales[[#This Row],[Discount %]]<=20,"15-20%","20%+")))) -> 20%+
A146: INV100145 | B146: 45499 | C146: CUST0309 | D146: PRD0126 | E146: STR074 | F146: EMP0170 | G146: 2 | H146: 947.98 | I146: 10 | J146: 189.6 | K146: 5 | L146: 85.32 | M146: 1791.68 | N146: 1291.18 | O146: =(M146-N146-L146) -> 415.18 | P146: UPI | Q146: =TRIM(CLEAN(P146)) -> UPI | R146: Online | S146: Not Returned | T146: 11:22 | U146: Weekday | V146: =TEXT(tblSales[[#This Row],[Invoice Date]],"mmm") -> Jul | W146: =MONTH(tblSales[[#This Row],[Invoice Date]]) -> 7 | X146: =YEAR(tblSales[[#This Row],[Invoice Date]]) -> 2024 | Y146: =TEXT(tblSales[[#This Row],[Invoice Date]],"mmm-yyyy") -> Jul-2024 | Z146: =_xlfn.XLOOKUP(tblSales[[#This Row],[Product_ID]],Products!$A:$A,Products!$C:$C,"Women Dresses") -> Men Shirts | AA146: =_xlfn.XLOOKUP(tblSales[[#This Row],[Product_ID]],Products!$A:$A,Products!$D:$D,"Unknown") -> Formal Shirt | AB146: =_xlfn.XLOOKUP(tblSales[[#This Row],[Product_ID]],Products!$A:$A,Products!$E:$E,"Unknown") -> Van Heusen | AC146: =_xlfn.XLOOKUP(tblSales[[#This Row],[Store_ID]],Stores!$A:$A,Stores!$B:$B,"Unknown") -> TrendMart Kurnool High Street | AD146: =_xlfn.XLOOKUP(tblSales[[#This Row],[Store_ID]],Stores!$A:$A,Stores!$E:$E,"Unknown") -> South Zone 3 | AE146: =_xlfn.XLOOKUP(tblSales[[#This Row],[Customer_ID]],Customers!$A:$A,Customers!$B:$B,"Unknown") -> Srinivas Gopalakrishnan | AF146: =_xlfn.XLOOKUP(tblSales[[#This Row],[Customer_ID]],Customers!$A:$A,Customers!$J:$J,"Unknown") -> Silver | AG146: =_xlfn.XLOOKUP(tblSales[[#This Row],[Employee_ID]],Employees!$A:$A,Employees!$B:$B,"Unknown") -> Jyothi Prasad | AH146: =IF(MONTH(tblSales[[#This Row],[Invoice Date]])>=4,MONTH(tblSales[[#This Row],[Invoice Date]]),MONTH(tblSales[[#This Row],[Invoice Date]])+12) -> 7 | AI146: =DATE(YEAR(tblSales[[#This Row],[Invoice Date]]),MONTH(tblSales[[#This Row],[Invoice Date]]),1) -> 45474 | AJ146: =_xlfn.XLOOKUP(tblSales[[#This Row],[Product_ID]],Products!$A:$A,Products!$B:$B,"Unknown") -> Van Heusen Formal Shirt Olive | AK146: =IFERROR(tblSales[[#This Row],[Profit]]/tblSales[[#This Row],[Sales Amount]],0) -> 0.23172665 | AL146: =IF(tblSales[[#This Row],[Discount %]]<=5,"0-5%", IF(tblSales[[#This Row],[Discount %]]<=10,"5-10%", IF(tblSales[[#This Row],[Discount %]]<=15,"10-15%", IF(tblSales[[#This Row],[Discount %]]<=20,"15-20%","20%+")))) -> 5-10%
A147: INV100146 | B147: 45405 | C147: CUST0340 | D147: PRD0096 | E147: STR007 | F147: EMP0203 | G147: 1 | H147: 4323.94 | I147: 0 | J147: 0 | K147: 12 | L147: 518.87 | M147: 4842.81 | N147: 2833.61 | O147: =(M147-N147-L147) -> 1490.33 | P147: UPI | Q147: =TRIM(CLEAN(P147)) -> UPI | R147: Offline | S147: Not Returned | T147: 15:21 | U147: Weekday | V147: =TEXT(tblSales[[#This Row],[Invoice Date]],"mmm") -> Apr | W147: =MONTH(tblSales[[#This Row],[Invoice Date]]) -> 4 | X147: =YEAR(tblSales[[#This Row],[Invoice Date]]) -> 2024 | Y147: =TEXT(tblSales[[#This Row],[Invoice Date]],"mmm-yyyy") -> Apr-2024 | Z147: =_xlfn.XLOOKUP(tblSales[[#This Row],[Product_ID]],Products!$A:$A,Products!$C:$C,"Women Dresses") -> Watches | AA147: =_xlfn.XLOOKUP(tblSales[[#This Row],[Product_ID]],Products!$A:$A,Products!$D:$D,"Unknown") -> Chronograph | AB147: =_xlfn.XLOOKUP(tblSales[[#This Row],[Product_ID]],Products!$A:$A,Products!$E:$E,"Unknown") -> Mufti | AC147: =_xlfn.XLOOKUP(tblSales[[#This Row],[Store_ID]],Stores!$A:$A,Stores!$B:$B,"Unknown") -> TrendMart Thoothukudi Mall Kiosk | AD147: =_xlfn.XLOOKUP(tblSales[[#This Row],[Store_ID]],Stores!$A:$A,Stores!$E:$E,"Unknown") -> South Zone 1 | AE147: =_xlfn.XLOOKUP(tblSales[[#This Row],[Customer_ID]],Customers!$A:$A,Customers!$B:$B,"Unknown") -> Gopal Prasad | AF147: =_xlfn.XLOOKUP(tblSales[[#This Row],[Customer_ID]],Customers!$A:$A,Customers!$J:$J,"Unknown") -> Regular | AG147: =_xlfn.XLOOKUP(tblSales[[#This Row],[Employee_ID]],Employees!$A:$A,Employees!$B:$B,"Unknown") -> Rani Mishra | AH147: =IF(MONTH(tblSales[[#This Row],[Invoice Date]])>=4,MONTH(tblSales[[#This Row],[Invoice Date]]),MONTH(tblSales[[#This Row],[Invoice Date]])+12) -> 4 | AI147: =DATE(YEAR(tblSales[[#This Row],[Invoice Date]]),MONTH(tblSales[[#This Row],[Invoice Date]]),1) -> 45383 | AJ147: =_xlfn.XLOOKUP(tblSales[[#This Row],[Product_ID]],Products!$A:$A,Products!$B:$B,"Unknown") -> Mufti Chronograph Grey | AK147: =IFERROR(tblSales[[#This Row],[Profit]]/tblSales[[#This Row],[Sales Amount]],0) -> 0.30774075 | AL147: =IF(tblSales[[#This Row],[Discount %]]<=5,"0-5%", IF(tblSales[[#This Row],[Discount %]]<=10,"5-10%", IF(tblSales[[#This Row],[Discount %]]<=15,"10-15%", IF(tblSales[[#This Row],[Discount %]]<=20,"15-20%","20%+")))) -> 0-5%
A148: INV100147 | B148: 45529 | C148: CUST0003 | D148: PRD0002 | E148: STR018 | F148: EMP0207 | G148: 1 | H148: 1289.85 | I148: 30 | J148: 386.95 | K148: 12 | L148: 108.35 | M148: 1011.25 | N148: 755.06 | O148: =(M148-N148-L148) -> 147.84 | P148: Net Banking | Q148: =TRIM(CLEAN(P148)) -> Net Banking | R148: Offline | S148: Not Returned | T148: 18:33 | U148: Weekend | V148: =TEXT(tblSales[[#This Row],[Invoice Date]],"mmm") -> Aug | W148: =MONTH(tblSales[[#This Row],[Invoice Date]]) -> 8 | X148: =YEAR(tblSales[[#This Row],[Invoice Date]]) -> 2024 | Y148: =TEXT(tblSales[[#This Row],[Invoice Date]],"mmm-yyyy") -> Aug-2024 | Z148: =_xlfn.XLOOKUP(tblSales[[#This Row],[Product_ID]],Products!$A:$A,Products!$C:$C,"Women Dresses") -> Winter Wear | AA148: =_xlfn.XLOOKUP(tblSales[[#This Row],[Product_ID]],Products!$A:$A,Products!$D:$D,"Unknown") -> Jacket | AB148: =_xlfn.XLOOKUP(tblSales[[#This Row],[Product_ID]],Products!$A:$A,Products!$E:$E,"Unknown") -> Fastrack | AC148: =_xlfn.XLOOKUP(tblSales[[#This Row],[Store_ID]],Stores!$A:$A,Stores!$B:$B,"Unknown") -> TrendMart Visakhapatnam High Street | AD148: =_xlfn.XLOOKUP(tblSales[[#This Row],[Store_ID]],Stores!$A:$A,Stores!$E:$E,"Unknown") -> South Zone 3 | AE148: =_xlfn.XLOOKUP(tblSales[[#This Row],[Customer_ID]],Customers!$A:$A,Customers!$B:$B,"Unknown") -> Swathi Bhat | AF148: =_xlfn.XLOOKUP(tblSales[[#This Row],[Customer_ID]],Customers!$A:$A,Customers!$J:$J,"Unknown") -> Regular | AG148: =_xlfn.XLOOKUP(tblSales[[#This Row],[Employee_ID]],Employees!$A:$A,Employees!$B:$B,"Unknown") -> Chitra Bhat | AH148: =IF(MONTH(tblSales[[#This Row],[Invoice Date]])>=4,MONTH(tblSales[[#This Row],[Invoice Date]]),MONTH(tblSales[[#This Row],[Invoice Date]])+12) -> 8 | AI148: =DATE(YEAR(tblSales[[#This Row],[Invoice Date]]),MONTH(tblSales[[#This Row],[Invoice Date]]),1) -> 45505 | AJ148: =_xlfn.XLOOKUP(tblSales[[#This Row],[Product_ID]],Products!$A:$A,Products!$B:$B,"Unknown") -> Fastrack Jacket Orange | AK148: =IFERROR(tblSales[[#This Row],[Profit]]/tblSales[[#This Row],[Sales Amount]],0) -> 0.1461953 | AL148: =IF(tblSales[[#This Row],[Discount %]]<=5,"0-5%", IF(tblSales[[#This Row],[Discount %]]<=10,"5-10%", IF(tblSales[[#This Row],[Discount %]]<=15,"10-15%", IF(tblSales[[#This Row],[Discount %]]<=20,"15-20%","20%+")))) -> 20%+
A149: INV100148 | B149: 45517 | C149: CUST0060 | D149: PRD0137 | E149: STR004 | F149: EMP0276 | G149: 1 | H149: 754.03 | I149: 25 | J149: 188.51 | K149: 5 | L149: 28.28 | M149: 593.8 | N149: 522.38 | O149: =(M149-N149-L149) -> 43.14 | P149: Credit Card | Q149: =TRIM(CLEAN(P149)) -> Credit Card | R149: Online | S149: Not Returned | T149: 16:13 | U149: Weekday | V149: =TEXT(tblSales[[#This Row],[Invoice Date]],"mmm") -> Aug | W149: =MONTH(tblSales[[#This Row],[Invoice Date]]) -> 8 | X149: =YEAR(tblSales[[#This Row],[Invoice Date]]) -> 2024 | Y149: =TEXT(tblSales[[#This Row],[Invoice Date]],"mmm-yyyy") -> Aug-2024 | Z149: =_xlfn.XLOOKUP(tblSales[[#This Row],[Product_ID]],Products!$A:$A,Products!$C:$C,"Women Dresses") -> Women Tops | AA149: =_xlfn.XLOOKUP(tblSales[[#This Row],[Product_ID]],Products!$A:$A,Products!$D:$D,"Unknown") -> Crop Top | AB149: =_xlfn.XLOOKUP(tblSales[[#This Row],[Product_ID]],Products!$A:$A,Products!$E:$E,"Unknown") -> Peter England | AC149: =_xlfn.XLOOKUP(tblSales[[#This Row],[Store_ID]],Stores!$A:$A,Stores!$B:$B,"Unknown") -> TrendMart Kalaburagi Mall Kiosk | AD149: =_xlfn.XLOOKUP(tblSales[[#This Row],[Store_ID]],Stores!$A:$A,Stores!$E:$E,"Unknown") -> South Zone 2 | AE149: =_xlfn.XLOOKUP(tblSales[[#This Row],[Customer_ID]],Customers!$A:$A,Customers!$B:$B,"Unknown") -> Karunakaran Yadav | AF149: =_xlfn.XLOOKUP(tblSales[[#This Row],[Customer_ID]],Customers!$A:$A,Customers!$J:$J,"Unknown") -> Regular | AG149: =_xlfn.XLOOKUP(tblSales[[#This Row],[Employee_ID]],Employees!$A:$A,Employees!$B:$B,"Unknown") -> Manoj Ramachandran | AH149: =IF(MONTH(tblSales[[#This Row],[Invoice Date]])>=4,MONTH(tblSales[[#This Row],[Invoice Date]]),MONTH(tblSales[[#This Row],[Invoice Date]])+12) -> 8 | AI149: =DATE(YEAR(tblSales[[#This Row],[Invoice Date]]),MONTH(tblSales[[#This Row],[Invoice Date]]),1) -> 45505 | AJ149: =_xlfn.XLOOKUP(tblSales[[#This Row],[Product_ID]],Products!$A:$A,Products!$B:$B,"Unknown") -> Peter England Crop Top Green | AK149: =IFERROR(tblSales[[#This Row],[Profit]]/tblSales[[#This Row],[Sales Amount]],0) -> 0.072650724 | AL149: =IF(tblSales[[#This Row],[Discount %]]<=5,"0-5%", IF(tblSales[[#This Row],[Discount %]]<=10,"5-10%", IF(tblSales[[#This Row],[Discount %]]<=15,"10-15%", IF(tblSales[[#This Row],[Discount %]]<=20,"15-20%","20%+")))) -> 20%+
A150: INV100149 | B150: 45636 | C150: CUST0460 | D150: PRD0064 | E150: STR077 | F150: EMP0063 | G150: 1 | H150: 324.55 | I150: 15 | J150: 48.68 | K150: 5 | L150: 13.79 | M150: 289.66 | N150: 254.15 | O150: =(M150-N150-L150) -> 21.72 | P150: UPI | Q150: =TRIM(CLEAN(P150)) -> UPI | R150: Offline | S150: Returned | T150: 16:55 | U150: Weekday | V150: =TEXT(tblSales[[#This Row],[Invoice Date]],"mmm") -> Dec | W150: =MONTH(tblSales[[#This Row],[Invoice Date]]) -> 12 | X150: =YEAR(tblSales[[#This Row],[Invoice Date]]) -> 2024 | Y150: =TEXT(tblSales[[#This Row],[Invoice Date]],"mmm-yyyy") -> Dec-2024 | Z150: =_xlfn.XLOOKUP(tblSales[[#This Row],[Product_ID]],Products!$A:$A,Products!$C:$C,"Women Dresses") -> Belts | AA150: =_xlfn.XLOOKUP(tblSales[[#This Row],[Product_ID]],Products!$A:$A,Products!$D:$D,"Unknown") -> Leather Belt | AB150: =_xlfn.XLOOKUP(tblSales[[#This Row],[Product_ID]],Products!$A:$A,Products!$E:$E,"Unknown") -> Raymond | AC150: =_xlfn.XLOOKUP(tblSales[[#This Row],[Store_ID]],Stores!$A:$A,Stores!$B:$B,"Unknown") -> TrendMart Hyderabad Mall Kiosk | AD150: =_xlfn.XLOOKUP(tblSales[[#This Row],[Store_ID]],Stores!$A:$A,Stores!$E:$E,"Unknown") -> South Zone 2 | AE150: =_xlfn.XLOOKUP(tblSales[[#This Row],[Customer_ID]],Customers!$A:$A,Customers!$B:$B,"Unknown") -> Ramesh Singh | AF150: =_xlfn.XLOOKUP(tblSales[[#This Row],[Customer_ID]],Customers!$A:$A,Customers!$J:$J,"Unknown") -> Silver | AG150: =_xlfn.XLOOKUP(tblSales[[#This Row],[Employee_ID]],Employees!$A:$A,Employees!$B:$B,"Unknown") -> Anusuya Subramaniam | AH150: =IF(MONTH(tblSales[[#This Row],[Invoice Date]])>=4,MONTH(tblSales[[#This Row],[Invoice Date]]),MONTH(tblSales[[#This Row],[Invoice Date]])+12) -> 12 | AI150: =DATE(YEAR(tblSales[[#This Row],[Invoice Date]]),MONTH(tblSales[[#This Row],[Invoice Date]]),1) -> 45627 | AJ150: =_xlfn.XLOOKUP(tblSales[[#This Row],[Product_ID]],Products!$A:$A,Products!$B:$B,"Unknown") -> Raymond Leather Belt White | AK150: =IFERROR(tblSales[[#This Row],[Profit]]/tblSales[[#This Row],[Sales Amount]],0) -> 0.074984465 | AL150: =IF(tblSales[[#This Row],[Discount %]]<=5,"0-5%", IF(tblSales[[#This Row],[Discount %]]<=10,"5-10%", IF(tblSales[[#This Row],[Discount %]]<=15,"10-15%", IF(tblSales[[#This Row],[Discount %]]<=20,"15-20%","20%+")))) -> 10-15%
A151: INV100150 | B151: 45384 | C151: CUST0114 | D151: PRD0123 | E151: STR101 | F151: EMP0206 | G151: 2 | H151: 1150.4 | I151: 20 | J151: 460.16 | K151: 12 | L151: 220.88 | M151: 2061.52 | N151: 1474.7 | O151: =(M151-N151-L151) -> 365.94 | P151: Credit Card | Q151: =TRIM(CLEAN(P151)) -> Credit Card | R151: Offline | S151: Not Returned | T151: 21:32 | U151: Weekday | V151: =TEXT(tblSales[[#This Row],[Invoice Date]],"mmm") -> Apr | W151: =MONTH(tblSales[[#This Row],[Invoice Date]]) -> 4 | X151: =YEAR(tblSales[[#This Row],[Invoice Date]]) -> 2024 | Y151: =TEXT(tblSales[[#This Row],[Invoice Date]],"mmm-yyyy") -> Apr-2024 | Z151: =_xlfn.XLOOKUP(tblSales[[#This Row],[Product_ID]],Products!$A:$A,Products!$C:$C,"Women Dresses") -> Belts | AA151: =_xlfn.XLOOKUP(tblSales[[#This Row],[Product_ID]],Products!$A:$A,Products!$D:$D,"Unknown") -> Formal Belt | AB151: =_xlfn.XLOOKUP(tblSales[[#This Row],[Product_ID]],Products!$A:$A,Products!$E:$E,"Unknown") -> Wrangler | AC151: =_xlfn.XLOOKUP(tblSales[[#This Row],[Store_ID]],Stores!$A:$A,Stores!$B:$B,"Unknown") -> TrendMart Thiruvananthapuram Standard | AD151: =_xlfn.XLOOKUP(tblSales[[#This Row],[Store_ID]],Stores!$A:$A,Stores!$E:$E,"Unknown") -> South Zone 1 | AE151: =_xlfn.XLOOKUP(tblSales[[#This Row],[Customer_ID]],Customers!$A:$A,Customers!$B:$B,"Unknown") -> Manikandan Gupta | AF151: =_xlfn.XLOOKUP(tblSales[[#This Row],[Customer_ID]],Customers!$A:$A,Customers!$J:$J,"Unknown") -> Regular | AG151: =_xlfn.XLOOKUP(tblSales[[#This Row],[Employee_ID]],Employees!$A:$A,Employees!$B:$B,"Unknown") -> Arjun Krishnan | AH151: =IF(MONTH(tblSales[[#This Row],[Invoice Date]])>=4,MONTH(tblSales[[#This Row],[Invoice Date]]),MONTH(tblSales[[#This Row],[Invoice Date]])+12) -> 4 | AI151: =DATE(YEAR(tblSales[[#This Row],[Invoice Date]]),MONTH(tblSales[[#This Row],[Invoice Date]]),1) -> 45383 | AJ151: =_xlfn.XLOOKUP(tblSales[[#This Row],[Product_ID]],Products!$A:$A,Products!$B:$B,"Unknown") -> Wrangler Formal Belt Brown | AK151: =IFERROR(tblSales[[#This Row],[Profit]]/tblSales[[#This Row],[Sales Amount]],0) -> 0.1775098 | AL151: =IF(tblSales[[#This Row],[Discount %]]<=5,"0-5%", IF(tblSales[[#This Row],[Discount %]]<=10,"5-10%", IF(tblSales[[#This Row],[Discount %]]<=15,"10-15%", IF(tblSales[[#This Row],[Discount %]]<=20,"15-20%","20%+")))) -> 15-20%
A152: INV100151 | B152: 45655 | C152: CUST0654 | D152: PRD0043 | E152: STR118 | F152: EMP0225 | G152: 2 | H152: 3566.32 | I152: 0 | J152: 0 | K152: 12 | L152: 855.92 | M152: 7988.56 | N152: 4068.02 | O152: =(M152-N152-L152) -> 3064.62 | P152: Credit Card | Q152: =TRIM(CLEAN(P152)) -> Credit Card | R152: Offline | S152: Returned | T152: 10:30 | U152: Weekend | V152: =TEXT(tblSales[[#This Row],[Invoice Date]],"mmm") -> Dec | W152: =MONTH(tblSales[[#This Row],[Invoice Date]]) -> 12 | X152: =YEAR(tblSales[[#This Row],[Invoice Date]]) -> 2024 | Y152: =TEXT(tblSales[[#This Row],[Invoice Date]],"mmm-yyyy") -> Dec-2024 | Z152: =_xlfn.XLOOKUP(tblSales[[#This Row],[Product_ID]],Products!$A:$A,Products!$C:$C,"Women Dresses") -> Handbags | AA152: =_xlfn.XLOOKUP(tblSales[[#This Row],[Product_ID]],Products!$A:$A,Products!$D:$D,"Unknown") -> Sling Bag | AB152: =_xlfn.XLOOKUP(tblSales[[#This Row],[Product_ID]],Products!$A:$A,Products!$E:$E,"Unknown") -> GRT Jewellers | AC152: =_xlfn.XLOOKUP(tblSales[[#This Row],[Store_ID]],Stores!$A:$A,Stores!$B:$B,"Unknown") -> TrendMart Nellore Mall Kiosk | AD152: =_xlfn.XLOOKUP(tblSales[[#This Row],[Store_ID]],Stores!$A:$A,Stores!$E:$E,"Unknown") -> South Zone 3 | AE152: =_xlfn.XLOOKUP(tblSales[[#This Row],[Customer_ID]],Customers!$A:$A,Customers!$B:$B,"Unknown") -> Lakshmi Nair | AF152: =_xlfn.XLOOKUP(tblSales[[#This Row],[Customer_ID]],Customers!$A:$A,Customers!$J:$J,"Unknown") -> Regular | AG152: =_xlfn.XLOOKUP(tblSales[[#This Row],[Employee_ID]],Employees!$A:$A,Employees!$B:$B,"Unknown") -> Swathi Achari | AH152: =IF(MONTH(tblSales[[#This Row],[Invoice Date]])>=4,MONTH(tblSales[[#This Row],[Invoice Date]]),MONTH(tblSales[[#This Row],[Invoice Date]])+12) -> 12 | AI152: =DATE(YEAR(tblSales[[#This Row],[Invoice Date]]),MONTH(tblSales[[#This Row],[Invoice Date]]),1) -> 45627 | AJ152: =_xlfn.XLOOKUP(tblSales[[#This Row],[Product_ID]],Products!$A:$A,Products!$B:$B,"Unknown") -> GRT Jewellers Sling Bag Olive | AK152: =IFERROR(tblSales[[#This Row],[Profit]]/tblSales[[#This Row],[Sales Amount]],0) -> 0.38362609 | AL152: =IF(tblSales[[#This Row],[Discount %]]<=5,"0-5%", IF(tblSales[[#This Row],[Discount %]]<=10,"5-10%", IF(tblSales[[#This Row],[Discount %]]<=15,"10-15%", IF(tblSales[[#This Row],[Discount %]]<=20,"15-20%","20%+")))) -> 0-5%
A153: INV100152 | B153: 45467 | C153: CUST0676 | D153: PRD0235 | E153: STR020 | F153: EMP0240 | G153: 1 | H153: 1908.46 | I153: 5 | J153: 95.42 | K153: 12 | L153: 217.56 | M153: 2030.6 | N153: 1378.38 | O153: =(M153-N153-L153) -> 434.66 | P153: Cash | Q153: =TRIM(CLEAN(P153)) -> Cash | R153: Online | S153: Not Returned | T153: 17:20 | U153: Weekday | V153: =TEXT(tblSales[[#This Row],[Invoice Date]],"mmm") -> Jun | W153: =MONTH(tblSales[[#This Row],[Invoice Date]]) -> 6 | X153: =YEAR(tblSales[[#This Row],[Invoice Date]]) -> 2024 | Y153: =TEXT(tblSales[[#This Row],[Invoice Date]],"mmm-yyyy") -> Jun-2024 | Z153: =_xlfn.XLOOKUP(tblSales[[#This Row],[Product_ID]],Products!$A:$A,Products!$C:$C,"Women Dresses") -> Women Sarees | AA153: =_xlfn.XLOOKUP(tblSales[[#This Row],[Product_ID]],Products!$A:$A,Products!$D:$D,"Unknown") -> Georgette Saree | AB153: =_xlfn.XLOOKUP(tblSales[[#This Row],[Product_ID]],Products!$A:$A,Products!$E:$E,"Unknown") -> Reebok | AC153: =_xlfn.XLOOKUP(tblSales[[#This Row],[Store_ID]],Stores!$A:$A,Stores!$B:$B,"Unknown") -> TrendMart Guntur Standard | AD153: =_xlfn.XLOOKUP(tblSales[[#This Row],[Store_ID]],Stores!$A:$A,Stores!$E:$E,"Unknown") -> South Zone 3 | AE153: =_xlfn.XLOOKUP(tblSales[[#This Row],[Customer_ID]],Customers!$A:$A,Customers!$B:$B,"Unknown") -> Dinesh Chandran | AF153: =_xlfn.XLOOKUP(tblSales[[#This Row],[Customer_ID]],Customers!$A:$A,Customers!$J:$J,"Unknown") -> Platinum | AG153: =_xlfn.XLOOKUP(tblSales[[#This Row],[Employee_ID]],Employees!$A:$A,Employees!$B:$B,"Unknown") -> Gopal Prasad | AH153: =IF(MONTH(tblSales[[#This Row],[Invoice Date]])>=4,MONTH(tblSales[[#This Row],[Invoice Date]]),MONTH(tblSales[[#This Row],[Invoice Date]])+12) -> 6 | AI153: =DATE(YEAR(tblSales[[#This Row],[Invoice Date]]),MONTH(tblSales[[#This Row],[Invoice Date]]),1) -> 45444 | AJ153: =_xlfn.XLOOKUP(tblSales[[#This Row],[Product_ID]],Products!$A:$A,Products!$B:$B,"Unknown") -> Reebok Georgette Saree Charcoal | AK153: =IFERROR(tblSales[[#This Row],[Profit]]/tblSales[[#This Row],[Sales Amount]],0) -> 0.21405496 | AL153: =IF(tblSales[[#This Row],[Discount %]]<=5,"0-5%", IF(tblSales[[#This Row],[Discount %]]<=10,"5-10%", IF(tblSales[[#This Row],[Discount %]]<=15,"10-15%", IF(tblSales[[#This Row],[Discount %]]<=20,"15-20%","20%+")))) -> 0-5%
A154: INV100153 | B154: 45577 | C154: CUST0033 | D154: PRD0062 | E154: STR001 | F154: EMP0240 | G154: 2 | H154: 610.55 | I154: 15 | J154: 183.16 | K154: 5 | L154: 51.9 | M154: 1089.84 | N154: 849.52 | O154: =(M154-N154-L154) -> 188.42 | P154: UPI | Q154: =TRIM(CLEAN(P154)) -> UPI | R154: Offline | S154: Not Returned | T154: 11:59 | U154: Weekend | V154: =TEXT(tblSales[[#This Row],[Invoice Date]],"mmm") -> Oct | W154: =MONTH(tblSales[[#This Row],[Invoice Date]]) -> 10 | X154: =YEAR(tblSales[[#This Row],[Invoice Date]]) -> 2024 | Y154: =TEXT(tblSales[[#This Row],[Invoice Date]],"mmm-yyyy") -> Oct-2024 | Z154: =_xlfn.XLOOKUP(tblSales[[#This Row],[Product_ID]],Products!$A:$A,Products!$C:$C,"Women Dresses") -> Kids Wear | AA154: =_xlfn.XLOOKUP(tblSales[[#This Row],[Product_ID]],Products!$A:$A,Products!$D:$D,"Unknown") -> Girls Frock | AB154: =_xlfn.XLOOKUP(tblSales[[#This Row],[Product_ID]],Products!$A:$A,Products!$E:$E,"Unknown") -> Being Human | AC154: =_xlfn.XLOOKUP(tblSales[[#This Row],[Store_ID]],Stores!$A:$A,Stores!$B:$B,"Unknown") -> TrendMart Kollam Standard | AD154: =_xlfn.XLOOKUP(tblSales[[#This Row],[Store_ID]],Stores!$A:$A,Stores!$E:$E,"Unknown") -> South Zone 1 | AE154: =_xlfn.XLOOKUP(tblSales[[#This Row],[Customer_ID]],Customers!$A:$A,Customers!$B:$B,"Unknown") -> Vidya Varma | AF154: =_xlfn.XLOOKUP(tblSales[[#This Row],[Customer_ID]],Customers!$A:$A,Customers!$J:$J,"Unknown") -> Regular | AG154: =_xlfn.XLOOKUP(tblSales[[#This Row],[Employee_ID]],Employees!$A:$A,Employees!$B:$B,"Unknown") -> Gopal Prasad | AH154: =IF(MONTH(tblSales[[#This Row],[Invoice Date]])>=4,MONTH(tblSales[[#This Row],[Invoice Date]]),MONTH(tblSales[[#This Row],[Invoice Date]])+12) -> 10 | AI154: =DATE(YEAR(tblSales[[#This Row],[Invoice Date]]),MONTH(tblSales[[#This Row],[Invoice Date]]),1) -> 45566 | AJ154: =_xlfn.XLOOKUP(tblSales[[#This Row],[Product_ID]],Products!$A:$A,Products!$B:$B,"Unknown") -> Being Human Girls Frock Teal | AK154: =IFERROR(tblSales[[#This Row],[Profit]]/tblSales[[#This Row],[Sales Amount]],0) -> 0.17288776 | AL154: =IF(tblSales[[#This Row],[Discount %]]<=5,"0-5%", IF(tblSales[[#This Row],[Discount %]]<=10,"5-10%", IF(tblSales[[#This Row],[Discount %]]<=15,"10-15%", IF(tblSales[[#This Row],[Discount %]]<=20,"15-20%","20%+")))) -> 10-15%
A155: INV100154 | B155: 45623 | C155: CUST0327 | D155: PRD0048 | E155: STR117 | F155: EMP0063 | G155: 3 | H155: 1026.23 | I155: 5 | J155: 153.93 | K155: 12 | L155: 350.97 | M155: 3275.73 | N155: 1751.58 | O155: =(M155-N155-L155) -> 1173.18 | P155: UPI | Q155: =TRIM(CLEAN(P155)) -> UPI | R155: Offline | S155: Returned | T155: 16:18 | U155: Weekday | V155: =TEXT(tblSales[[#This Row],[Invoice Date]],"mmm") -> Nov | W155: =MONTH(tblSales[[#This Row],[Invoice Date]]) -> 11 | X155: =YEAR(tblSales[[#This Row],[Invoice Date]]) -> 2024 | Y155: =TEXT(tblSales[[#This Row],[Invoice Date]],"mmm-yyyy") -> Nov-2024 | Z155: =_xlfn.XLOOKUP(tblSales[[#This Row],[Product_ID]],Products!$A:$A,Products!$C:$C,"Women Dresses") -> Accessories | AA155: =_xlfn.XLOOKUP(tblSales[[#This Row],[Product_ID]],Products!$A:$A,Products!$D:$D,"Unknown") -> Tie | AB155: =_xlfn.XLOOKUP(tblSales[[#This Row],[Product_ID]],Products!$A:$A,Products!$E:$E,"Unknown") -> Being Human | AC155: =_xlfn.XLOOKUP(tblSales[[#This Row],[Store_ID]],Stores!$A:$A,Stores!$B:$B,"Unknown") -> TrendMart Tirunelveli Flagship | AD155: =_xlfn.XLOOKUP(tblSales[[#This Row],[Store_ID]],Stores!$A:$A,Stores!$E:$E,"Unknown") -> South Zone 1 | AE155: =_xlfn.XLOOKUP(tblSales[[#This Row],[Customer_ID]],Customers!$A:$A,Customers!$B:$B,"Unknown") -> Manju Varma | AF155: =_xlfn.XLOOKUP(tblSales[[#This Row],[Customer_ID]],Customers!$A:$A,Customers!$J:$J,"Unknown") -> Gold | AG155: =_xlfn.XLOOKUP(tblSales[[#This Row],[Employee_ID]],Employees!$A:$A,Employees!$B:$B,"Unknown") -> Anusuya Subramaniam | AH155: =IF(MONTH(tblSales[[#This Row],[Invoice Date]])>=4,MONTH(tblSales[[#This Row],[Invoice Date]]),MONTH(tblSales[[#This Row],[Invoice Date]])+12) -> 11 | AI155: =DATE(YEAR(tblSales[[#This Row],[Invoice Date]]),MONTH(tblSales[[#This Row],[Invoice Date]]),1) -> 45597 | AJ155: =_xlfn.XLOOKUP(tblSales[[#This Row],[Product_ID]],Products!$A:$A,Products!$B:$B,"Unknown") -> Indian Terrain Denim Shirt Wine | AK155: =IFERROR(tblSales[[#This Row],[Profit]]/tblSales[[#This Row],[Sales Amount]],0) -> 0.35814307 | AL155: =IF(tblSales[[#This Row],[Discount %]]<=5,"0-5%", IF(tblSales[[#This Row],[Discount %]]<=10,"5-10%", IF(tblSales[[#This Row],[Discount %]]<=15,"10-15%", IF(tblSales[[#This Row],[Discount %]]<=20,"15-20%","20%+")))) -> 0-5%
A156: INV100155 | B156: 45618 | C156: CUST0614 | D156: PRD0025 | E156: STR091 | F156: EMP0002 | G156: 2 | H156: 1322.6 | I156: 0 | J156: 0 | K156: 12 | L156: 317.42 | M156: 2962.62 | N156: 2050.48 | O156: =(M156-N156-L156) -> 594.72 | P156: Net Banking | Q156: =TRIM(CLEAN(P156)) -> Net Banking | R156: Online | S156: Not Returned | T156: 19:18 | U156: Weekday | V156: =TEXT(tblSales[[#This Row],[Invoice Date]],"mmm") -> Nov | W156: =MONTH(tblSales[[#This Row],[Invoice Date]]) -> 11 | X156: =YEAR(tblSales[[#This Row],[Invoice Date]]) -> 2024 | Y156: =TEXT(tblSales[[#This Row],[Invoice Date]],"mmm-yyyy") -> Nov-2024 | Z156: =_xlfn.XLOOKUP(tblSales[[#This Row],[Product_ID]],Products!$A:$A,Products!$C:$C,"Women Dresses") -> Women Jeans | AA156: =_xlfn.XLOOKUP(tblSales[[#This Row],[Product_ID]],Products!$A:$A,Products!$D:$D,"Unknown") -> Straight Fit | AB156: =_xlfn.XLOOKUP(tblSales[[#This Row],[Product_ID]],Products!$A:$A,Products!$E:$E,"Unknown") -> Pothys | AC156: =_xlfn.XLOOKUP(tblSales[[#This Row],[Store_ID]],Stores!$A:$A,Stores!$B:$B,"Unknown") -> TrendMart Nizamabad Standard | AD156: =_xlfn.XLOOKUP(tblSales[[#This Row],[Store_ID]],Stores!$A:$A,Stores!$E:$E,"Unknown") -> South Zone 2 | AE156: =_xlfn.XLOOKUP(tblSales[[#This Row],[Customer_ID]],Customers!$A:$A,Customers!$B:$B,"Unknown") -> Deepthi Gupta | AF156: =_xlfn.XLOOKUP(tblSales[[#This Row],[Customer_ID]],Customers!$A:$A,Customers!$J:$J,"Unknown") -> Regular | AG156: =_xlfn.XLOOKUP(tblSales[[#This Row],[Employee_ID]],Employees!$A:$A,Employees!$B:$B,"Unknown") -> Girish Sundaram | AH156: =IF(MONTH(tblSales[[#This Row],[Invoice Date]])>=4,MONTH(tblSales[[#This Row],[Invoice Date]]),MONTH(tblSales[[#This Row],[Invoice Date]])+12) -> 11 | AI156: =DATE(YEAR(tblSales[[#This Row],[Invoice Date]]),MONTH(tblSales[[#This Row],[Invoice Date]]),1) -> 45597 | AJ156: =_xlfn.XLOOKUP(tblSales[[#This Row],[Product_ID]],Products!$A:$A,Products!$B:$B,"Unknown") -> Pothys Straight Fit Charcoal | AK156: =IFERROR(tblSales[[#This Row],[Profit]]/tblSales[[#This Row],[Sales Amount]],0) -> 0.20074124 | AL156: =IF(tblSales[[#This Row],[Discount %]]<=5,"0-5%", IF(tblSales[[#This Row],[Discount %]]<=10,"5-10%", IF(tblSales[[#This Row],[Discount %]]<=15,"10-15%", IF(tblSales[[#This Row],[Discount %]]<=20,"15-20%","20%+")))) -> 0-5%
... A356: INV100355 | B356: 45604 | C356: CUST0725 | D356: PRD0141 | E356: STR094 | F356: EMP0215 | G356: 2 | H356: 751.36 | I356: 20 | J356: 300.54 | K356: 5 | L356: 60.11 | M356: 1262.29 | N356: 1095.34 | O356: =(M356-N356-L356) -> 106.84 | P356: UPI | Q356: =TRIM(CLEAN(P356)) -> UPI | R356: Offline | S356: Not Returned | T356: 12:43 | U356: Weekday | V356: =TEXT(tblSales[[#This Row],[Invoice Date]],"mmm") -> Nov | W356: =MONTH(tblSales[[#This Row],[Invoice Date]]) -> 11 | X356: =YEAR(tblSales[[#This Row],[Invoice Date]]) -> 2024 | Y356: =TEXT(tblSales[[#This Row],[Invoice Date]],"mmm-yyyy") -> Nov-2024 | Z356: =_xlfn.XLOOKUP(tblSales[[#This Row],[Product_ID]],Products!$A:$A,Products!$C:$C,"Women Dresses") -> Women Tops | AA356: =_xlfn.XLOOKUP(tblSales[[#This Row],[Product_ID]],Products!$A:$A,Products!$D:$D,"Unknown") -> Formal Top | AB356: =_xlfn.XLOOKUP(tblSales[[#This Row],[Product_ID]],Products!$A:$A,Products!$E:$E,"Unknown") -> Indian Terrain | AC356: =_xlfn.XLOOKUP(tblSales[[#This Row],[Store_ID]],Stores!$A:$A,Stores!$B:$B,"Unknown") -> TrendMart Kollam Flagship | AD356: =_xlfn.XLOOKUP(tblSales[[#This Row],[Store_ID]],Stores!$A:$A,Stores!$E:$E,"Unknown") -> South Zone 1 | AE356: =_xlfn.XLOOKUP(tblSales[[#This Row],[Customer_ID]],Customers!$A:$A,Customers!$B:$B,"Unknown") -> Padma Gopalakrishnan | AF356: =_xlfn.XLOOKUP(tblSales[[#This Row],[Customer_ID]],Customers!$A:$A,Customers!$J:$J,"Unknown") -> Silver | AG356: =_xlfn.XLOOKUP(tblSales[[#This Row],[Employee_ID]],Employees!$A:$A,Employees!$B:$B,"Unknown") -> Praveen Gupta | AH356: =IF(MONTH(tblSales[[#This Row],[Invoice Date]])>=4,MONTH(tblSales[[#This Row],[Invoice Date]]),MONTH(tblSales[[#This Row],[Invoice Date]])+12) -> 11 | AI356: =DATE(YEAR(tblSales[[#This Row],[Invoice Date]]),MONTH(tblSales[[#This Row],[Invoice Date]]),1) -> 45597 | AJ356: =_xlfn.XLOOKUP(tblSales[[#This Row],[Product_ID]],Products!$A:$A,Products!$B:$B,"Unknown") -> Indian Terrain Formal Top Maroon | AK356: =IFERROR(tblSales[[#This Row],[Profit]]/tblSales[[#This Row],[Sales Amount]],0) -> 0.084639821 | AL356: =IF(tblSales[[#This Row],[Discount %]]<=5,"0-5%", IF(tblSales[[#This Row],[Discount %]]<=10,"5-10%", IF(tblSales[[#This Row],[Discount %]]<=15,"10-15%", IF(tblSales[[#This Row],[Discount %]]<=20,"15-20%","20%+")))) -> 15-20%
A357: INV100355 | B357: 45447 | C357: CUST0084 | D357: PRD0055 | E357: STR047 | F357: EMP0026 | G357: 0 | H357: 1453.56 | I357: 15 | J357: 0 | K357: 12 | L357: 0 | M357: 0 | N357: 0 | O357: 0 | P357: Cash | Q357: =TRIM(CLEAN(P357)) -> Cash | R357: Online | S357: Returned | T357: 18:20 | U357: Weekday | V357: =TEXT(tblSales[[#This Row],[Invoice Date]],"mmm") -> Jun | W357: =MONTH(tblSales[[#This Row],[Invoice Date]]) -> 6 | X357: =YEAR(tblSales[[#This Row],[Invoice Date]]) -> 2024 | Y357: =TEXT(tblSales[[#This Row],[Invoice Date]],"mmm-yyyy") -> Jun-2024 | Z357: =_xlfn.XLOOKUP(tblSales[[#This Row],[Product_ID]],Products!$A:$A,Products!$C:$C,"Women Dresses") -> Sportswear | AA357: =_xlfn.XLOOKUP(tblSales[[#This Row],[Product_ID]],Products!$A:$A,Products!$D:$D,"Unknown") -> Sports T-Shirt | AB357: =_xlfn.XLOOKUP(tblSales[[#This Row],[Product_ID]],Products!$A:$A,Products!$E:$E,"Unknown") -> GRT Jewellers | AC357: =_xlfn.XLOOKUP(tblSales[[#This Row],[Store_ID]],Stores!$A:$A,Stores!$B:$B,"Unknown") -> TrendMart Kurnool Standard | AD357: =_xlfn.XLOOKUP(tblSales[[#This Row],[Store_ID]],Stores!$A:$A,Stores!$E:$E,"Unknown") -> South Zone 3 | AE357: =_xlfn.XLOOKUP(tblSales[[#This Row],[Customer_ID]],Customers!$A:$A,Customers!$B:$B,"Unknown") -> Hari Kamath | AF357: =_xlfn.XLOOKUP(tblSales[[#This Row],[Customer_ID]],Customers!$A:$A,Customers!$J:$J,"Unknown") -> Platinum | AG357: =_xlfn.XLOOKUP(tblSales[[#This Row],[Employee_ID]],Employees!$A:$A,Employees!$B:$B,"Unknown") -> Sunita Ramachandran | AH357: =IF(MONTH(tblSales[[#This Row],[Invoice Date]])>=4,MONTH(tblSales[[#This Row],[Invoice Date]]),MONTH(tblSales[[#This Row],[Invoice Date]])+12) -> 6 | AI357: =DATE(YEAR(tblSales[[#This Row],[Invoice Date]]),MONTH(tblSales[[#This Row],[Invoice Date]]),1) -> 45444 | AJ357: =_xlfn.XLOOKUP(tblSales[[#This Row],[Product_ID]],Products!$A:$A,Products!$B:$B,"Unknown") -> GRT Jewellers Sports T-Shirt Cream | AK357: =IFERROR(tblSales[[#This Row],[Profit]]/tblSales[[#This Row],[Sales Amount]],0) -> 0 | AL357: =IF(tblSales[[#This Row],[Discount %]]<=5,"0-5%", IF(tblSales[[#This Row],[Discount %]]<=10,"5-10%", IF(tblSales[[#This Row],[Discount %]]<=15,"10-15%", IF(tblSales[[#This Row],[Discount %]]<=20,"15-20%","20%+")))) -> 10-15%
A358: INV100356 | B358: 45469 | C358: CUST0331 | D358: PRD0128 | E358: STR105 | F358: EMP0020 | G358: 2 | H358: 1329.24 | I358: 30 | J358: 797.54 | K358: 12 | L358: 223.31 | M358: 2084.25 | N358: 1689.3 | O358: =(M358-N358-L358) -> 171.64 | P358: Debit Card | Q358: =TRIM(CLEAN(P358)) -> Debit Card | R358: Offline | S358: Not Returned | T358: 15:51 | U358: Weekday | V358: =TEXT(tblSales[[#This Row],[Invoice Date]],"mmm") -> Jun | W358: =MONTH(tblSales[[#This Row],[Invoice Date]]) -> 6 | X358: =YEAR(tblSales[[#This Row],[Invoice Date]]) -> 2024 | Y358: =TEXT(tblSales[[#This Row],[Invoice Date]],"mmm-yyyy") -> Jun-2024 | Z358: =_xlfn.XLOOKUP(tblSales[[#This Row],[Product_ID]],Products!$A:$A,Products!$C:$C,"Women Dresses") -> Women Kurtis | AA358: =_xlfn.XLOOKUP(tblSales[[#This Row],[Product_ID]],Products!$A:$A,Products!$D:$D,"Unknown") -> Straight Kurti | AB358: =_xlfn.XLOOKUP(tblSales[[#This Row],[Product_ID]],Products!$A:$A,Products!$E:$E,"Unknown") -> Woodland | AC358: =_xlfn.XLOOKUP(tblSales[[#This Row],[Store_ID]],Stores!$A:$A,Stores!$B:$B,"Unknown") -> TrendMart Coimbatore Mall Kiosk | AD358: =_xlfn.XLOOKUP(tblSales[[#This Row],[Store_ID]],Stores!$A:$A,Stores!$E:$E,"Unknown") -> South Zone 1 | AE358: =_xlfn.XLOOKUP(tblSales[[#This Row],[Customer_ID]],Customers!$A:$A,Customers!$B:$B,"Unknown") -> Anjali Bhat | AF358: =_xlfn.XLOOKUP(tblSales[[#This Row],[Customer_ID]],Customers!$A:$A,Customers!$J:$J,"Unknown") -> Silver | AG358: =_xlfn.XLOOKUP(tblSales[[#This Row],[Employee_ID]],Employees!$A:$A,Employees!$B:$B,"Unknown") -> Eswar Prasad | AH358: =IF(MONTH(tblSales[[#This Row],[Invoice Date]])>=4,MONTH(tblSales[[#This Row],[Invoice Date]]),MONTH(tblSales[[#This Row],[Invoice Date]])+12) -> 6 | AI358: =DATE(YEAR(tblSales[[#This Row],[Invoice Date]]),MONTH(tblSales[[#This Row],[Invoice Date]]),1) -> 45444 | AJ358: =_xlfn.XLOOKUP(tblSales[[#This Row],[Product_ID]],Products!$A:$A,Products!$B:$B,"Unknown") -> Woodland Straight Kurti White | AK358: =IFERROR(tblSales[[#This Row],[Profit]]/tblSales[[#This Row],[Sales Amount]],0) -> 0.082350966 | AL358: =IF(tblSales[[#This Row],[Discount %]]<=5,"0-5%", IF(tblSales[[#This Row],[Discount %]]<=10,"5-10%", IF(tblSales[[#This Row],[Discount %]]<=15,"10-15%", IF(tblSales[[#This Row],[Discount %]]<=20,"15-20%","20%+")))) -> 20%+
A359: INV100357 | B359: 45529 | C359: CUST0645 | D359: PRD0141 | E359: STR076 | F359: EMP0160 | G359: 1 | H359: 815.61 | I359: 15 | J359: 122.34 | K359: 5 | L359: 34.66 | M359: 727.93 | N359: 547.67 | O359: =(M359-N359-L359) -> 145.6 | P359: UPI | Q359: =TRIM(CLEAN(P359)) -> UPI | R359: Online | S359: Not Returned | T359: 11:33 | U359: Weekend | V359: =TEXT(tblSales[[#This Row],[Invoice Date]],"mmm") -> Aug | W359: =MONTH(tblSales[[#This Row],[Invoice Date]]) -> 8 | X359: =YEAR(tblSales[[#This Row],[Invoice Date]]) -> 2024 | Y359: =TEXT(tblSales[[#This Row],[Invoice Date]],"mmm-yyyy") -> Aug-2024 | Z359: =_xlfn.XLOOKUP(tblSales[[#This Row],[Product_ID]],Products!$A:$A,Products!$C:$C,"Women Dresses") -> Women Tops | AA359: =_xlfn.XLOOKUP(tblSales[[#This Row],[Product_ID]],Products!$A:$A,Products!$D:$D,"Unknown") -> Formal Top | AB359: =_xlfn.XLOOKUP(tblSales[[#This Row],[Product_ID]],Products!$A:$A,Products!$E:$E,"Unknown") -> Indian Terrain | AC359: =_xlfn.XLOOKUP(tblSales[[#This Row],[Store_ID]],Stores!$A:$A,Stores!$B:$B,"Unknown") -> TrendMart Chennai Standard | AD359: =_xlfn.XLOOKUP(tblSales[[#This Row],[Store_ID]],Stores!$A:$A,Stores!$E:$E,"Unknown") -> South Zone 1 | AE359: =_xlfn.XLOOKUP(tblSales[[#This Row],[Customer_ID]],Customers!$A:$A,Customers!$B:$B,"Unknown") -> Ganapathy Hegde | AF359: =_xlfn.XLOOKUP(tblSales[[#This Row],[Customer_ID]],Customers!$A:$A,Customers!$J:$J,"Unknown") -> Silver | AG359: =_xlfn.XLOOKUP(tblSales[[#This Row],[Employee_ID]],Employees!$A:$A,Employees!$B:$B,"Unknown") -> Ganesh Iyengar | AH359: =IF(MONTH(tblSales[[#This Row],[Invoice Date]])>=4,MONTH(tblSales[[#This Row],[Invoice Date]]),MONTH(tblSales[[#This Row],[Invoice Date]])+12) -> 8 | AI359: =DATE(YEAR(tblSales[[#This Row],[Invoice Date]]),MONTH(tblSales[[#This Row],[Invoice Date]]),1) -> 45505 | AJ359: =_xlfn.XLOOKUP(tblSales[[#This Row],[Product_ID]],Products!$A:$A,Products!$B:$B,"Unknown") -> Indian Terrain Formal Top Maroon | AK359: =IFERROR(tblSales[[#This Row],[Profit]]/tblSales[[#This Row],[Sales Amount]],0) -> 0.20001923 | AL359: =IF(tblSales[[#This Row],[Discount %]]<=5,"0-5%", IF(tblSales[[#This Row],[Discount %]]<=10,"5-10%", IF(tblSales[[#This Row],[Discount %]]<=15,"10-15%", IF(tblSales[[#This Row],[Discount %]]<=20,"15-20%","20%+")))) -> 10-15%
A360: INV100358 | B360: 45644 | C360: CUST0351 | D360: PRD0227 | E360: STR011 | F360: EMP0204 | G360: 4 | H360: 721.33 | I360: 15 | J360: 432.8 | K360: 5 | L360: 122.63 | M360: 2575.15 | N360: 1772.76 | O360: =(M360-N360-L360) -> 679.76 | P360: Debit Card | Q360: =TRIM(CLEAN(P360)) -> Debit Card | R360: Online | S360: Not Returned | T360: 20:41 | U360: Weekday | V360: =TEXT(tblSales[[#This Row],[Invoice Date]],"mmm") -> Dec | W360: =MONTH(tblSales[[#This Row],[Invoice Date]]) -> 12 | X360: =YEAR(tblSales[[#This Row],[Invoice Date]]) -> 2024 | Y360: =TEXT(tblSales[[#This Row],[Invoice Date]],"mmm-yyyy") -> Dec-2024 | Z360: =_xlfn.XLOOKUP(tblSales[[#This Row],[Product_ID]],Products!$A:$A,Products!$C:$C,"Women Dresses") -> Accessories | AA360: =_xlfn.XLOOKUP(tblSales[[#This Row],[Product_ID]],Products!$A:$A,Products!$D:$D,"Unknown") -> Tie | AB360: =_xlfn.XLOOKUP(tblSales[[#This Row],[Product_ID]],Products!$A:$A,Products!$E:$E,"Unknown") -> Allen Solly | AC360: =_xlfn.XLOOKUP(tblSales[[#This Row],[Store_ID]],Stores!$A:$A,Stores!$B:$B,"Unknown") -> TrendMart Tirupati Standard | AD360: =_xlfn.XLOOKUP(tblSales[[#This Row],[Store_ID]],Stores!$A:$A,Stores!$E:$E,"Unknown") -> South Zone 3 | AE360: =_xlfn.XLOOKUP(tblSales[[#This Row],[Customer_ID]],Customers!$A:$A,Customers!$B:$B,"Unknown") -> Tara Subramaniam | AF360: =_xlfn.XLOOKUP(tblSales[[#This Row],[Customer_ID]],Customers!$A:$A,Customers!$J:$J,"Unknown") -> Platinum | AG360: =_xlfn.XLOOKUP(tblSales[[#This Row],[Employee_ID]],Employees!$A:$A,Employees!$B:$B,"Unknown") -> Rahul Krishnan | AH360: =IF(MONTH(tblSales[[#This Row],[Invoice Date]])>=4,MONTH(tblSales[[#This Row],[Invoice Date]]),MONTH(tblSales[[#This Row],[Invoice Date]])+12) -> 12 | AI360: =DATE(YEAR(tblSales[[#This Row],[Invoice Date]]),MONTH(tblSales[[#This Row],[Invoice Date]]),1) -> 45627 | AJ360: =_xlfn.XLOOKUP(tblSales[[#This Row],[Product_ID]],Products!$A:$A,Products!$B:$B,"Unknown") -> Allen Solly Tie Pink | AK360: =IFERROR(tblSales[[#This Row],[Profit]]/tblSales[[#This Row],[Sales Amount]],0) -> 0.26396909 | AL360: =IF(tblSales[[#This Row],[Discount %]]<=5,"0-5%", IF(tblSales[[#This Row],[Discount %]]<=10,"5-10%", IF(tblSales[[#This Row],[Discount %]]<=15,"10-15%", IF(tblSales[[#This Row],[Discount %]]<=20,"15-20%","20%+")))) -> 10-15%
A361: INV100359 | B361: 45603 | C361: CUST0526 | D361: PRD0146 | E361: STR037 | F361: EMP0127 | G361: 4 | H361: 6217 | I361: 10 | J361: 2486.8 | K361: 12 | L361: 2685.74 | M361: 25066.94 | N361: 15846.48 | O361: =(M361-N361-L361) -> 6534.72 | P361: UPI | Q361: =TRIM(CLEAN(P361)) -> UPI | R361: Offline | S361: Not Returned | T361: 10:04 | U361: Weekday | V361: =TEXT(tblSales[[#This Row],[Invoice Date]],"mmm") -> Nov | W361: =MONTH(tblSales[[#This Row],[Invoice Date]]) -> 11 | X361: =YEAR(tblSales[[#This Row],[Invoice Date]]) -> 2024 | Y361: =TEXT(tblSales[[#This Row],[Invoice Date]],"mmm-yyyy") -> Nov-2024 | Z361: =_xlfn.XLOOKUP(tblSales[[#This Row],[Product_ID]],Products!$A:$A,Products!$C:$C,"Women Dresses") -> Watches | AA361: =_xlfn.XLOOKUP(tblSales[[#This Row],[Product_ID]],Products!$A:$A,Products!$D:$D,"Unknown") -> Digital Watch | AB361: =_xlfn.XLOOKUP(tblSales[[#This Row],[Product_ID]],Products!$A:$A,Products!$E:$E,"Unknown") -> Metro Shoes | AC361: =_xlfn.XLOOKUP(tblSales[[#This Row],[Store_ID]],Stores!$A:$A,Stores!$B:$B,"Unknown") -> TrendMart Vijayawada High Street | AD361: =_xlfn.XLOOKUP(tblSales[[#This Row],[Store_ID]],Stores!$A:$A,Stores!$E:$E,"Unknown") -> South Zone 3 | AE361: =_xlfn.XLOOKUP(tblSales[[#This Row],[Customer_ID]],Customers!$A:$A,Customers!$B:$B,"Unknown") -> Manikandan Chettiar | AF361: =_xlfn.XLOOKUP(tblSales[[#This Row],[Customer_ID]],Customers!$A:$A,Customers!$J:$J,"Unknown") -> Regular | AG361: =_xlfn.XLOOKUP(tblSales[[#This Row],[Employee_ID]],Employees!$A:$A,Employees!$B:$B,"Unknown") -> Chandra Reddy | AH361: =IF(MONTH(tblSales[[#This Row],[Invoice Date]])>=4,MONTH(tblSales[[#This Row],[Invoice Date]]),MONTH(tblSales[[#This Row],[Invoice Date]])+12) -> 11 | AI361: =DATE(YEAR(tblSales[[#This Row],[Invoice Date]]),MONTH(tblSales[[#This Row],[Invoice Date]]),1) -> 45597 | AJ361: =_xlfn.XLOOKUP(tblSales[[#This Row],[Product_ID]],Products!$A:$A,Products!$B:$B,"Unknown") -> Metro Shoes Digital Watch Beige | AK361: =IFERROR(tblSales[[#This Row],[Profit]]/tblSales[[#This Row],[Sales Amount]],0) -> 0.26069077 | AL361: =IF(tblSales[[#This Row],[Discount %]]<=5,"0-5%", IF(tblSales[[#This Row],[Discount %]]<=10,"5-10%", IF(tblSales[[#This Row],[Discount %]]<=15,"10-15%", IF(tblSales[[#This Row],[Discount %]]<=20,"15-20%","20%+")))) -> 5-10%
A362: INV100360 | B362: 45572 | C362: CUST0100 | D362: PRD0072 | E362: STR014 | F362: EMP0225 | G362: 1 | H362: 859.03 | I362: 10 | J362: 85.9 | K362: 5 | L362: 38.66 | M362: 811.79 | N362: 599.28 | O362: =(M362-N362-L362) -> 173.85 | P362: UPI | Q362: =TRIM(CLEAN(P362)) -> UPI | R362: Online | S362: Not Returned | T362: 16:58 | U362: Weekday | V362: =TEXT(tblSales[[#This Row],[Invoice Date]],"mmm") -> Oct | W362: =MONTH(tblSales[[#This Row],[Invoice Date]]) -> 10 | X362: =YEAR(tblSales[[#This Row],[Invoice Date]]) -> 2024 | Y362: =TEXT(tblSales[[#This Row],[Invoice Date]],"mmm-yyyy") -> Oct-2024 | Z362: =_xlfn.XLOOKUP(tblSales[[#This Row],[Product_ID]],Products!$A:$A,Products!$C:$C,"Women Dresses") -> Women Kurtis | AA362: =_xlfn.XLOOKUP(tblSales[[#This Row],[Product_ID]],Products!$A:$A,Products!$D:$D,"Unknown") -> Straight Kurti | AB362: =_xlfn.XLOOKUP(tblSales[[#This Row],[Product_ID]],Products!$A:$A,Products!$E:$E,"Unknown") -> Metro Shoes | AC362: =_xlfn.XLOOKUP(tblSales[[#This Row],[Store_ID]],Stores!$A:$A,Stores!$B:$B,"Unknown") -> TrendMart Tirupati Outlet | AD362: =_xlfn.XLOOKUP(tblSales[[#This Row],[Store_ID]],Stores!$A:$A,Stores!$E:$E,"Unknown") -> South Zone 3 | AE362: =_xlfn.XLOOKUP(tblSales[[#This Row],[Customer_ID]],Customers!$A:$A,Customers!$B:$B,"Unknown") -> Chidambaram Rao | AF362: =_xlfn.XLOOKUP(tblSales[[#This Row],[Customer_ID]],Customers!$A:$A,Customers!$J:$J,"Unknown") -> Platinum | AG362: =_xlfn.XLOOKUP(tblSales[[#This Row],[Employee_ID]],Employees!$A:$A,Employees!$B:$B,"Unknown") -> Swathi Achari | AH362: =IF(MONTH(tblSales[[#This Row],[Invoice Date]])>=4,MONTH(tblSales[[#This Row],[Invoice Date]]),MONTH(tblSales[[#This Row],[Invoice Date]])+12) -> 10 | AI362: =DATE(YEAR(tblSales[[#This Row],[Invoice Date]]),MONTH(tblSales[[#This Row],[Invoice Date]]),1) -> 45566 | AJ362: =_xlfn.XLOOKUP(tblSales[[#This Row],[Product_ID]],Products!$A:$A,Products!$B:$B,"Unknown") -> Metro Shoes Straight Kurti Green | AK362: =IFERROR(tblSales[[#This Row],[Profit]]/tblSales[[#This Row],[Sales Amount]],0) -> 0.21415637 | AL362: =IF(tblSales[[#This Row],[Discount %]]<=5,"0-5%", IF(tblSales[[#This Row],[Discount %]]<=10,"5-10%", IF(tblSales[[#This Row],[Discount %]]<=15,"10-15%", IF(tblSales[[#This Row],[Discount %]]<=20,"15-20%","20%+")))) -> 5-10%
A363: INV100361 | B363: 45690 | C363: CUST0678 | D363: PRD0126 | E363: STR080 | F363: EMP0225 | G363: 1 | H363: 1065.87 | I363: 15 | J363: 159.88 | K363: 12 | L363: 108.72 | M363: 1014.71 | N363: 645.59 | O363: =(M363-N363-L363) -> 260.4 | P363: Cash | Q363: =TRIM(CLEAN(P363)) -> Cash | R363: Online | S363: Not Returned | T363: 17:44 | U363: Weekend | V363: =TEXT(tblSales[[#This Row],[Invoice Date]],"mmm") -> Feb | W363: =MONTH(tblSales[[#This Row],[Invoice Date]]) -> 2 | X363: =YEAR(tblSales[[#This Row],[Invoice Date]]) -> 2025 | Y363: =TEXT(tblSales[[#This Row],[Invoice Date]],"mmm-yyyy") -> Feb-2025 | Z363: =_xlfn.XLOOKUP(tblSales[[#This Row],[Product_ID]],Products!$A:$A,Products!$C:$C,"Women Dresses") -> Men Shirts | AA363: =_xlfn.XLOOKUP(tblSales[[#This Row],[Product_ID]],Products!$A:$A,Products!$D:$D,"Unknown") -> Formal Shirt | AB363: =_xlfn.XLOOKUP(tblSales[[#This Row],[Product_ID]],Products!$A:$A,Products!$E:$E,"Unknown") -> Van Heusen | AC363: =_xlfn.XLOOKUP(tblSales[[#This Row],[Store_ID]],Stores!$A:$A,Stores!$B:$B,"Unknown") -> TrendMart Kochi High Street | AD363: =_xlfn.XLOOKUP(tblSales[[#This Row],[Store_ID]],Stores!$A:$A,Stores!$E:$E,"Unknown") -> South Zone 1 | AE363: =_xlfn.XLOOKUP(tblSales[[#This Row],[Customer_ID]],Customers!$A:$A,Customers!$B:$B,"Unknown") -> Ganesh Kamath | AF363: =_xlfn.XLOOKUP(tblSales[[#This Row],[Customer_ID]],Customers!$A:$A,Customers!$J:$J,"Unknown") -> Gold | AG363: =_xlfn.XLOOKUP(tblSales[[#This Row],[Employee_ID]],Employees!$A:$A,Employees!$B:$B,"Unknown") -> Swathi Achari | AH363: =IF(MONTH(tblSales[[#This Row],[Invoice Date]])>=4,MONTH(tblSales[[#This Row],[Invoice Date]]),MONTH(tblSales[[#This Row],[Invoice Date]])+12) -> 14 | AI363: =DATE(YEAR(tblSales[[#This Row],[Invoice Date]]),MONTH(tblSales[[#This Row],[Invoice Date]]),1) -> 45689 | AJ363: =_xlfn.XLOOKUP(tblSales[[#This Row],[Product_ID]],Products!$A:$A,Products!$B:$B,"Unknown") -> Van Heusen Formal Shirt Olive | AK363: =IFERROR(tblSales[[#This Row],[Profit]]/tblSales[[#This Row],[Sales Amount]],0) -> 0.25662505 | AL363: =IF(tblSales[[#This Row],[Discount %]]<=5,"0-5%", IF(tblSales[[#This Row],[Discount %]]<=10,"5-10%", IF(tblSales[[#This Row],[Discount %]]<=15,"10-15%", IF(tblSales[[#This Row],[Discount %]]<=20,"15-20%","20%+")))) -> 10-15%
A364: INV100362 | B364: 45602 | C364: CUST0289 | D364: PRD0025 | E364: STR066 | F364: EMP0173 | G364: 2 | H364: 1382.13 | I364: 0 | J364: 0 | K364: 12 | L364: 331.71 | M364: 3095.97 | N364: 2050.48 | O364: =(M364-N364-L364) -> 713.78 | P364: UPI | Q364: =TRIM(CLEAN(P364)) -> UPI | R364: Offline | S364: Not Returned | T364: 13:02 | U364: Weekday | V364: =TEXT(tblSales[[#This Row],[Invoice Date]],"mmm") -> Nov | W364: =MONTH(tblSales[[#This Row],[Invoice Date]]) -> 11 | X364: =YEAR(tblSales[[#This Row],[Invoice Date]]) -> 2024 | Y364: =TEXT(tblSales[[#This Row],[Invoice Date]],"mmm-yyyy") -> Nov-2024 | Z364: =_xlfn.XLOOKUP(tblSales[[#This Row],[Product_ID]],Products!$A:$A,Products!$C:$C,"Women Dresses") -> Women Jeans | AA364: =_xlfn.XLOOKUP(tblSales[[#This Row],[Product_ID]],Products!$A:$A,Products!$D:$D,"Unknown") -> Straight Fit | AB364: =_xlfn.XLOOKUP(tblSales[[#This Row],[Product_ID]],Products!$A:$A,Products!$E:$E,"Unknown") -> Pothys | AC364: =_xlfn.XLOOKUP(tblSales[[#This Row],[Store_ID]],Stores!$A:$A,Stores!$B:$B,"Unknown") -> TrendMart Dindigul Standard | AD364: =_xlfn.XLOOKUP(tblSales[[#This Row],[Store_ID]],Stores!$A:$A,Stores!$E:$E,"Unknown") -> South Zone 1 | AE364: =_xlfn.XLOOKUP(tblSales[[#This Row],[Customer_ID]],Customers!$A:$A,Customers!$B:$B,"Unknown") -> Balaji Kumar | AF364: =_xlfn.XLOOKUP(tblSales[[#This Row],[Customer_ID]],Customers!$A:$A,Customers!$J:$J,"Unknown") -> Silver | AG364: =_xlfn.XLOOKUP(tblSales[[#This Row],[Employee_ID]],Employees!$A:$A,Employees!$B:$B,"Unknown") -> Logesh Gopalakrishnan | AH364: =IF(MONTH(tblSales[[#This Row],[Invoice Date]])>=4,MONTH(tblSales[[#This Row],[Invoice Date]]),MONTH(tblSales[[#This Row],[Invoice Date]])+12) -> 11 | AI364: =DATE(YEAR(tblSales[[#This Row],[Invoice Date]]),MONTH(tblSales[[#This Row],[Invoice Date]]),1) -> 45597 | AJ364: =_xlfn.XLOOKUP(tblSales[[#This Row],[Product_ID]],Products!$A:$A,Products!$B:$B,"Unknown") -> Pothys Straight Fit Charcoal | AK364: =IFERROR(tblSales[[#This Row],[Profit]]/tblSales[[#This Row],[Sales Amount]],0) -> 0.23055133 | AL364: =IF(tblSales[[#This Row],[Discount %]]<=5,"0-5%", IF(tblSales[[#This Row],[Discount %]]<=10,"5-10%", IF(tblSales[[#This Row],[Discount %]]<=15,"10-15%", IF(tblSales[[#This Row],[Discount %]]<=20,"15-20%","20%+")))) -> 0-5%
A365: INV100363 | B365: 45663 | C365: CUST0815 | D365: PRD0175 | E365: STR049 | F365: EMP0205 | G365: 2 | H365: 768.22 | I365: 0 | J365: 0 | K365: 5 | L365: 76.82 | M365: 1613.26 | N365: 1142.18 | O365: =(M365-N365-L365) -> 394.26 | P365: UPI | Q365: =TRIM(CLEAN(P365)) -> UPI | R365: Offline | S365: Not Returned | T365: 20:48 | U365: Weekday | V365: =TEXT(tblSales[[#This Row],[Invoice Date]],"mmm") -> Jan | W365: =MONTH(tblSales[[#This Row],[Invoice Date]]) -> 1 | X365: =YEAR(tblSales[[#This Row],[Invoice Date]]) -> 2025 | Y365: =TEXT(tblSales[[#This Row],[Invoice Date]],"mmm-yyyy") -> Jan-2025 | Z365: =_xlfn.XLOOKUP(tblSales[[#This Row],[Product_ID]],Products!$A:$A,Products!$C:$C,"Women Dresses") -> Women Kurtis | AA365: =_xlfn.XLOOKUP(tblSales[[#This Row],[Product_ID]],Products!$A:$A,Products!$D:$D,"Unknown") -> Straight Kurti | AB365: =_xlfn.XLOOKUP(tblSales[[#This Row],[Product_ID]],Products!$A:$A,Products!$E:$E,"Unknown") -> Fabindia | AC365: =_xlfn.XLOOKUP(tblSales[[#This Row],[Store_ID]],Stores!$A:$A,Stores!$B:$B,"Unknown") -> TrendMart Bengaluru Flagship | AD365: =_xlfn.XLOOKUP(tblSales[[#This Row],[Store_ID]],Stores!$A:$A,Stores!$E:$E,"Unknown") -> South Zone 2 | AE365: =_xlfn.XLOOKUP(tblSales[[#This Row],[Customer_ID]],Customers!$A:$A,Customers!$B:$B,"Unknown") -> Varsha Chandran | AF365: =_xlfn.XLOOKUP(tblSales[[#This Row],[Customer_ID]],Customers!$A:$A,Customers!$J:$J,"Unknown") -> Regular | AG365: =_xlfn.XLOOKUP(tblSales[[#This Row],[Employee_ID]],Employees!$A:$A,Employees!$B:$B,"Unknown") -> Malini Gowda | AH365: =IF(MONTH(tblSales[[#This Row],[Invoice Date]])>=4,MONTH(tblSales[[#This Row],[Invoice Date]]),MONTH(tblSales[[#This Row],[Invoice Date]])+12) -> 13 | AI365: =DATE(YEAR(tblSales[[#This Row],[Invoice Date]]),MONTH(tblSales[[#This Row],[Invoice Date]]),1) -> 45658 | AJ365: =_xlfn.XLOOKUP(tblSales[[#This Row],[Product_ID]],Products!$A:$A,Products!$B:$B,"Unknown") -> Fabindia Straight Kurti Olive | AK365: =IFERROR(tblSales[[#This Row],[Profit]]/tblSales[[#This Row],[Sales Amount]],0) -> 0.24438714 | AL365: =IF(tblSales[[#This Row],[Discount %]]<=5,"0-5%", IF(tblSales[[#This Row],[Discount %]]<=10,"5-10%", IF(tblSales[[#This Row],[Discount %]]<=15,"10-15%", IF(tblSales[[#This Row],[Discount %]]<=20,"15-20%","20%+")))) -> 0-5%
A366: INV100364 | B366: 45609 | C366: CUST0579 | D366: PRD0072 | E366: STR087 | F366: EMP0285 | G366: 1 | H366: 842.07 | I366: 15 | J366: 126.31 | K366: 5 | L366: 35.79 | M366: 751.55 | N366: 599.28 | O366: =(M366-N366-L366) -> 116.48 | P366: Credit Card | Q366: =TRIM(CLEAN(P366)) -> Credit Card | R366: Offline | S366: Not Returned | T366: 21:38 | U366: Weekday | V366: =TEXT(tblSales[[#This Row],[Invoice Date]],"mmm") -> Nov | W366: =MONTH(tblSales[[#This Row],[Invoice Date]]) -> 11 | X366: =YEAR(tblSales[[#This Row],[Invoice Date]]) -> 2024 | Y366: =TEXT(tblSales[[#This Row],[Invoice Date]],"mmm-yyyy") -> Nov-2024 | Z366: =_xlfn.XLOOKUP(tblSales[[#This Row],[Product_ID]],Products!$A:$A,Products!$C:$C,"Women Dresses") -> Women Kurtis | AA366: =_xlfn.XLOOKUP(tblSales[[#This Row],[Product_ID]],Products!$A:$A,Products!$D:$D,"Unknown") -> Straight Kurti | AB366: =_xlfn.XLOOKUP(tblSales[[#This Row],[Product_ID]],Products!$A:$A,Products!$E:$E,"Unknown") -> Metro Shoes | AC366: =_xlfn.XLOOKUP(tblSales[[#This Row],[Store_ID]],Stores!$A:$A,Stores!$B:$B,"Unknown") -> TrendMart Salem Outlet | AD366: =_xlfn.XLOOKUP(tblSales[[#This Row],[Store_ID]],Stores!$A:$A,Stores!$E:$E,"Unknown") -> South Zone 1 | AE366: =_xlfn.XLOOKUP(tblSales[[#This Row],[Customer_ID]],Customers!$A:$A,Customers!$B:$B,"Unknown") -> Meena Rao | AF366: =_xlfn.XLOOKUP(tblSales[[#This Row],[Customer_ID]],Customers!$A:$A,Customers!$J:$J,"Unknown") -> Platinum | AG366: =_xlfn.XLOOKUP(tblSales[[#This Row],[Employee_ID]],Employees!$A:$A,Employees!$B:$B,"Unknown") -> Chandran Krishnan | AH366: =IF(MONTH(tblSales[[#This Row],[Invoice Date]])>=4,MONTH(tblSales[[#This Row],[Invoice Date]]),MONTH(tblSales[[#This Row],[Invoice Date]])+12) -> 11 | AI366: =DATE(YEAR(tblSales[[#This Row],[Invoice Date]]),MONTH(tblSales[[#This Row],[Invoice Date]]),1) -> 45597 | AJ366: =_xlfn.XLOOKUP(tblSales[[#This Row],[Product_ID]],Products!$A:$A,Products!$B:$B,"Unknown") -> Metro Shoes Straight Kurti Green | AK366: =IFERROR(tblSales[[#This Row],[Profit]]/tblSales[[#This Row],[Sales Amount]],0) -> 0.15498636 | AL366: =IF(tblSales[[#This Row],[Discount %]]<=5,"0-5%", IF(tblSales[[#This Row],[Discount %]]<=10,"5-10%", IF(tblSales[[#This Row],[Discount %]]<=15,"10-15%", IF(tblSales[[#This Row],[Discount %]]<=20,"15-20%","20%+")))) -> 10-15%
A367: INV100365 | B367: 45400 | C367: CUST0588 | D367: PRD0247 | E367: STR012 | F367: EMP0225 | G367: 1 | H367: 1118.69 | I367: 0 | J367: 0 | K367: 12 | L367: 134.24 | M367: 1252.93 | N367: 765.23 | O367: =(M367-N367-L367) -> 353.46 | P367: UPI | Q367: =TRIM(CLEAN(P367)) -> UPI | R367: Offline | S367: Not Returned | T367: 15:59 | U367: Weekday | V367: =TEXT(tblSales[[#This Row],[Invoice Date]],"mmm") -> Apr | W367: =MONTH(tblSales[[#This Row],[Invoice Date]]) -> 4 | X367: =YEAR(tblSales[[#This Row],[Invoice Date]]) -> 2024 | Y367: =TEXT(tblSales[[#This Row],[Invoice Date]],"mmm-yyyy") -> Apr-2024 | Z367: =_xlfn.XLOOKUP(tblSales[[#This Row],[Product_ID]],Products!$A:$A,Products!$C:$C,"Women Dresses") -> Belts | AA367: =_xlfn.XLOOKUP(tblSales[[#This Row],[Product_ID]],Products!$A:$A,Products!$D:$D,"Unknown") -> Braided Belt | AB367: =_xlfn.XLOOKUP(tblSales[[#This Row],[Product_ID]],Products!$A:$A,Products!$E:$E,"Unknown") -> Pantaloons | AC367: =_xlfn.XLOOKUP(tblSales[[#This Row],[Store_ID]],Stores!$A:$A,Stores!$B:$B,"Unknown") -> TrendMart Vijayawada Mall Kiosk | AD367: =_xlfn.XLOOKUP(tblSales[[#This Row],[Store_ID]],Stores!$A:$A,Stores!$E:$E,"Unknown") -> South Zone 3 | AE367: =_xlfn.XLOOKUP(tblSales[[#This Row],[Customer_ID]],Customers!$A:$A,Customers!$B:$B,"Unknown") -> Nisha Achari | AF367: =_xlfn.XLOOKUP(tblSales[[#This Row],[Customer_ID]],Customers!$A:$A,Customers!$J:$J,"Unknown") -> Silver | AG367: =_xlfn.XLOOKUP(tblSales[[#This Row],[Employee_ID]],Employees!$A:$A,Employees!$B:$B,"Unknown") -> Swathi Achari | AH367: =IF(MONTH(tblSales[[#This Row],[Invoice Date]])>=4,MONTH(tblSales[[#This Row],[Invoice Date]]),MONTH(tblSales[[#This Row],[Invoice Date]])+12) -> 4 | AI367: =DATE(YEAR(tblSales[[#This Row],[Invoice Date]]),MONTH(tblSales[[#This Row],[Invoice Date]]),1) -> 45383 | AJ367: =_xlfn.XLOOKUP(tblSales[[#This Row],[Product_ID]],Products!$A:$A,Products!$B:$B,"Unknown") -> Pantaloons Braided Belt Brown | AK367: =IFERROR(tblSales[[#This Row],[Profit]]/tblSales[[#This Row],[Sales Amount]],0) -> 0.28210674 | AL367: =IF(tblSales[[#This Row],[Discount %]]<=5,"0-5%", IF(tblSales[[#This Row],[Discount %]]<=10,"5-10%", IF(tblSales[[#This Row],[Discount %]]<=15,"10-15%", IF(tblSales[[#This Row],[Discount %]]<=20,"15-20%","20%+")))) -> 0-5%
A368: INV100366 | B368: 45586 | C368: CUST0350 | D368: PRD0226 | E368: STR115 | F368: EMP0001 | G368: 2 | H368: 919.75 | I368: 0 | J368: 0 | K368: 5 | L368: 91.97 | M368: 1931.47 | N368: 1252.52 | O368: =(M368-N368-L368) -> 586.98 | P368: UPI | Q368: =TRIM(CLEAN(P368)) -> UPI | R368: Offline | S368: Not Returned | T368: 15:50 | U368: Weekday | V368: =TEXT(tblSales[[#This Row],[Invoice Date]],"mmm") -> Oct | W368: =MONTH(tblSales[[#This Row],[Invoice Date]]) -> 10 | X368: =YEAR(tblSales[[#This Row],[Invoice Date]]) -> 2024 | Y368: =TEXT(tblSales[[#This Row],[Invoice Date]],"mmm-yyyy") -> Oct-2024 | Z368: =_xlfn.XLOOKUP(tblSales[[#This Row],[Product_ID]],Products!$A:$A,Products!$C:$C,"Women Dresses") -> Sportswear | AA368: =_xlfn.XLOOKUP(tblSales[[#This Row],[Product_ID]],Products!$A:$A,Products!$D:$D,"Unknown") -> Track Suit | AB368: =_xlfn.XLOOKUP(tblSales[[#This Row],[Product_ID]],Products!$A:$A,Products!$E:$E,"Unknown") -> Being Human | AC368: =_xlfn.XLOOKUP(tblSales[[#This Row],[Store_ID]],Stores!$A:$A,Stores!$B:$B,"Unknown") -> TrendMart Bengaluru Standard | AD368: =_xlfn.XLOOKUP(tblSales[[#This Row],[Store_ID]],Stores!$A:$A,Stores!$E:$E,"Unknown") -> South Zone 2 | AE368: =_xlfn.XLOOKUP(tblSales[[#This Row],[Customer_ID]],Customers!$A:$A,Customers!$B:$B,"Unknown") -> Sanjay Chandran | AF368: =_xlfn.XLOOKUP(tblSales[[#This Row],[Customer_ID]],Customers!$A:$A,Customers!$J:$J,"Unknown") -> Gold | AG368: =_xlfn.XLOOKUP(tblSales[[#This Row],[Employee_ID]],Employees!$A:$A,Employees!$B:$B,"Unknown") -> Charulatha Kumar | AH368: =IF(MONTH(tblSales[[#This Row],[Invoice Date]])>=4,MONTH(tblSales[[#This Row],[Invoice Date]]),MONTH(tblSales[[#This Row],[Invoice Date]])+12) -> 10 | AI368: =DATE(YEAR(tblSales[[#This Row],[Invoice Date]]),MONTH(tblSales[[#This Row],[Invoice Date]]),1) -> 45566 | AJ368: =_xlfn.XLOOKUP(tblSales[[#This Row],[Product_ID]],Products!$A:$A,Products!$B:$B,"Unknown") -> Being Human Track Suit Mustard | AK368: =IFERROR(tblSales[[#This Row],[Profit]]/tblSales[[#This Row],[Sales Amount]],0) -> 0.30390324 | AL368: =IF(tblSales[[#This Row],[Discount %]]<=5,"0-5%", IF(tblSales[[#This Row],[Discount %]]<=10,"5-10%", IF(tblSales[[#This Row],[Discount %]]<=15,"10-15%", IF(tblSales[[#This Row],[Discount %]]<=20,"15-20%","20%+")))) -> 0-5%
A369: INV100367 | B369: 45410 | C369: CUST0792 | D369: PRD0061 | E369: STR120 | F369: EMP0215 | G369: 2 | H369: 723.48 | I369: 0 | J369: 0 | K369: 5 | L369: 72.35 | M369: 1519.31 | N369: 1018.88 | O369: =(M369-N369-L369) -> 428.08 | P369: UPI | Q369: =TRIM(CLEAN(P369)) -> UPI | R369: Offline | S369: Not Returned | T369: 15:54 | U369: Weekend | V369: =TEXT(tblSales[[#This Row],[Invoice Date]],"mmm") -> Apr | W369: =MONTH(tblSales[[#This Row],[Invoice Date]]) -> 4 | X369: =YEAR(tblSales[[#This Row],[Invoice Date]]) -> 2024 | Y369: =TEXT(tblSales[[#This Row],[Invoice Date]],"mmm-yyyy") -> Apr-2024 | Z369: =_xlfn.XLOOKUP(tblSales[[#This Row],[Product_ID]],Products!$A:$A,Products!$C:$C,"Women Dresses") -> Kids Wear | AA369: =_xlfn.XLOOKUP(tblSales[[#This Row],[Product_ID]],Products!$A:$A,Products!$D:$D,"Unknown") -> Kids Shorts | AB369: =_xlfn.XLOOKUP(tblSales[[#This Row],[Product_ID]],Products!$A:$A,Products!$E:$E,"Unknown") -> Allen Solly | AC369: =_xlfn.XLOOKUP(tblSales[[#This Row],[Store_ID]],Stores!$A:$A,Stores!$B:$B,"Unknown") -> TrendMart Karimnagar Standard | AD369: =_xlfn.XLOOKUP(tblSales[[#This Row],[Store_ID]],Stores!$A:$A,Stores!$E:$E,"Unknown") -> South Zone 2 | AE369: =_xlfn.XLOOKUP(tblSales[[#This Row],[Customer_ID]],Customers!$A:$A,Customers!$B:$B,"Unknown") -> Varsha Kamath | AF369: =_xlfn.XLOOKUP(tblSales[[#This Row],[Customer_ID]],Customers!$A:$A,Customers!$J:$J,"Unknown") -> Gold | AG369: =_xlfn.XLOOKUP(tblSales[[#This Row],[Employee_ID]],Employees!$A:$A,Employees!$B:$B,"Unknown") -> Praveen Gupta | AH369: =IF(MONTH(tblSales[[#This Row],[Invoice Date]])>=4,MONTH(tblSales[[#This Row],[Invoice Date]]),MONTH(tblSales[[#This Row],[Invoice Date]])+12) -> 4 | AI369: =DATE(YEAR(tblSales[[#This Row],[Invoice Date]]),MONTH(tblSales[[#This Row],[Invoice Date]]),1) -> 45383 | AJ369: =_xlfn.XLOOKUP(tblSales[[#This Row],[Product_ID]],Products!$A:$A,Products!$B:$B,"Unknown") -> Allen Solly Kids Shorts Teal | AK369: =IFERROR(tblSales[[#This Row],[Profit]]/tblSales[[#This Row],[Sales Amount]],0) -> 0.28175948 | AL369: =IF(tblSales[[#This Row],[Discount %]]<=5,"0-5%", IF(tblSales[[#This Row],[Discount %]]<=10,"5-10%", IF(tblSales[[#This Row],[Discount %]]<=15,"10-15%", IF(tblSales[[#This Row],[Discount %]]<=20,"15-20%","20%+")))) -> 0-5%
... A387: INV100385 | B387: 45705 | C387: CUST0079 | D387: PRD0182 | E387: STR031 | F387: EMP0141 | G387: 3 | H387: 3179.94 | I387: 5 | J387: 476.99 | K387: 12 | L387: 1087.54 | M387: 10150.37 | N387: 6407.55 | O387: =(M387-N387-L387) -> 2655.28 | P387: Credit Card | Q387: =TRIM(CLEAN(P387)) -> Credit Card | R387: Offline | S387: Not Returned | T387: 20:36 | U387: Weekday | V387: =TEXT(tblSales[[#This Row],[Invoice Date]],"mmm") -> Feb | W387: =MONTH(tblSales[[#This Row],[Invoice Date]]) -> 2 | X387: =YEAR(tblSales[[#This Row],[Invoice Date]]) -> 2025 | Y387: =TEXT(tblSales[[#This Row],[Invoice Date]],"mmm-yyyy") -> Feb-2025 | Z387: =_xlfn.XLOOKUP(tblSales[[#This Row],[Product_ID]],Products!$A:$A,Products!$C:$C,"Women Dresses") -> Handbags | AA387: =_xlfn.XLOOKUP(tblSales[[#This Row],[Product_ID]],Products!$A:$A,Products!$D:$D,"Unknown") -> Sling Bag | AB387: =_xlfn.XLOOKUP(tblSales[[#This Row],[Product_ID]],Products!$A:$A,Products!$E:$E,"Unknown") -> Tanishq | AC387: =_xlfn.XLOOKUP(tblSales[[#This Row],[Store_ID]],Stores!$A:$A,Stores!$B:$B,"Unknown") -> TrendMart Kozhikode Mall Kiosk | AD387: =_xlfn.XLOOKUP(tblSales[[#This Row],[Store_ID]],Stores!$A:$A,Stores!$E:$E,"Unknown") -> South Zone 1 | AE387: =_xlfn.XLOOKUP(tblSales[[#This Row],[Customer_ID]],Customers!$A:$A,Customers!$B:$B,"Unknown") -> Dhruv Natarajan | AF387: =_xlfn.XLOOKUP(tblSales[[#This Row],[Customer_ID]],Customers!$A:$A,Customers!$J:$J,"Unknown") -> Platinum | AG387: =_xlfn.XLOOKUP(tblSales[[#This Row],[Employee_ID]],Employees!$A:$A,Employees!$B:$B,"Unknown") -> Dhruv Mishra | AH387: =IF(MONTH(tblSales[[#This Row],[Invoice Date]])>=4,MONTH(tblSales[[#This Row],[Invoice Date]]),MONTH(tblSales[[#This Row],[Invoice Date]])+12) -> 14 | AI387: =DATE(YEAR(tblSales[[#This Row],[Invoice Date]]),MONTH(tblSales[[#This Row],[Invoice Date]]),1) -> 45689 | AJ387: =_xlfn.XLOOKUP(tblSales[[#This Row],[Product_ID]],Products!$A:$A,Products!$B:$B,"Unknown") -> Tanishq Sling Bag Mustard | AK387: =IFERROR(tblSales[[#This Row],[Profit]]/tblSales[[#This Row],[Sales Amount]],0) -> 0.2615944 | AL387: =IF(tblSales[[#This Row],[Discount %]]<=5,"0-5%", IF(tblSales[[#This Row],[Discount %]]<=10,"5-10%", IF(tblSales[[#This Row],[Discount %]]<=15,"10-15%", IF(tblSales[[#This Row],[Discount %]]<=20,"15-20%","20%+")))) -> 0-5%
A388: INV100386 | B388: 45518 | C388: CUST0200 | D388: PRD0043 | E388: STR091 | F388: EMP0215 | G388: 0 | H388: 2923.57 | I388: 15 | J388: 0 | K388: 12 | L388: 0 | M388: 0 | N388: 0 | O388: 0 | P388: Credit Card | Q388: =TRIM(CLEAN(P388)) -> Credit Card | R388: Online | S388: Returned | T388: 18:31 | U388: Weekday | V388: =TEXT(tblSales[[#This Row],[Invoice Date]],"mmm") -> Aug | W388: =MONTH(tblSales[[#This Row],[Invoice Date]]) -> 8 | X388: =YEAR(tblSales[[#This Row],[Invoice Date]]) -> 2024 | Y388: =TEXT(tblSales[[#This Row],[Invoice Date]],"mmm-yyyy") -> Aug-2024 | Z388: =_xlfn.XLOOKUP(tblSales[[#This Row],[Product_ID]],Products!$A:$A,Products!$C:$C,"Women Dresses") -> Handbags | AA388: =_xlfn.XLOOKUP(tblSales[[#This Row],[Product_ID]],Products!$A:$A,Products!$D:$D,"Unknown") -> Sling Bag | AB388: =_xlfn.XLOOKUP(tblSales[[#This Row],[Product_ID]],Products!$A:$A,Products!$E:$E,"Unknown") -> GRT Jewellers | AC388: =_xlfn.XLOOKUP(tblSales[[#This Row],[Store_ID]],Stores!$A:$A,Stores!$B:$B,"Unknown") -> TrendMart Nizamabad Standard | AD388: =_xlfn.XLOOKUP(tblSales[[#This Row],[Store_ID]],Stores!$A:$A,Stores!$E:$E,"Unknown") -> South Zone 2 | AE388: =_xlfn.XLOOKUP(tblSales[[#This Row],[Customer_ID]],Customers!$A:$A,Customers!$B:$B,"Unknown") -> Balaji Chettiar | AF388: =_xlfn.XLOOKUP(tblSales[[#This Row],[Customer_ID]],Customers!$A:$A,Customers!$J:$J,"Unknown") -> Gold | AG388: =_xlfn.XLOOKUP(tblSales[[#This Row],[Employee_ID]],Employees!$A:$A,Employees!$B:$B,"Unknown") -> Praveen Gupta | AH388: =IF(MONTH(tblSales[[#This Row],[Invoice Date]])>=4,MONTH(tblSales[[#This Row],[Invoice Date]]),MONTH(tblSales[[#This Row],[Invoice Date]])+12) -> 8 | AI388: =DATE(YEAR(tblSales[[#This Row],[Invoice Date]]),MONTH(tblSales[[#This Row],[Invoice Date]]),1) -> 45505 | AJ388: =_xlfn.XLOOKUP(tblSales[[#This Row],[Product_ID]],Products!$A:$A,Products!$B:$B,"Unknown") -> GRT Jewellers Sling Bag Olive | AK388: =IFERROR(tblSales[[#This Row],[Profit]]/tblSales[[#This Row],[Sales Amount]],0) -> 0 | AL388: =IF(tblSales[[#This Row],[Discount %]]<=5,"0-5%", IF(tblSales[[#This Row],[Discount %]]<=10,"5-10%", IF(tblSales[[#This Row],[Discount %]]<=15,"10-15%", IF(tblSales[[#This Row],[Discount %]]<=20,"15-20%","20%+")))) -> 10-15%
A389: INV100387 | B389: 45601 | C389: CUST0749 | D389: PRD0087 | E389: STR085 | F389: EMP0020 | G389: 2 | H389: 1265.63 | I389: 10 | J389: 253.13 | K389: 12 | L389: 273.38 | M389: 2551.51 | N389: 1746.86 | O389: =(M389-N389-L389) -> 531.27 | P389: Debit Card | Q389: =TRIM(CLEAN(P389)) -> Debit Card | R389: Offline | S389: Not Returned | T389: 16:17 | U389: Weekday | V389: =TEXT(tblSales[[#This Row],[Invoice Date]],"mmm") -> Nov | W389: =MONTH(tblSales[[#This Row],[Invoice Date]]) -> 11 | X389: =YEAR(tblSales[[#This Row],[Invoice Date]]) -> 2024 | Y389: =TEXT(tblSales[[#This Row],[Invoice Date]],"mmm-yyyy") -> Nov-2024 | Z389: =_xlfn.XLOOKUP(tblSales[[#This Row],[Product_ID]],Products!$A:$A,Products!$C:$C,"Women Dresses") -> Men Trousers | AA389: =_xlfn.XLOOKUP(tblSales[[#This Row],[Product_ID]],Products!$A:$A,Products!$D:$D,"Unknown") -> Formal Trouser | AB389: =_xlfn.XLOOKUP(tblSales[[#This Row],[Product_ID]],Products!$A:$A,Products!$E:$E,"Unknown") -> Missing Brand Name | AC389: =_xlfn.XLOOKUP(tblSales[[#This Row],[Store_ID]],Stores!$A:$A,Stores!$B:$B,"Unknown") -> TrendMart Nizamabad Outlet | AD389: =_xlfn.XLOOKUP(tblSales[[#This Row],[Store_ID]],Stores!$A:$A,Stores!$E:$E,"Unknown") -> South Zone 2 | AE389: =_xlfn.XLOOKUP(tblSales[[#This Row],[Customer_ID]],Customers!$A:$A,Customers!$B:$B,"Unknown") -> Anusuya Mudaliar | AF389: =_xlfn.XLOOKUP(tblSales[[#This Row],[Customer_ID]],Customers!$A:$A,Customers!$J:$J,"Unknown") -> Silver | AG389: =_xlfn.XLOOKUP(tblSales[[#This Row],[Employee_ID]],Employees!$A:$A,Employees!$B:$B,"Unknown") -> Eswar Prasad | AH389: =IF(MONTH(tblSales[[#This Row],[Invoice Date]])>=4,MONTH(tblSales[[#This Row],[Invoice Date]]),MONTH(tblSales[[#This Row],[Invoice Date]])+12) -> 11 | AI389: =DATE(YEAR(tblSales[[#This Row],[Invoice Date]]),MONTH(tblSales[[#This Row],[Invoice Date]]),1) -> 45597 | AJ389: =_xlfn.XLOOKUP(tblSales[[#This Row],[Product_ID]],Products!$A:$A,Products!$B:$B,"Unknown") -> Blackberrys Formal Trouser Mustard | AK389: =IFERROR(tblSales[[#This Row],[Profit]]/tblSales[[#This Row],[Sales Amount]],0) -> 0.20821788 | AL389: =IF(tblSales[[#This Row],[Discount %]]<=5,"0-5%", IF(tblSales[[#This Row],[Discount %]]<=10,"5-10%", IF(tblSales[[#This Row],[Discount %]]<=15,"10-15%", IF(tblSales[[#This Row],[Discount %]]<=20,"15-20%","20%+")))) -> 5-10%
A390: INV100388 | B390: 45587 | C390: CUST0416 | D390: PRD0119 | E390: STR050 | F390: EMP0147 | G390: 1 | H390: 740.3 | I390: 0 | J390: 0 | K390: 5 | L390: 37.02 | M390: 777.32 | N390: 428.16 | O390: =(M390-N390-L390) -> 312.14 | P390: Credit Card | Q390: =TRIM(CLEAN(P390)) -> Credit Card | R390: Offline | S390: Not Returned | T390: 20:36 | U390: Weekday | V390: =TEXT(tblSales[[#This Row],[Invoice Date]],"mmm") -> Oct | W390: =MONTH(tblSales[[#This Row],[Invoice Date]]) -> 10 | X390: =YEAR(tblSales[[#This Row],[Invoice Date]]) -> 2024 | Y390: =TEXT(tblSales[[#This Row],[Invoice Date]],"mmm-yyyy") -> Oct-2024 | Z390: =_xlfn.XLOOKUP(tblSales[[#This Row],[Product_ID]],Products!$A:$A,Products!$C:$C,"Women Dresses") -> Men T-Shirts | AA390: =_xlfn.XLOOKUP(tblSales[[#This Row],[Product_ID]],Products!$A:$A,Products!$D:$D,"Unknown") -> Round Neck | AB390: =_xlfn.XLOOKUP(tblSales[[#This Row],[Product_ID]],Products!$A:$A,Products!$E:$E,"Unknown") -> Killer Jeans | AC390: =_xlfn.XLOOKUP(tblSales[[#This Row],[Store_ID]],Stores!$A:$A,Stores!$B:$B,"Unknown") -> TrendMart Thrissur High Street | AD390: =_xlfn.XLOOKUP(tblSales[[#This Row],[Store_ID]],Stores!$A:$A,Stores!$E:$E,"Unknown") -> South Zone 1 | AE390: =_xlfn.XLOOKUP(tblSales[[#This Row],[Customer_ID]],Customers!$A:$A,Customers!$B:$B,"Unknown") -> Bharathi Prasad | AF390: =_xlfn.XLOOKUP(tblSales[[#This Row],[Customer_ID]],Customers!$A:$A,Customers!$J:$J,"Unknown") -> Regular | AG390: =_xlfn.XLOOKUP(tblSales[[#This Row],[Employee_ID]],Employees!$A:$A,Employees!$B:$B,"Unknown") -> Yogesh Chettiar | AH390: =IF(MONTH(tblSales[[#This Row],[Invoice Date]])>=4,MONTH(tblSales[[#This Row],[Invoice Date]]),MONTH(tblSales[[#This Row],[Invoice Date]])+12) -> 10 | AI390: =DATE(YEAR(tblSales[[#This Row],[Invoice Date]]),MONTH(tblSales[[#This Row],[Invoice Date]]),1) -> 45566 | AJ390: =_xlfn.XLOOKUP(tblSales[[#This Row],[Product_ID]],Products!$A:$A,Products!$B:$B,"Unknown") -> Killer Jeans Round Neck Charcoal | AK390: =IFERROR(tblSales[[#This Row],[Profit]]/tblSales[[#This Row],[Sales Amount]],0) -> 0.4015592 | AL390: =IF(tblSales[[#This Row],[Discount %]]<=5,"0-5%", IF(tblSales[[#This Row],[Discount %]]<=10,"5-10%", IF(tblSales[[#This Row],[Discount %]]<=15,"10-15%", IF(tblSales[[#This Row],[Discount %]]<=20,"15-20%","20%+")))) -> 0-5%
A391: INV100389 | B391: 45500 | C391: CUST0057 | D391: PRD0202 | E391: STR058 | F391: EMP0149 | G391: 2 | H391: 869.16 | I391: 15 | J391: 260.75 | K391: 5 | L391: 73.88 | M391: 1551.45 | N391: 1180.04 | O391: =(M391-N391-L391) -> 297.53 | P391: Debit Card | Q391: =TRIM(CLEAN(P391)) -> Debit Card | R391: Offline | S391: Not Returned | T391: 13:44 | U391: Weekend | V391: =TEXT(tblSales[[#This Row],[Invoice Date]],"mmm") -> Jul | W391: =MONTH(tblSales[[#This Row],[Invoice Date]]) -> 7 | X391: =YEAR(tblSales[[#This Row],[Invoice Date]]) -> 2024 | Y391: =TEXT(tblSales[[#This Row],[Invoice Date]],"mmm-yyyy") -> Jul-2024 | Z391: =_xlfn.XLOOKUP(tblSales[[#This Row],[Product_ID]],Products!$A:$A,Products!$C:$C,"Women Dresses") -> Belts | AA391: =_xlfn.XLOOKUP(tblSales[[#This Row],[Product_ID]],Products!$A:$A,Products!$D:$D,"Unknown") -> Casual Belt | AB391: =_xlfn.XLOOKUP(tblSales[[#This Row],[Product_ID]],Products!$A:$A,Products!$E:$E,"Unknown") -> Skechers | AC391: =_xlfn.XLOOKUP(tblSales[[#This Row],[Store_ID]],Stores!$A:$A,Stores!$B:$B,"Unknown") -> TrendMart Thoothukudi Flagship | AD391: =_xlfn.XLOOKUP(tblSales[[#This Row],[Store_ID]],Stores!$A:$A,Stores!$E:$E,"Unknown") -> South Zone 1 | AE391: =_xlfn.XLOOKUP(tblSales[[#This Row],[Customer_ID]],Customers!$A:$A,Customers!$B:$B,"Unknown") -> Bharathi Natarajan | AF391: =_xlfn.XLOOKUP(tblSales[[#This Row],[Customer_ID]],Customers!$A:$A,Customers!$J:$J,"Unknown") -> Gold | AG391: =_xlfn.XLOOKUP(tblSales[[#This Row],[Employee_ID]],Employees!$A:$A,Employees!$B:$B,"Unknown") -> Vasanthi Kamath | AH391: =IF(MONTH(tblSales[[#This Row],[Invoice Date]])>=4,MONTH(tblSales[[#This Row],[Invoice Date]]),MONTH(tblSales[[#This Row],[Invoice Date]])+12) -> 7 | AI391: =DATE(YEAR(tblSales[[#This Row],[Invoice Date]]),MONTH(tblSales[[#This Row],[Invoice Date]]),1) -> 45474 | AJ391: =_xlfn.XLOOKUP(tblSales[[#This Row],[Product_ID]],Products!$A:$A,Products!$B:$B,"Unknown") -> Skechers Casual Belt Sky Blue | AK391: =IFERROR(tblSales[[#This Row],[Profit]]/tblSales[[#This Row],[Sales Amount]],0) -> 0.19177544 | AL391: =IF(tblSales[[#This Row],[Discount %]]<=5,"0-5%", IF(tblSales[[#This Row],[Discount %]]<=10,"5-10%", IF(tblSales[[#This Row],[Discount %]]<=15,"10-15%", IF(tblSales[[#This Row],[Discount %]]<=20,"15-20%","20%+")))) -> 10-15%
A392: INV100390 | B392: 45558 | C392: CUST0266 | D392: PRD0050 | E392: STR041 | F392: EMP0063 | G392: 1 | H392: 1132.58 | I392: 0 | J392: 0 | K392: 12 | L392: 135.91 | M392: 1268.49 | N392: 769.63 | O392: =(M392-N392-L392) -> 362.95 | P392: Cash | Q392: =TRIM(CLEAN(P392)) -> Cash | R392: Online | S392: Not Returned | T392: 15:32 | U392: Weekday | V392: =TEXT(tblSales[[#This Row],[Invoice Date]],"mmm") -> Sep | W392: =MONTH(tblSales[[#This Row],[Invoice Date]]) -> 9 | X392: =YEAR(tblSales[[#This Row],[Invoice Date]]) -> 2024 | Y392: =TEXT(tblSales[[#This Row],[Invoice Date]],"mmm-yyyy") -> Sep-2024 | Z392: =_xlfn.XLOOKUP(tblSales[[#This Row],[Product_ID]],Products!$A:$A,Products!$C:$C,"Women Dresses") -> Women Dresses | AA392: =_xlfn.XLOOKUP(tblSales[[#This Row],[Product_ID]],Products!$A:$A,Products!$D:$D,"Unknown") -> A-Line Dress | AB392: =_xlfn.XLOOKUP(tblSales[[#This Row],[Product_ID]],Products!$A:$A,Products!$E:$E,"Unknown") -> Ramraj Cotton | AC392: =_xlfn.XLOOKUP(tblSales[[#This Row],[Store_ID]],Stores!$A:$A,Stores!$B:$B,"Unknown") -> TrendMart Thiruvananthapuram Standard | AD392: =_xlfn.XLOOKUP(tblSales[[#This Row],[Store_ID]],Stores!$A:$A,Stores!$E:$E,"Unknown") -> South Zone 1 | AE392: =_xlfn.XLOOKUP(tblSales[[#This Row],[Customer_ID]],Customers!$A:$A,Customers!$B:$B,"Unknown") -> Chandra Subramaniam | AF392: =_xlfn.XLOOKUP(tblSales[[#This Row],[Customer_ID]],Customers!$A:$A,Customers!$J:$J,"Unknown") -> Silver | AG392: =_xlfn.XLOOKUP(tblSales[[#This Row],[Employee_ID]],Employees!$A:$A,Employees!$B:$B,"Unknown") -> Anusuya Subramaniam | AH392: =IF(MONTH(tblSales[[#This Row],[Invoice Date]])>=4,MONTH(tblSales[[#This Row],[Invoice Date]]),MONTH(tblSales[[#This Row],[Invoice Date]])+12) -> 9 | AI392: =DATE(YEAR(tblSales[[#This Row],[Invoice Date]]),MONTH(tblSales[[#This Row],[Invoice Date]]),1) -> 45536 | AJ392: =_xlfn.XLOOKUP(tblSales[[#This Row],[Product_ID]],Products!$A:$A,Products!$B:$B,"Unknown") -> Ramraj Cotton A-Line Dress Brown | AK392: =IFERROR(tblSales[[#This Row],[Profit]]/tblSales[[#This Row],[Sales Amount]],0) -> 0.2861276 | AL392: =IF(tblSales[[#This Row],[Discount %]]<=5,"0-5%", IF(tblSales[[#This Row],[Discount %]]<=10,"5-10%", IF(tblSales[[#This Row],[Discount %]]<=15,"10-15%", IF(tblSales[[#This Row],[Discount %]]<=20,"15-20%","20%+")))) -> 0-5%
A393: INV100391 | B393: 45611 | C393: CUST0374 | D393: PRD0043 | E393: STR006 | F393: EMP0203 | G393: 4 | H393: 3074.18 | I393: 25 | J393: 3074.18 | K393: 12 | L393: 1106.7 | M393: 10329.24 | N393: 8136.04 | O393: =(M393-N393-L393) -> 1086.5 | P393: UPI | Q393: =TRIM(CLEAN(P393)) -> UPI | R393: Offline | S393: Returned | T393: 12:22 | U393: Weekday | V393: =TEXT(tblSales[[#This Row],[Invoice Date]],"mmm") -> Nov | W393: =MONTH(tblSales[[#This Row],[Invoice Date]]) -> 11 | X393: =YEAR(tblSales[[#This Row],[Invoice Date]]) -> 2024 | Y393: =TEXT(tblSales[[#This Row],[Invoice Date]],"mmm-yyyy") -> Nov-2024 | Z393: =_xlfn.XLOOKUP(tblSales[[#This Row],[Product_ID]],Products!$A:$A,Products!$C:$C,"Women Dresses") -> Handbags | AA393: =_xlfn.XLOOKUP(tblSales[[#This Row],[Product_ID]],Products!$A:$A,Products!$D:$D,"Unknown") -> Sling Bag | AB393: =_xlfn.XLOOKUP(tblSales[[#This Row],[Product_ID]],Products!$A:$A,Products!$E:$E,"Unknown") -> GRT Jewellers | AC393: =_xlfn.XLOOKUP(tblSales[[#This Row],[Store_ID]],Stores!$A:$A,Stores!$B:$B,"Unknown") -> TrendMart Vellore Standard | AD393: =_xlfn.XLOOKUP(tblSales[[#This Row],[Store_ID]],Stores!$A:$A,Stores!$E:$E,"Unknown") -> South Zone 1 | AE393: =_xlfn.XLOOKUP(tblSales[[#This Row],[Customer_ID]],Customers!$A:$A,Customers!$B:$B,"Unknown") -> Varsha Rao | AF393: =_xlfn.XLOOKUP(tblSales[[#This Row],[Customer_ID]],Customers!$A:$A,Customers!$J:$J,"Unknown") -> Regular | AG393: =_xlfn.XLOOKUP(tblSales[[#This Row],[Employee_ID]],Employees!$A:$A,Employees!$B:$B,"Unknown") -> Rani Mishra | AH393: =IF(MONTH(tblSales[[#This Row],[Invoice Date]])>=4,MONTH(tblSales[[#This Row],[Invoice Date]]),MONTH(tblSales[[#This Row],[Invoice Date]])+12) -> 11 | AI393: =DATE(YEAR(tblSales[[#This Row],[Invoice Date]]),MONTH(tblSales[[#This Row],[Invoice Date]]),1) -> 45597 | AJ393: =_xlfn.XLOOKUP(tblSales[[#This Row],[Product_ID]],Products!$A:$A,Products!$B:$B,"Unknown") -> GRT Jewellers Sling Bag Olive | AK393: =IFERROR(tblSales[[#This Row],[Profit]]/tblSales[[#This Row],[Sales Amount]],0) -> 0.10518683 | AL393: =IF(tblSales[[#This Row],[Discount %]]<=5,"0-5%", IF(tblSales[[#This Row],[Discount %]]<=10,"5-10%", IF(tblSales[[#This Row],[Discount %]]<=15,"10-15%", IF(tblSales[[#This Row],[Discount %]]<=20,"15-20%","20%+")))) -> 20%+
A394: INV100392 | B394: 45416 | C394: CUST0130 | D394: PRD0198 | E394: STR029 | F394: EMP0255 | G394: 0 | H394: 822.23 | I394: 10 | J394: 0 | K394: 5 | L394: 0 | M394: 0 | N394: 0 | O394: 0 | P394: Debit Card | Q394: =TRIM(CLEAN(P394)) -> Debit Card | R394: Offline | S394: Not Returned | T394: 18:10 | U394: Weekend | V394: =TEXT(tblSales[[#This Row],[Invoice Date]],"mmm") -> May | W394: =MONTH(tblSales[[#This Row],[Invoice Date]]) -> 5 | X394: =YEAR(tblSales[[#This Row],[Invoice Date]]) -> 2024 | Y394: =TEXT(tblSales[[#This Row],[Invoice Date]],"mmm-yyyy") -> May-2024 | Z394: =_xlfn.XLOOKUP(tblSales[[#This Row],[Product_ID]],Products!$A:$A,Products!$C:$C,"Women Dresses") -> Men Trousers | AA394: =_xlfn.XLOOKUP(tblSales[[#This Row],[Product_ID]],Products!$A:$A,Products!$D:$D,"Unknown") -> Formal Trouser | AB394: =_xlfn.XLOOKUP(tblSales[[#This Row],[Product_ID]],Products!$A:$A,Products!$E:$E,"Unknown") -> Van Heusen | AC394: =_xlfn.XLOOKUP(tblSales[[#This Row],[Store_ID]],Stores!$A:$A,Stores!$B:$B,"Unknown") -> TrendMart Davanagere High Street | AD394: =_xlfn.XLOOKUP(tblSales[[#This Row],[Store_ID]],Stores!$A:$A,Stores!$E:$E,"Unknown") -> South Zone 2 | AE394: =_xlfn.XLOOKUP(tblSales[[#This Row],[Customer_ID]],Customers!$A:$A,Customers!$B:$B,"Unknown") -> Tejaswini Murthy | AF394: =_xlfn.XLOOKUP(tblSales[[#This Row],[Customer_ID]],Customers!$A:$A,Customers!$J:$J,"Unknown") -> Regular | AG394: =_xlfn.XLOOKUP(tblSales[[#This Row],[Employee_ID]],Employees!$A:$A,Employees!$B:$B,"Unknown") -> Venkat Sharma | AH394: =IF(MONTH(tblSales[[#This Row],[Invoice Date]])>=4,MONTH(tblSales[[#This Row],[Invoice Date]]),MONTH(tblSales[[#This Row],[Invoice Date]])+12) -> 5 | AI394: =DATE(YEAR(tblSales[[#This Row],[Invoice Date]]),MONTH(tblSales[[#This Row],[Invoice Date]]),1) -> 45413 | AJ394: =_xlfn.XLOOKUP(tblSales[[#This Row],[Product_ID]],Products!$A:$A,Products!$B:$B,"Unknown") -> Van Heusen Formal Trouser Maroon | AK394: =IFERROR(tblSales[[#This Row],[Profit]]/tblSales[[#This Row],[Sales Amount]],0) -> 0 | AL394: =IF(tblSales[[#This Row],[Discount %]]<=5,"0-5%", IF(tblSales[[#This Row],[Discount %]]<=10,"5-10%", IF(tblSales[[#This Row],[Discount %]]<=15,"10-15%", IF(tblSales[[#This Row],[Discount %]]<=20,"15-20%","20%+")))) -> 5-10%
A395: INV100393 | B395: 45430 | C395: CUST0331 | D395: PRD0070 | E395: STR098 | F395: EMP0090 | G395: 2 | H395: 859.76 | I395: 5 | J395: 85.98 | K395: 5 | L395: 81.68 | M395: 1715.22 | N395: 1130.9 | O395: =(M395-N395-L395) -> 502.64 | P395: Cash | Q395: =TRIM(CLEAN(P395)) -> Cash | R395: Offline | S395: Not Returned | T395: 17:21 | U395: Weekend | V395: =TEXT(tblSales[[#This Row],[Invoice Date]],"mmm") -> May | W395: =MONTH(tblSales[[#This Row],[Invoice Date]]) -> 5 | X395: =YEAR(tblSales[[#This Row],[Invoice Date]]) -> 2024 | Y395: =TEXT(tblSales[[#This Row],[Invoice Date]],"mmm-yyyy") -> May-2024 | Z395: =_xlfn.XLOOKUP(tblSales[[#This Row],[Product_ID]],Products!$A:$A,Products!$C:$C,"Women Dresses") -> Kids Wear | AA395: =_xlfn.XLOOKUP(tblSales[[#This Row],[Product_ID]],Products!$A:$A,Products!$D:$D,"Unknown") -> Boys Shirt | AB395: =_xlfn.XLOOKUP(tblSales[[#This Row],[Product_ID]],Products!$A:$A,Products!$E:$E,"Unknown") -> Woodland | AC395: =_xlfn.XLOOKUP(tblSales[[#This Row],[Store_ID]],Stores!$A:$A,Stores!$B:$B,"Unknown") -> TrendMart Guntur High Street | AD395: =_xlfn.XLOOKUP(tblSales[[#This Row],[Store_ID]],Stores!$A:$A,Stores!$E:$E,"Unknown") -> South Zone 3 | AE395: =_xlfn.XLOOKUP(tblSales[[#This Row],[Customer_ID]],Customers!$A:$A,Customers!$B:$B,"Unknown") -> Anjali Bhat | AF395: =_xlfn.XLOOKUP(tblSales[[#This Row],[Customer_ID]],Customers!$A:$A,Customers!$J:$J,"Unknown") -> Silver | AG395: =_xlfn.XLOOKUP(tblSales[[#This Row],[Employee_ID]],Employees!$A:$A,Employees!$B:$B,"Unknown") -> Padma Gounder | AH395: =IF(MONTH(tblSales[[#This Row],[Invoice Date]])>=4,MONTH(tblSales[[#This Row],[Invoice Date]]),MONTH(tblSales[[#This Row],[Invoice Date]])+12) -> 5 | AI395: =DATE(YEAR(tblSales[[#This Row],[Invoice Date]]),MONTH(tblSales[[#This Row],[Invoice Date]]),1) -> 45413 | AJ395: =_xlfn.XLOOKUP(tblSales[[#This Row],[Product_ID]],Products!$A:$A,Products!$B:$B,"Unknown") -> Woodland Boys Shirt White | AK395: =IFERROR(tblSales[[#This Row],[Profit]]/tblSales[[#This Row],[Sales Amount]],0) -> 0.29304696 | AL395: =IF(tblSales[[#This Row],[Discount %]]<=5,"0-5%", IF(tblSales[[#This Row],[Discount %]]<=10,"5-10%", IF(tblSales[[#This Row],[Discount %]]<=15,"10-15%", IF(tblSales[[#This Row],[Discount %]]<=20,"15-20%","20%+")))) -> 0-5%
A396: INV100394 | B396: 45588 | C396: CUST0188 | D396: PRD0122 | E396: STR037 | F396: EMP0100 | G396: 1 | H396: 725.13 | I396: 5 | J396: 36.26 | K396: 3 | L396: 20.67 | M396: 709.54 | N396: 556.99 | O396: =(M396-N396-L396) -> 131.88 | P396: Debit Card | Q396: =TRIM(CLEAN(P396)) -> Debit Card | R396: Online | S396: Not Returned | T396: 18:15 | U396: Weekday | V396: =TEXT(tblSales[[#This Row],[Invoice Date]],"mmm") -> Oct | W396: =MONTH(tblSales[[#This Row],[Invoice Date]]) -> 10 | X396: =YEAR(tblSales[[#This Row],[Invoice Date]]) -> 2024 | Y396: =TEXT(tblSales[[#This Row],[Invoice Date]],"mmm-yyyy") -> Oct-2024 | Z396: =_xlfn.XLOOKUP(tblSales[[#This Row],[Product_ID]],Products!$A:$A,Products!$C:$C,"Women Dresses") -> Jewellery | AA396: =_xlfn.XLOOKUP(tblSales[[#This Row],[Product_ID]],Products!$A:$A,Products!$D:$D,"Unknown") -> Necklace | AB396: =_xlfn.XLOOKUP(tblSales[[#This Row],[Product_ID]],Products!$A:$A,Products!$E:$E,"Unknown") -> Aurelia | AC396: =_xlfn.XLOOKUP(tblSales[[#This Row],[Store_ID]],Stores!$A:$A,Stores!$B:$B,"Unknown") -> TrendMart Vijayawada High Street | AD396: =_xlfn.XLOOKUP(tblSales[[#This Row],[Store_ID]],Stores!$A:$A,Stores!$E:$E,"Unknown") -> South Zone 3 | AE396: =_xlfn.XLOOKUP(tblSales[[#This Row],[Customer_ID]],Customers!$A:$A,Customers!$B:$B,"Unknown") -> Vasanthi Srinivasan | AF396: =_xlfn.XLOOKUP(tblSales[[#This Row],[Customer_ID]],Customers!$A:$A,Customers!$J:$J,"Unknown") -> Silver | AG396: =_xlfn.XLOOKUP(tblSales[[#This Row],[Employee_ID]],Employees!$A:$A,Employees!$B:$B,"Unknown") -> Priya Balasubramaniam | AH396: =IF(MONTH(tblSales[[#This Row],[Invoice Date]])>=4,MONTH(tblSales[[#This Row],[Invoice Date]]),MONTH(tblSales[[#This Row],[Invoice Date]])+12) -> 10 | AI396: =DATE(YEAR(tblSales[[#This Row],[Invoice Date]]),MONTH(tblSales[[#This Row],[Invoice Date]]),1) -> 45566 | AJ396: =_xlfn.XLOOKUP(tblSales[[#This Row],[Product_ID]],Products!$A:$A,Products!$B:$B,"Unknown") -> Aurelia Necklace Grey | AK396: =IFERROR(tblSales[[#This Row],[Profit]]/tblSales[[#This Row],[Sales Amount]],0) -> 0.1858669 | AL396: =IF(tblSales[[#This Row],[Discount %]]<=5,"0-5%", IF(tblSales[[#This Row],[Discount %]]<=10,"5-10%", IF(tblSales[[#This Row],[Discount %]]<=15,"10-15%", IF(tblSales[[#This Row],[Discount %]]<=20,"15-20%","20%+")))) -> 0-5%
A397: INV100395 | B397: 45464 | C397: CUST0482 | D397: PRD0213 | E397: STR087 | F397: EMP0285 | G397: 3 | H397: 6700.89 | I397: 25 | J397: 5025.67 | K397: 3 | L397: 452.31 | M397: 15529.31 | N397: 14601.63 | O397: =(M397-N397-L397) -> 475.37 | P397: Debit Card | Q397: =TRIM(CLEAN(P397)) -> Debit Card | R397: Online | S397: Not Returned | T397: 14:12 | U397: Weekday | V397: =TEXT(tblSales[[#This Row],[Invoice Date]],"mmm") -> Jun | W397: =MONTH(tblSales[[#This Row],[Invoice Date]]) -> 6 | X397: =YEAR(tblSales[[#This Row],[Invoice Date]]) -> 2024 | Y397: =TEXT(tblSales[[#This Row],[Invoice Date]],"mmm-yyyy") -> Jun-2024 | Z397: =_xlfn.XLOOKUP(tblSales[[#This Row],[Product_ID]],Products!$A:$A,Products!$C:$C,"Women Dresses") -> Jewellery | AA397: =_xlfn.XLOOKUP(tblSales[[#This Row],[Product_ID]],Products!$A:$A,Products!$D:$D,"Unknown") -> Earrings | AB397: =_xlfn.XLOOKUP(tblSales[[#This Row],[Product_ID]],Products!$A:$A,Products!$E:$E,"Unknown") -> Global Desi | AC397: =_xlfn.XLOOKUP(tblSales[[#This Row],[Store_ID]],Stores!$A:$A,Stores!$B:$B,"Unknown") -> TrendMart Salem Outlet | AD397: =_xlfn.XLOOKUP(tblSales[[#This Row],[Store_ID]],Stores!$A:$A,Stores!$E:$E,"Unknown") -> South Zone 1 | AE397: =_xlfn.XLOOKUP(tblSales[[#This Row],[Customer_ID]],Customers!$A:$A,Customers!$B:$B,"Unknown") -> Suresh Mishra | AF397: =_xlfn.XLOOKUP(tblSales[[#This Row],[Customer_ID]],Customers!$A:$A,Customers!$J:$J,"Unknown") -> Silver | AG397: =_xlfn.XLOOKUP(tblSales[[#This Row],[Employee_ID]],Employees!$A:$A,Employees!$B:$B,"Unknown") -> Chandran Krishnan | AH397: =IF(MONTH(tblSales[[#This Row],[Invoice Date]])>=4,MONTH(tblSales[[#This Row],[Invoice Date]]),MONTH(tblSales[[#This Row],[Invoice Date]])+12) -> 6 | AI397: =DATE(YEAR(tblSales[[#This Row],[Invoice Date]]),MONTH(tblSales[[#This Row],[Invoice Date]]),1) -> 45444 | AJ397: =_xlfn.XLOOKUP(tblSales[[#This Row],[Product_ID]],Products!$A:$A,Products!$B:$B,"Unknown") -> Global Desi Earrings Green | AK397: =IFERROR(tblSales[[#This Row],[Profit]]/tblSales[[#This Row],[Sales Amount]],0) -> 0.030611148 | AL397: =IF(tblSales[[#This Row],[Discount %]]<=5,"0-5%", IF(tblSales[[#This Row],[Discount %]]<=10,"5-10%", IF(tblSales[[#This Row],[Discount %]]<=15,"10-15%", IF(tblSales[[#This Row],[Discount %]]<=20,"15-20%","20%+")))) -> 20%+
A398: INV100396 | B398: 45472 | C398: CUST0532 | D398: PRD0130 | E398: STR060 | F398: EMP0170 | G398: 1 | H398: 1522 | I398: 10 | J398: 152.2 | K398: 12 | L398: 164.38 | M398: 1534.18 | N398: 962.17 | O398: =(M398-N398-L398) -> 407.63 | P398: UPI | Q398: =TRIM(CLEAN(P398)) -> UPI | R398: Online | S398: Not Returned | T398: 20:41 | U398: Weekend | V398: =TEXT(tblSales[[#This Row],[Invoice Date]],"mmm") -> Jun | W398: =MONTH(tblSales[[#This Row],[Invoice Date]]) -> 6 | X398: =YEAR(tblSales[[#This Row],[Invoice Date]]) -> 2024 | Y398: =TEXT(tblSales[[#This Row],[Invoice Date]],"mmm-yyyy") -> Jun-2024 | Z398: =_xlfn.XLOOKUP(tblSales[[#This Row],[Product_ID]],Products!$A:$A,Products!$C:$C,"Women Dresses") -> Women Sarees | AA398: =_xlfn.XLOOKUP(tblSales[[#This Row],[Product_ID]],Products!$A:$A,Products!$D:$D,"Unknown") -> Cotton Saree | AB398: =_xlfn.XLOOKUP(tblSales[[#This Row],[Product_ID]],Products!$A:$A,Products!$E:$E,"Unknown") -> Spykar | AC398: =_xlfn.XLOOKUP(tblSales[[#This Row],[Store_ID]],Stores!$A:$A,Stores!$B:$B,"Unknown") -> TrendMart Tirunelveli Flagship | AD398: =_xlfn.XLOOKUP(tblSales[[#This Row],[Store_ID]],Stores!$A:$A,Stores!$E:$E,"Unknown") -> South Zone 1 | AE398: =_xlfn.XLOOKUP(tblSales[[#This Row],[Customer_ID]],Customers!$A:$A,Customers!$B:$B,"Unknown") -> Ravi Subramaniam | AF398: =_xlfn.XLOOKUP(tblSales[[#This Row],[Customer_ID]],Customers!$A:$A,Customers!$J:$J,"Unknown") -> Regular | AG398: =_xlfn.XLOOKUP(tblSales[[#This Row],[Employee_ID]],Employees!$A:$A,Employees!$B:$B,"Unknown") -> Jyothi Prasad | AH398: =IF(MONTH(tblSales[[#This Row],[Invoice Date]])>=4,MONTH(tblSales[[#This Row],[Invoice Date]]),MONTH(tblSales[[#This Row],[Invoice Date]])+12) -> 6 | AI398: =DATE(YEAR(tblSales[[#This Row],[Invoice Date]]),MONTH(tblSales[[#This Row],[Invoice Date]]),1) -> 45444 | AJ398: =_xlfn.XLOOKUP(tblSales[[#This Row],[Product_ID]],Products!$A:$A,Products!$B:$B,"Unknown") -> Spykar Cotton Saree Black | AK398: =IFERROR(tblSales[[#This Row],[Profit]]/tblSales[[#This Row],[Sales Amount]],0) -> 0.26569894 | AL398: =IF(tblSales[[#This Row],[Discount %]]<=5,"0-5%", IF(tblSales[[#This Row],[Discount %]]<=10,"5-10%", IF(tblSales[[#This Row],[Discount %]]<=15,"10-15%", IF(tblSales[[#This Row],[Discount %]]<=20,"15-20%","20%+")))) -> 5-10%
A399: INV100397 | B399: 45473 | C399: CUST0277 | D399: PRD0048 | E399: STR112 | F399: EMP0285 | G399: 2 | H399: 1175.1 | I399: 0 | J399: 0 | K399: 12 | L399: 282.02 | M399: 2632.22 | N399: 1167.72 | O399: =(M399-N399-L399) -> 1182.48 | P399: UPI | Q399: =TRIM(CLEAN(P399)) -> UPI | R399: Offline | S399: Not Returned | T399: 19:18 | U399: Weekend | V399: =TEXT(tblSales[[#This Row],[Invoice Date]],"mmm") -> Jun | W399: =MONTH(tblSales[[#This Row],[Invoice Date]]) -> 6 | X399: =YEAR(tblSales[[#This Row],[Invoice Date]]) -> 2024 | Y399: =TEXT(tblSales[[#This Row],[Invoice Date]],"mmm-yyyy") -> Jun-2024 | Z399: =_xlfn.XLOOKUP(tblSales[[#This Row],[Product_ID]],Products!$A:$A,Products!$C:$C,"Women Dresses") -> Accessories | AA399: =_xlfn.XLOOKUP(tblSales[[#This Row],[Product_ID]],Products!$A:$A,Products!$D:$D,"Unknown") -> Tie | AB399: =_xlfn.XLOOKUP(tblSales[[#This Row],[Product_ID]],Products!$A:$A,Products!$E:$E,"Unknown") -> Being Human | AC399: =_xlfn.XLOOKUP(tblSales[[#This Row],[Store_ID]],Stores!$A:$A,Stores!$B:$B,"Unknown") -> TrendMart Guntur Outlet | AD399: =_xlfn.XLOOKUP(tblSales[[#This Row],[Store_ID]],Stores!$A:$A,Stores!$E:$E,"Unknown") -> South Zone 3 | AE399: =_xlfn.XLOOKUP(tblSales[[#This Row],[Customer_ID]],Customers!$A:$A,Customers!$B:$B,"Unknown") -> Kiran Gupta | AF399: =_xlfn.XLOOKUP(tblSales[[#This Row],[Customer_ID]],Customers!$A:$A,Customers!$J:$J,"Unknown") -> Gold | AG399: =_xlfn.XLOOKUP(tblSales[[#This Row],[Employee_ID]],Employees!$A:$A,Employees!$B:$B,"Unknown") -> Chandran Krishnan | AH399: =IF(MONTH(tblSales[[#This Row],[Invoice Date]])>=4,MONTH(tblSales[[#This Row],[Invoice Date]]),MONTH(tblSales[[#This Row],[Invoice Date]])+12) -> 6 | AI399: =DATE(YEAR(tblSales[[#This Row],[Invoice Date]]),MONTH(tblSales[[#This Row],[Invoice Date]]),1) -> 45444 | AJ399: =_xlfn.XLOOKUP(tblSales[[#This Row],[Product_ID]],Products!$A:$A,Products!$B:$B,"Unknown") -> Indian Terrain Denim Shirt Wine | AK399: =IFERROR(tblSales[[#This Row],[Profit]]/tblSales[[#This Row],[Sales Amount]],0) -> 0.44923297 | AL399: =IF(tblSales[[#This Row],[Discount %]]<=5,"0-5%", IF(tblSales[[#This Row],[Discount %]]<=10,"5-10%", IF(tblSales[[#This Row],[Discount %]]<=15,"10-15%", IF(tblSales[[#This Row],[Discount %]]<=20,"15-20%","20%+")))) -> 0-5%
A400: INV100398 | B400: 45405 | C400: CUST0131 | D400: PRD0200 | E400: STR035 | F400: EMP0170 | G400: 4 | H400: 771.33 | I400: 5 | J400: 154.27 | K400: 5 | L400: 146.55 | M400: 3077.6 | N400: 1986.68 | O400: =(M400-N400-L400) -> 944.37 | P400: UPI | Q400: =TRIM(CLEAN(P400)) -> UPI | R400: Online | S400: Not Returned | T400: 12:59 | U400: Weekday | V400: =TEXT(tblSales[[#This Row],[Invoice Date]],"mmm") -> Apr | W400: =MONTH(tblSales[[#This Row],[Invoice Date]]) -> 4 | X400: =YEAR(tblSales[[#This Row],[Invoice Date]]) -> 2024 | Y400: =TEXT(tblSales[[#This Row],[Invoice Date]],"mmm-yyyy") -> Apr-2024 | Z400: =_xlfn.XLOOKUP(tblSales[[#This Row],[Product_ID]],Products!$A:$A,Products!$C:$C,"Women Dresses") -> Women Kurtis | AA400: =_xlfn.XLOOKUP(tblSales[[#This Row],[Product_ID]],Products!$A:$A,Products!$D:$D,"Unknown") -> A-Line Kurti | AB400: =_xlfn.XLOOKUP(tblSales[[#This Row],[Product_ID]],Products!$A:$A,Products!$E:$E,"Unknown") -> Pepe Jeans | AC400: =_xlfn.XLOOKUP(tblSales[[#This Row],[Store_ID]],Stores!$A:$A,Stores!$B:$B,"Unknown") -> TrendMart Vijayawada Mall Kiosk | AD400: =_xlfn.XLOOKUP(tblSales[[#This Row],[Store_ID]],Stores!$A:$A,Stores!$E:$E,"Unknown") -> South Zone 3 | AE400: =_xlfn.XLOOKUP(tblSales[[#This Row],[Customer_ID]],Customers!$A:$A,Customers!$B:$B,"Unknown") -> Jyothi Achari | AF400: =_xlfn.XLOOKUP(tblSales[[#This Row],[Customer_ID]],Customers!$A:$A,Customers!$J:$J,"Unknown") -> Regular | AG400: =_xlfn.XLOOKUP(tblSales[[#This Row],[Employee_ID]],Employees!$A:$A,Employees!$B:$B,"Unknown") -> Jyothi Prasad | AH400: =IF(MONTH(tblSales[[#This Row],[Invoice Date]])>=4,MONTH(tblSales[[#This Row],[Invoice Date]]),MONTH(tblSales[[#This Row],[Invoice Date]])+12) -> 4 | AI400: =DATE(YEAR(tblSales[[#This Row],[Invoice Date]]),MONTH(tblSales[[#This Row],[Invoice Date]]),1) -> 45383 | AJ400: =_xlfn.XLOOKUP(tblSales[[#This Row],[Product_ID]],Products!$A:$A,Products!$B:$B,"Unknown") -> Pepe Jeans A-Line Kurti White | AK400: =IFERROR(tblSales[[#This Row],[Profit]]/tblSales[[#This Row],[Sales Amount]],0) -> 0.30685274 | AL400: =IF(tblSales[[#This Row],[Discount %]]<=5,"0-5%", IF(tblSales[[#This Row],[Discount %]]<=10,"5-10%", IF(tblSales[[#This Row],[Discount %]]<=15,"10-15%", IF(tblSales[[#This Row],[Discount %]]<=20,"15-20%","20%+")))) -> 0-5%
A401: INV100399 | B401: 45555 | C401: CUST0736 | D401: PRD0019 | E401: STR115 | F401: EMP0276 | G401: 3 | H401: 655.45 | I401: 15 | J401: 294.95 | K401: 5 | L401: 83.57 | M401: 1754.97 | N401: 1240.17 | O401: =(M401-N401-L401) -> 431.23 | P401: Cash | Q401: =TRIM(CLEAN(P401)) -> Cash | R401: Online | S401: Not Returned | T401: 21:07 | U401: Weekday | V401: =TEXT(tblSales[[#This Row],[Invoice Date]],"mmm") -> Sep | W401: =MONTH(tblSales[[#This Row],[Invoice Date]]) -> 9 | X401: =YEAR(tblSales[[#This Row],[Invoice Date]]) -> 2024 | Y401: =TEXT(tblSales[[#This Row],[Invoice Date]],"mmm-yyyy") -> Sep-2024 | Z401: =_xlfn.XLOOKUP(tblSales[[#This Row],[Product_ID]],Products!$A:$A,Products!$C:$C,"Women Dresses") -> Kids Wear | AA401: =_xlfn.XLOOKUP(tblSales[[#This Row],[Product_ID]],Products!$A:$A,Products!$D:$D,"Unknown") -> Kids T-Shirt | AB401: =_xlfn.XLOOKUP(tblSales[[#This Row],[Product_ID]],Products!$A:$A,Products!$E:$E,"Unknown") -> Jack & Jones | AC401: =_xlfn.XLOOKUP(tblSales[[#This Row],[Store_ID]],Stores!$A:$A,Stores!$B:$B,"Unknown") -> TrendMart Bengaluru Standard | AD401: =_xlfn.XLOOKUP(tblSales[[#This Row],[Store_ID]],Stores!$A:$A,Stores!$E:$E,"Unknown") -> South Zone 2 | AE401: =_xlfn.XLOOKUP(tblSales[[#This Row],[Customer_ID]],Customers!$A:$A,Customers!$B:$B,"Unknown") -> Yashoda Menon | AF401: =_xlfn.XLOOKUP(tblSales[[#This Row],[Customer_ID]],Customers!$A:$A,Customers!$J:$J,"Unknown") -> Regular | AG401: =_xlfn.XLOOKUP(tblSales[[#This Row],[Employee_ID]],Employees!$A:$A,Employees!$B:$B,"Unknown") -> Manoj Ramachandran | AH401: =IF(MONTH(tblSales[[#This Row],[Invoice Date]])>=4,MONTH(tblSales[[#This Row],[Invoice Date]]),MONTH(tblSales[[#This Row],[Invoice Date]])+12) -> 9 | AI401: =DATE(YEAR(tblSales[[#This Row],[Invoice Date]]),MONTH(tblSales[[#This Row],[Invoice Date]]),1) -> 45536 | AJ401: =_xlfn.XLOOKUP(tblSales[[#This Row],[Product_ID]],Products!$A:$A,Products!$B:$B,"Unknown") -> Sonata Girls Frock Cream | AK401: =IFERROR(tblSales[[#This Row],[Profit]]/tblSales[[#This Row],[Sales Amount]],0) -> 0.2457193 | AL401: =IF(tblSales[[#This Row],[Discount %]]<=5,"0-5%", IF(tblSales[[#This Row],[Discount %]]<=10,"5-10%", IF(tblSales[[#This Row],[Discount %]]<=15,"10-15%", IF(tblSales[[#This Row],[Discount %]]<=20,"15-20%","20%+")))) -> 10-15%
A402: INV100400 | B402: 45449 | C402: CUST0504 | D402: PRD0058 | E402: STR116 | F402: EMP0255 | G402: 0 | H402: 1567.26 | I402: 0 | J402: 0 | K402: 12 | L402: 0 | M402: 0 | N402: 0 | O402: 0 | P402: Debit Card | Q402: =TRIM(CLEAN(P402)) -> Debit Card | R402: Offline | S402: Not Returned | T402: 12:58 | U402: Weekday | V402: =TEXT(tblSales[[#This Row],[Invoice Date]],"mmm") -> Jun | W402: =MONTH(tblSales[[#This Row],[Invoice Date]]) -> 6 | X402: =YEAR(tblSales[[#This Row],[Invoice Date]]) -> 2024 | Y402: =TEXT(tblSales[[#This Row],[Invoice Date]],"mmm-yyyy") -> Jun-2024 | Z402: =_xlfn.XLOOKUP(tblSales[[#This Row],[Product_ID]],Products!$A:$A,Products!$C:$C,"Women Dresses") -> Wallets | AA402: =_xlfn.XLOOKUP(tblSales[[#This Row],[Product_ID]],Products!$A:$A,Products!$D:$D,"Unknown") -> Card Holder | AB402: =_xlfn.XLOOKUP(tblSales[[#This Row],[Product_ID]],Products!$A:$A,Products!$E:$E,"Unknown") -> Nalli Silks | AC402: =_xlfn.XLOOKUP(tblSales[[#This Row],[Store_ID]],Stores!$A:$A,Stores!$B:$B,"Unknown") -> TrendMart Madurai High Street | AD402: =_xlfn.XLOOKUP(tblSales[[#This Row],[Store_ID]],Stores!$A:$A,Stores!$E:$E,"Unknown") -> South Zone 1 | AE402: =_xlfn.XLOOKUP(tblSales[[#This Row],[Customer_ID]],Customers!$A:$A,Customers!$B:$B,"Unknown") -> Hari Reddy | AF402: =_xlfn.XLOOKUP(tblSales[[#This Row],[Customer_ID]],Customers!$A:$A,Customers!$J:$J,"Unknown") -> Gold | AG402: =_xlfn.XLOOKUP(tblSales[[#This Row],[Employee_ID]],Employees!$A:$A,Employees!$B:$B,"Unknown") -> Venkat Sharma | AH402: =IF(MONTH(tblSales[[#This Row],[Invoice Date]])>=4,MONTH(tblSales[[#This Row],[Invoice Date]]),MONTH(tblSales[[#This Row],[Invoice Date]])+12) -> 6 | AI402: =DATE(YEAR(tblSales[[#This Row],[Invoice Date]]),MONTH(tblSales[[#This Row],[Invoice Date]]),1) -> 45444 | AJ402: =_xlfn.XLOOKUP(tblSales[[#This Row],[Product_ID]],Products!$A:$A,Products!$B:$B,"Unknown") -> Nalli Silks Card Holder Beige | AK402: =IFERROR(tblSales[[#This Row],[Profit]]/tblSales[[#This Row],[Sales Amount]],0) -> 0 | AL402: =IF(tblSales[[#This Row],[Discount %]]<=5,"0-5%", IF(tblSales[[#This Row],[Discount %]]<=10,"5-10%", IF(tblSales[[#This Row],[Discount %]]<=15,"10-15%", IF(tblSales[[#This Row],[Discount %]]<=20,"15-20%","20%+")))) -> 0-5%
A403: INV100401 | B403: 45454 | C403: CUST0460 | D403: PRD0122 | E403: STR097 | F403: EMP0255 | G403: 1 | H403: 721.95 | I403: 15 | J403: 108.29 | K403: 3 | L403: 18.41 | M403: 632.07 | N403: 556.99 | O403: =(M403-N403-L403) -> 56.67 | P403: Cash | Q403: =TRIM(CLEAN(P403)) -> Cash | R403: Offline | S403: Not Returned | T403: 21:30 | U403: Weekday | V403: =TEXT(tblSales[[#This Row],[Invoice Date]],"mmm") -> Jun | W403: =MONTH(tblSales[[#This Row],[Invoice Date]]) -> 6 | X403: =YEAR(tblSales[[#This Row],[Invoice Date]]) -> 2024 | Y403: =TEXT(tblSales[[#This Row],[Invoice Date]],"mmm-yyyy") -> Jun-2024 | Z403: =_xlfn.XLOOKUP(tblSales[[#This Row],[Product_ID]],Products!$A:$A,Products!$C:$C,"Women Dresses") -> Jewellery | AA403: =_xlfn.XLOOKUP(tblSales[[#This Row],[Product_ID]],Products!$A:$A,Products!$D:$D,"Unknown") -> Necklace | AB403: =_xlfn.XLOOKUP(tblSales[[#This Row],[Product_ID]],Products!$A:$A,Products!$E:$E,"Unknown") -> Aurelia | AC403: =_xlfn.XLOOKUP(tblSales[[#This Row],[Store_ID]],Stores!$A:$A,Stores!$B:$B,"Unknown") -> TrendMart Thiruvananthapuram High Street | AD403: =_xlfn.XLOOKUP(tblSales[[#This Row],[Store_ID]],Stores!$A:$A,Stores!$E:$E,"Unknown") -> South Zone 1 | AE403: =_xlfn.XLOOKUP(tblSales[[#This Row],[Customer_ID]],Customers!$A:$A,Customers!$B:$B,"Unknown") -> Ramesh Singh | AF403: =_xlfn.XLOOKUP(tblSales[[#This Row],[Customer_ID]],Customers!$A:$A,Customers!$J:$J,"Unknown") -> Silver | AG403: =_xlfn.XLOOKUP(tblSales[[#This Row],[Employee_ID]],Employees!$A:$A,Employees!$B:$B,"Unknown") -> Venkat Sharma | AH403: =IF(MONTH(tblSales[[#This Row],[Invoice Date]])>=4,MONTH(tblSales[[#This Row],[Invoice Date]]),MONTH(tblSales[[#This Row],[Invoice Date]])+12) -> 6 | AI403: =DATE(YEAR(tblSales[[#This Row],[Invoice Date]]),MONTH(tblSales[[#This Row],[Invoice Date]]),1) -> 45444 | AJ403: =_xlfn.XLOOKUP(tblSales[[#This Row],[Product_ID]],Products!$A:$A,Products!$B:$B,"Unknown") -> Aurelia Necklace Grey | AK403: =IFERROR(tblSales[[#This Row],[Profit]]/tblSales[[#This Row],[Sales Amount]],0) -> 0.089657791 | AL403: =IF(tblSales[[#This Row],[Discount %]]<=5,"0-5%", IF(tblSales[[#This Row],[Discount %]]<=10,"5-10%", IF(tblSales[[#This Row],[Discount %]]<=15,"10-15%", IF(tblSales[[#This Row],[Discount %]]<=20,"15-20%","20%+")))) -> 10-15%
A404: INV100402 | B404: 45629 | C404: CUST0809 | D404: PRD0035 | E404: STR021 | F404: EMP0072 | G404: 1 | H404: 850.86 | I404: 20 | J404: 170.17 | K404: 5 | L404: 34.03 | M404: 714.72 | N404: 539.76 | O404: =(M404-N404-L404) -> 140.93 | P404: Debit Card | Q404: =TRIM(CLEAN(P404)) -> Debit Card | R404: Online | S404: Not Returned | T404: 13:09 | U404: Weekday | V404: =TEXT(tblSales[[#This Row],[Invoice Date]],"mmm") -> Dec | W404: =MONTH(tblSales[[#This Row],[Invoice Date]]) -> 12 | X404: =YEAR(tblSales[[#This Row],[Invoice Date]]) -> 2024 | Y404: =TEXT(tblSales[[#This Row],[Invoice Date]],"mmm-yyyy") -> Dec-2024 | Z404: =_xlfn.XLOOKUP(tblSales[[#This Row],[Product_ID]],Products!$A:$A,Products!$C:$C,"Women Dresses") -> Women Kurtis | AA404: =_xlfn.XLOOKUP(tblSales[[#This Row],[Product_ID]],Products!$A:$A,Products!$D:$D,"Unknown") -> Printed Kurti | AB404: =_xlfn.XLOOKUP(tblSales[[#This Row],[Product_ID]],Products!$A:$A,Products!$E:$E,"Unknown") -> Reebok | AC404: =_xlfn.XLOOKUP(tblSales[[#This Row],[Store_ID]],Stores!$A:$A,Stores!$B:$B,"Unknown") -> TrendMart Kozhikode Standard | AD404: =_xlfn.XLOOKUP(tblSales[[#This Row],[Store_ID]],Stores!$A:$A,Stores!$E:$E,"Unknown") -> South Zone 1 | AE404: =_xlfn.XLOOKUP(tblSales[[#This Row],[Customer_ID]],Customers!$A:$A,Customers!$B:$B,"Unknown") -> Ganesh Gupta | AF404: =_xlfn.XLOOKUP(tblSales[[#This Row],[Customer_ID]],Customers!$A:$A,Customers!$J:$J,"Unknown") -> Gold | AG404: =_xlfn.XLOOKUP(tblSales[[#This Row],[Employee_ID]],Employees!$A:$A,Employees!$B:$B,"Unknown") -> Anitha Ramachandran | AH404: =IF(MONTH(tblSales[[#This Row],[Invoice Date]])>=4,MONTH(tblSales[[#This Row],[Invoice Date]]),MONTH(tblSales[[#This Row],[Invoice Date]])+12) -> 12 | AI404: =DATE(YEAR(tblSales[[#This Row],[Invoice Date]]),MONTH(tblSales[[#This Row],[Invoice Date]]),1) -> 45627 | AJ404: =_xlfn.XLOOKUP(tblSales[[#This Row],[Product_ID]],Products!$A:$A,Products!$B:$B,"Unknown") -> Reebok Printed Kurti Wine | AK404: =IFERROR(tblSales[[#This Row],[Profit]]/tblSales[[#This Row],[Sales Amount]],0) -> 0.19718211 | AL404: =IF(tblSales[[#This Row],[Discount %]]<=5,"0-5%", IF(tblSales[[#This Row],[Discount %]]<=10,"5-10%", IF(tblSales[[#This Row],[Discount %]]<=15,"10-15%", IF(tblSales[[#This Row],[Discount %]]<=20,"15-20%","20%+")))) -> 15-20%
A405: INV100403 | B405: 45384 | C405: CUST0308 | D405: PRD0124 | E405: STR102 | F405: EMP0285 | G405: 1 | H405: 697.15 | I405: 30 | J405: 209.15 | K405: 5 | L405: 24.4 | M405: 512.4 | N405: 499.31 | O405: =(M405-N405-L405) -> -11.31 | P405: Credit Card | Q405: =TRIM(CLEAN(P405)) -> Credit Card | R405: Offline | S405: Not Returned | T405: 21:20 | U405: Weekday | V405: =TEXT(tblSales[[#This Row],[Invoice Date]],"mmm") -> Apr | W405: =MONTH(tblSales[[#This Row],[Invoice Date]]) -> 4 | X405: =YEAR(tblSales[[#This Row],[Invoice Date]]) -> 2024 | Y405: =TEXT(tblSales[[#This Row],[Invoice Date]],"mmm-yyyy") -> Apr-2024 | Z405: =_xlfn.XLOOKUP(tblSales[[#This Row],[Product_ID]],Products!$A:$A,Products!$C:$C,"Women Dresses") -> Kids Wear | AA405: =_xlfn.XLOOKUP(tblSales[[#This Row],[Product_ID]],Products!$A:$A,Products!$D:$D,"Unknown") -> Kids Shorts | AB405: =_xlfn.XLOOKUP(tblSales[[#This Row],[Product_ID]],Products!$A:$A,Products!$E:$E,"Unknown") -> Global Desi | AC405: =_xlfn.XLOOKUP(tblSales[[#This Row],[Store_ID]],Stores!$A:$A,Stores!$B:$B,"Unknown") -> TrendMart Tirunelveli High Street | AD405: =_xlfn.XLOOKUP(tblSales[[#This Row],[Store_ID]],Stores!$A:$A,Stores!$E:$E,"Unknown") -> South Zone 1 | AE405: =_xlfn.XLOOKUP(tblSales[[#This Row],[Customer_ID]],Customers!$A:$A,Customers!$B:$B,"Unknown") -> Kalpana Kamath | AF405: =_xlfn.XLOOKUP(tblSales[[#This Row],[Customer_ID]],Customers!$A:$A,Customers!$J:$J,"Unknown") -> Silver | AG405: =_xlfn.XLOOKUP(tblSales[[#This Row],[Employee_ID]],Employees!$A:$A,Employees!$B:$B,"Unknown") -> Chandran Krishnan | AH405: =IF(MONTH(tblSales[[#This Row],[Invoice Date]])>=4,MONTH(tblSales[[#This Row],[Invoice Date]]),MONTH(tblSales[[#This Row],[Invoice Date]])+12) -> 4 | AI405: =DATE(YEAR(tblSales[[#This Row],[Invoice Date]]),MONTH(tblSales[[#This Row],[Invoice Date]]),1) -> 45383 | AJ405: =_xlfn.XLOOKUP(tblSales[[#This Row],[Product_ID]],Products!$A:$A,Products!$B:$B,"Unknown") -> Global Desi Kids Shorts Charcoal | AK405: =IFERROR(tblSales[[#This Row],[Profit]]/tblSales[[#This Row],[Sales Amount]],0) -> -0.0220726 | AL405: =IF(tblSales[[#This Row],[Discount %]]<=5,"0-5%", IF(tblSales[[#This Row],[Discount %]]<=10,"5-10%", IF(tblSales[[#This Row],[Discount %]]<=15,"10-15%", IF(tblSales[[#This Row],[Discount %]]<=20,"15-20%","20%+")))) -> 20%+
A406: INV100404 | B406: 45598 | C406: CUST0255 | D406: PRD0210 | E406: STR015 | F406: EMP0260 | G406: 2 | H406: 1430.69 | I406: 20 | J406: 572.28 | K406: 12 | L406: 274.69 | M406: 2563.79 | N406: 2041.8 | O406: =(M406-N406-L406) -> 247.3 | P406: UPI | Q406: =TRIM(CLEAN(P406)) -> UPI | R406: Offline | S406: Not Returned | T406: 14:36 | U406: Weekend | V406: =TEXT(tblSales[[#This Row],[Invoice Date]],"mmm") -> Nov | W406: =MONTH(tblSales[[#This Row],[Invoice Date]]) -> 11 | X406: =YEAR(tblSales[[#This Row],[Invoice Date]]) -> 2024 | Y406: =TEXT(tblSales[[#This Row],[Invoice Date]],"mmm-yyyy") -> Nov-2024 | Z406: =_xlfn.XLOOKUP(tblSales[[#This Row],[Product_ID]],Products!$A:$A,Products!$C:$C,"Women Dresses") -> Women Sarees | AA406: =_xlfn.XLOOKUP(tblSales[[#This Row],[Product_ID]],Products!$A:$A,Products!$D:$D,"Unknown") -> Georgette Saree | AB406: =_xlfn.XLOOKUP(tblSales[[#This Row],[Product_ID]],Products!$A:$A,Products!$E:$E,"Unknown") -> Jack & Jones | AC406: =_xlfn.XLOOKUP(tblSales[[#This Row],[Store_ID]],Stores!$A:$A,Stores!$B:$B,"Unknown") -> TrendMart Madurai Mall Kiosk | AD406: =_xlfn.XLOOKUP(tblSales[[#This Row],[Store_ID]],Stores!$A:$A,Stores!$E:$E,"Unknown") -> South Zone 1 | AE406: =_xlfn.XLOOKUP(tblSales[[#This Row],[Customer_ID]],Customers!$A:$A,Customers!$B:$B,"Unknown") -> Akhila Sundaram | AF406: =_xlfn.XLOOKUP(tblSales[[#This Row],[Customer_ID]],Customers!$A:$A,Customers!$J:$J,"Unknown") -> Regular | AG406: =_xlfn.XLOOKUP(tblSales[[#This Row],[Employee_ID]],Employees!$A:$A,Employees!$B:$B,"Unknown") -> Malathi Varma | AH406: =IF(MONTH(tblSales[[#This Row],[Invoice Date]])>=4,MONTH(tblSales[[#This Row],[Invoice Date]]),MONTH(tblSales[[#This Row],[Invoice Date]])+12) -> 11 | AI406: =DATE(YEAR(tblSales[[#This Row],[Invoice Date]]),MONTH(tblSales[[#This Row],[Invoice Date]]),1) -> 45597 | AJ406: =_xlfn.XLOOKUP(tblSales[[#This Row],[Product_ID]],Products!$A:$A,Products!$B:$B,"Unknown") -> Jack & Jones Georgette Saree Sky Blue | AK406: =IFERROR(tblSales[[#This Row],[Profit]]/tblSales[[#This Row],[Sales Amount]],0) -> 0.096458758 | AL406: =IF(tblSales[[#This Row],[Discount %]]<=5,"0-5%", IF(tblSales[[#This Row],[Discount %]]<=10,"5-10%", IF(tblSales[[#This Row],[Discount %]]<=15,"10-15%", IF(tblSales[[#This Row],[Discount %]]<=20,"15-20%","20%+")))) -> 15-20%
A407: INV100405 | B407: 45451 | C407: CUST0284 | D407: PRD0004 | E407: STR039 | F407: EMP0258 | G407: 3 | H407: 1902.88 | I407: 5 | J407: 285.43 | K407: 12 | L407: 650.79 | M407: 6074 | N407: 3433.77 | O407: =(M407-N407-L407) -> 1989.44 | P407: Credit Card | Q407: =TRIM(CLEAN(P407)) -> Credit Card | R407: Offline | S407: Not Returned | T407: 13:21 | U407: Weekend | V407: =TEXT(tblSales[[#This Row],[Invoice Date]],"mmm") -> Jun | W407: =MONTH(tblSales[[#This Row],[Invoice Date]]) -> 6 | X407: =YEAR(tblSales[[#This Row],[Invoice Date]]) -> 2024 | Y407: =TEXT(tblSales[[#This Row],[Invoice Date]],"mmm-yyyy") -> Jun-2024 | Z407: =_xlfn.XLOOKUP(tblSales[[#This Row],[Product_ID]],Products!$A:$A,Products!$C:$C,"Women Dresses") -> Women Dresses | AA407: =_xlfn.XLOOKUP(tblSales[[#This Row],[Product_ID]],Products!$A:$A,Products!$D:$D,"Unknown") -> Bodycon Dress | AB407: =_xlfn.XLOOKUP(tblSales[[#This Row],[Product_ID]],Products!$A:$A,Products!$E:$E,"Unknown") -> Westside | AC407: =_xlfn.XLOOKUP(tblSales[[#This Row],[Store_ID]],Stores!$A:$A,Stores!$B:$B,"Unknown") -> TrendMart Bengaluru High Street | AD407: =_xlfn.XLOOKUP(tblSales[[#This Row],[Store_ID]],Stores!$A:$A,Stores!$E:$E,"Unknown") -> South Zone 2 | AE407: =_xlfn.XLOOKUP(tblSales[[#This Row],[Customer_ID]],Customers!$A:$A,Customers!$B:$B,"Unknown") -> Janani Krishnan | AF407: =_xlfn.XLOOKUP(tblSales[[#This Row],[Customer_ID]],Customers!$A:$A,Customers!$J:$J,"Unknown") -> Platinum | AG407: =_xlfn.XLOOKUP(tblSales[[#This Row],[Employee_ID]],Employees!$A:$A,Employees!$B:$B,"Unknown") -> Preethi Singh | AH407: =IF(MONTH(tblSales[[#This Row],[Invoice Date]])>=4,MONTH(tblSales[[#This Row],[Invoice Date]]),MONTH(tblSales[[#This Row],[Invoice Date]])+12) -> 6 | AI407: =DATE(YEAR(tblSales[[#This Row],[Invoice Date]]),MONTH(tblSales[[#This Row],[Invoice Date]]),1) -> 45444 | AJ407: =_xlfn.XLOOKUP(tblSales[[#This Row],[Product_ID]],Products!$A:$A,Products!$B:$B,"Unknown") -> Westside Bodycon Dress Green | AK407: =IFERROR(tblSales[[#This Row],[Profit]]/tblSales[[#This Row],[Sales Amount]],0) -> 0.32753375 | AL407: =IF(tblSales[[#This Row],[Discount %]]<=5,"0-5%", IF(tblSales[[#This Row],[Discount %]]<=10,"5-10%", IF(tblSales[[#This Row],[Discount %]]<=15,"10-15%", IF(tblSales[[#This Row],[Discount %]]<=20,"15-20%","20%+")))) -> 0-5%
A408: INV100406 | B408: 45499 | C408: CUST0253 | D408: PRD0090 | E408: STR003 | F408: EMP0127 | G408: 5 | H408: 653.08 | I408: 10 | J408: 326.54 | K408: 5 | L408: 146.94 | M408: 3085.8 | N408: 2096.4 | O408: =(M408-N408-L408) -> 842.46 | P408: UPI | Q408: =TRIM(CLEAN(P408)) -> UPI | R408: Online | S408: Not Returned | T408: 16:19 | U408: Weekday | V408: =TEXT(tblSales[[#This Row],[Invoice Date]],"mmm") -> Jul | W408: =MONTH(tblSales[[#This Row],[Invoice Date]]) -> 7 | X408: =YEAR(tblSales[[#This Row],[Invoice Date]]) -> 2024 | Y408: =TEXT(tblSales[[#This Row],[Invoice Date]],"mmm-yyyy") -> Jul-2024 | Z408: =_xlfn.XLOOKUP(tblSales[[#This Row],[Product_ID]],Products!$A:$A,Products!$C:$C,"Women Dresses") -> Men T-Shirts | AA408: =_xlfn.XLOOKUP(tblSales[[#This Row],[Product_ID]],Products!$A:$A,Products!$D:$D,"Unknown") -> Round Neck | AB408: =_xlfn.XLOOKUP(tblSales[[#This Row],[Product_ID]],Products!$A:$A,Products!$E:$E,"Unknown") -> Peter England | AC408: =_xlfn.XLOOKUP(tblSales[[#This Row],[Store_ID]],Stores!$A:$A,Stores!$B:$B,"Unknown") -> TrendMart Tumakuru High Street | AD408: =_xlfn.XLOOKUP(tblSales[[#This Row],[Store_ID]],Stores!$A:$A,Stores!$E:$E,"Unknown") -> South Zone 2 | AE408: =_xlfn.XLOOKUP(tblSales[[#This Row],[Customer_ID]],Customers!$A:$A,Customers!$B:$B,"Unknown") -> Gayathri Chandran | AF408: =_xlfn.XLOOKUP(tblSales[[#This Row],[Customer_ID]],Customers!$A:$A,Customers!$J:$J,"Unknown") -> Gold | AG408: =_xlfn.XLOOKUP(tblSales[[#This Row],[Employee_ID]],Employees!$A:$A,Employees!$B:$B,"Unknown") -> Chandra Reddy | AH408: =IF(MONTH(tblSales[[#This Row],[Invoice Date]])>=4,MONTH(tblSales[[#This Row],[Invoice Date]]),MONTH(tblSales[[#This Row],[Invoice Date]])+12) -> 7 | AI408: =DATE(YEAR(tblSales[[#This Row],[Invoice Date]]),MONTH(tblSales[[#This Row],[Invoice Date]]),1) -> 45474 | AJ408: =_xlfn.XLOOKUP(tblSales[[#This Row],[Product_ID]],Products!$A:$A,Products!$B:$B,"Unknown") -> Peter England Round Neck Sky Blue | AK408: =IFERROR(tblSales[[#This Row],[Profit]]/tblSales[[#This Row],[Sales Amount]],0) -> 0.27301186 | AL408: =IF(tblSales[[#This Row],[Discount %]]<=5,"0-5%", IF(tblSales[[#This Row],[Discount %]]<=10,"5-10%", IF(tblSales[[#This Row],[Discount %]]<=15,"10-15%", IF(tblSales[[#This Row],[Discount %]]<=20,"15-20%","20%+")))) -> 5-10%
A409: INV100407 | B409: 45453 | C409: CUST0649 | D409: PRD0005 | E409: STR069 | F409: EMP0205 | G409: 2 | H409: 2325.99 | I409: 0 | J409: 0 | K409: 12 | L409: 558.24 | M409: 5210.22 | N409: 3612.06 | O409: =(M409-N409-L409) -> 1039.92 | P409: UPI | Q409: =TRIM(CLEAN(P409)) -> UPI | R409: Online | S409: Not Returned | T409: 10:08 | U409: Weekday | V409: =TEXT(tblSales[[#This Row],[Invoice Date]],"mmm") -> Jun | W409: =MONTH(tblSales[[#This Row],[Invoice Date]]) -> 6 | X409: =YEAR(tblSales[[#This Row],[Invoice Date]]) -> 2024 | Y409: =TEXT(tblSales[[#This Row],[Invoice Date]],"mmm-yyyy") -> Jun-2024 | Z409: =_xlfn.XLOOKUP(tblSales[[#This Row],[Product_ID]],Products!$A:$A,Products!$C:$C,"Women Dresses") -> Watches | AA409: =_xlfn.XLOOKUP(tblSales[[#This Row],[Product_ID]],Products!$A:$A,Products!$D:$D,"Unknown") -> Digital Watch | AB409: =_xlfn.XLOOKUP(tblSales[[#This Row],[Product_ID]],Products!$A:$A,Products!$E:$E,"Unknown") -> Woodland | AC409: =_xlfn.XLOOKUP(tblSales[[#This Row],[Store_ID]],Stores!$A:$A,Stores!$B:$B,"Unknown") -> TrendMart Erode Mall Kiosk | AD409: =_xlfn.XLOOKUP(tblSales[[#This Row],[Store_ID]],Stores!$A:$A,Stores!$E:$E,"Unknown") -> South Zone 1 | AE409: =_xlfn.XLOOKUP(tblSales[[#This Row],[Customer_ID]],Customers!$A:$A,Customers!$B:$B,"Unknown") -> Bala Mishra | AF409: =_xlfn.XLOOKUP(tblSales[[#This Row],[Customer_ID]],Customers!$A:$A,Customers!$J:$J,"Unknown") -> Gold | AG409: =_xlfn.XLOOKUP(tblSales[[#This Row],[Employee_ID]],Employees!$A:$A,Employees!$B:$B,"Unknown") -> Malini Gowda | AH409: =IF(MONTH(tblSales[[#This Row],[Invoice Date]])>=4,MONTH(tblSales[[#This Row],[Invoice Date]]),MONTH(tblSales[[#This Row],[Invoice Date]])+12) -> 6 | AI409: =DATE(YEAR(tblSales[[#This Row],[Invoice Date]]),MONTH(tblSales[[#This Row],[Invoice Date]]),1) -> 45444 | AJ409: =_xlfn.XLOOKUP(tblSales[[#This Row],[Product_ID]],Products!$A:$A,Products!$B:$B,"Unknown") -> Woodland Digital Watch Brown | AK409: =IFERROR(tblSales[[#This Row],[Profit]]/tblSales[[#This Row],[Sales Amount]],0) -> 0.19959234 | AL409: =IF(tblSales[[#This Row],[Discount %]]<=5,"0-5%", IF(tblSales[[#This Row],[Discount %]]<=10,"5-10%", IF(tblSales[[#This Row],[Discount %]]<=15,"10-15%", IF(tblSales[[#This Row],[Discount %]]<=20,"15-20%","20%+")))) -> 0-5%
A410: INV100408 | B410: 45416 | C410: CUST0375 | D410: PRD0030 | E410: STR114 | F410: EMP0207 | G410: 2 | H410: 703.06 | I410: 0 | J410: 0 | K410: 5 | L410: 70.31 | M410: 1476.43 | N410: 838.8 | O410: =(M410-N410-L410) -> 567.32 | P410: Debit Card | Q410: =TRIM(CLEAN(P410)) -> Debit Card | R410: Online | S410: Not Returned | T410: 20:52 | U410: Weekend | V410: =TEXT(tblSales[[#This Row],[Invoice Date]],"mmm") -> May | W410: =MONTH(tblSales[[#This Row],[Invoice Date]]) -> 5 | X410: =YEAR(tblSales[[#This Row],[Invoice Date]]) -> 2024 | Y410: =TEXT(tblSales[[#This Row],[Invoice Date]],"mmm-yyyy") -> May-2024 | Z410: =_xlfn.XLOOKUP(tblSales[[#This Row],[Product_ID]],Products!$A:$A,Products!$C:$C,"Women Dresses") -> Women Tops | AA410: =_xlfn.XLOOKUP(tblSales[[#This Row],[Product_ID]],Products!$A:$A,Products!$D:$D,"Unknown") -> Tunic | AB410: =_xlfn.XLOOKUP(tblSales[[#This Row],[Product_ID]],Products!$A:$A,Products!$E:$E,"Unknown") -> Jack & Jones | AC410: =_xlfn.XLOOKUP(tblSales[[#This Row],[Store_ID]],Stores!$A:$A,Stores!$B:$B,"Unknown") -> TrendMart Thiruvananthapuram High Street | AD410: =_xlfn.XLOOKUP(tblSales[[#This Row],[Store_ID]],Stores!$A:$A,Stores!$E:$E,"Unknown") -> South Zone 1 | AE410: =_xlfn.XLOOKUP(tblSales[[#This Row],[Customer_ID]],Customers!$A:$A,Customers!$B:$B,"Unknown") -> Venkat Pillai | AF410: =_xlfn.XLOOKUP(tblSales[[#This Row],[Customer_ID]],Customers!$A:$A,Customers!$J:$J,"Unknown") -> Regular | AG410: =_xlfn.XLOOKUP(tblSales[[#This Row],[Employee_ID]],Employees!$A:$A,Employees!$B:$B,"Unknown") -> Chitra Bhat | AH410: =IF(MONTH(tblSales[[#This Row],[Invoice Date]])>=4,MONTH(tblSales[[#This Row],[Invoice Date]]),MONTH(tblSales[[#This Row],[Invoice Date]])+12) -> 5 | AI410: =DATE(YEAR(tblSales[[#This Row],[Invoice Date]]),MONTH(tblSales[[#This Row],[Invoice Date]]),1) -> 45413 | AJ410: =_xlfn.XLOOKUP(tblSales[[#This Row],[Product_ID]],Products!$A:$A,Products!$B:$B,"Unknown") -> Jack & Jones Tunic Olive | AK410: =IFERROR(tblSales[[#This Row],[Profit]]/tblSales[[#This Row],[Sales Amount]],0) -> 0.3842512 | AL410: =IF(tblSales[[#This Row],[Discount %]]<=5,"0-5%", IF(tblSales[[#This Row],[Discount %]]<=10,"5-10%", IF(tblSales[[#This Row],[Discount %]]<=15,"10-15%", IF(tblSales[[#This Row],[Discount %]]<=20,"15-20%","20%+")))) -> 0-5%
A411: INV100409 | B411: 45515 | C411: CUST0636 | D411: PRD0192 | E411: STR020 | F411: EMP0020 | G411: 2 | H411: 444.77 | I411: 0 | J411: 0 | K411: 5 | L411: 44.48 | M411: 934.02 | N411: 524.12 | O411: =(M411-N411-L411) -> 365.42 | P411: UPI | Q411: =TRIM(CLEAN(P411)) -> UPI | R411: Offline | S411: Not Returned | T411: 11:37 | U411: Weekend | V411: =TEXT(tblSales[[#This Row],[Invoice Date]],"mmm") -> Aug | W411: =MONTH(tblSales[[#This Row],[Invoice Date]]) -> 8 | X411: =YEAR(tblSales[[#This Row],[Invoice Date]]) -> 2024 | Y411: =TEXT(tblSales[[#This Row],[Invoice Date]],"mmm-yyyy") -> Aug-2024 | Z411: =_xlfn.XLOOKUP(tblSales[[#This Row],[Product_ID]],Products!$A:$A,Products!$C:$C,"Women Dresses") -> Men T-Shirts | AA411: =_xlfn.XLOOKUP(tblSales[[#This Row],[Product_ID]],Products!$A:$A,Products!$D:$D,"Unknown") -> Round Neck | AB411: =_xlfn.XLOOKUP(tblSales[[#This Row],[Product_ID]],Products!$A:$A,Products!$E:$E,"Unknown") -> Skechers | AC411: =_xlfn.XLOOKUP(tblSales[[#This Row],[Store_ID]],Stores!$A:$A,Stores!$B:$B,"Unknown") -> TrendMart Guntur Standard | AD411: =_xlfn.XLOOKUP(tblSales[[#This Row],[Store_ID]],Stores!$A:$A,Stores!$E:$E,"Unknown") -> South Zone 3 | AE411: =_xlfn.XLOOKUP(tblSales[[#This Row],[Customer_ID]],Customers!$A:$A,Customers!$B:$B,"Unknown") -> Gayathri Gowda | AF411: =_xlfn.XLOOKUP(tblSales[[#This Row],[Customer_ID]],Customers!$A:$A,Customers!$J:$J,"Unknown") -> Regular | AG411: =_xlfn.XLOOKUP(tblSales[[#This Row],[Employee_ID]],Employees!$A:$A,Employees!$B:$B,"Unknown") -> Eswar Prasad | AH411: =IF(MONTH(tblSales[[#This Row],[Invoice Date]])>=4,MONTH(tblSales[[#This Row],[Invoice Date]]),MONTH(tblSales[[#This Row],[Invoice Date]])+12) -> 8 | AI411: =DATE(YEAR(tblSales[[#This Row],[Invoice Date]]),MONTH(tblSales[[#This Row],[Invoice Date]]),1) -> 45505 | AJ411: =_xlfn.XLOOKUP(tblSales[[#This Row],[Product_ID]],Products!$A:$A,Products!$B:$B,"Unknown") -> Skechers Round Neck Red | AK411: =IFERROR(tblSales[[#This Row],[Profit]]/tblSales[[#This Row],[Sales Amount]],0) -> 0.39123359 | AL411: =IF(tblSales[[#This Row],[Discount %]]<=5,"0-5%", IF(tblSales[[#This Row],[Discount %]]<=10,"5-10%", IF(tblSales[[#This Row],[Discount %]]<=15,"10-15%", IF(tblSales[[#This Row],[Discount %]]<=20,"15-20%","20%+")))) -> 0-5%
A412: INV100410 | B412: 45497 | C412: CUST0358 | D412: PRD0007 | E412: STR086 | F412: EMP0141 | G412: 1 | H412: 4527.71 | I412: 0 | J412: 0 | K412: 12 | L412: 543.33 | M412: 5071.04 | N412: 3236.57 | O412: =(M412-N412-L412) -> 1291.14 | P412: Debit Card | Q412: =TRIM(CLEAN(P412)) -> Debit Card | R412: Offline | S412: Not Returned | T412: 11:21 | U412: Weekday | V412: =TEXT(tblSales[[#This Row],[Invoice Date]],"mmm") -> Jul | W412: =MONTH(tblSales[[#This Row],[Invoice Date]]) -> 7 | X412: =YEAR(tblSales[[#This Row],[Invoice Date]]) -> 2024 | Y412: =TEXT(tblSales[[#This Row],[Invoice Date]],"mmm-yyyy") -> Jul-2024 | Z412: =_xlfn.XLOOKUP(tblSales[[#This Row],[Product_ID]],Products!$A:$A,Products!$C:$C,"Women Dresses") -> Women Sarees | AA412: =_xlfn.XLOOKUP(tblSales[[#This Row],[Product_ID]],Products!$A:$A,Products!$D:$D,"Unknown") -> Silk Saree | AB412: =_xlfn.XLOOKUP(tblSales[[#This Row],[Product_ID]],Products!$A:$A,Products!$E:$E,"Unknown") -> Pepe Jeans | AC412: =_xlfn.XLOOKUP(tblSales[[#This Row],[Store_ID]],Stores!$A:$A,Stores!$B:$B,"Unknown") -> TrendMart Thiruvananthapuram Outlet | AD412: =_xlfn.XLOOKUP(tblSales[[#This Row],[Store_ID]],Stores!$A:$A,Stores!$E:$E,"Unknown") -> South Zone 1 | AE412: =_xlfn.XLOOKUP(tblSales[[#This Row],[Customer_ID]],Customers!$A:$A,Customers!$B:$B,"Unknown") -> Rohit Kumar | AF412: =_xlfn.XLOOKUP(tblSales[[#This Row],[Customer_ID]],Customers!$A:$A,Customers!$J:$J,"Unknown") -> Regular | AG412: =_xlfn.XLOOKUP(tblSales[[#This Row],[Employee_ID]],Employees!$A:$A,Employees!$B:$B,"Unknown") -> Dhruv Mishra | AH412: =IF(MONTH(tblSales[[#This Row],[Invoice Date]])>=4,MONTH(tblSales[[#This Row],[Invoice Date]]),MONTH(tblSales[[#This Row],[Invoice Date]])+12) -> 7 | AI412: =DATE(YEAR(tblSales[[#This Row],[Invoice Date]]),MONTH(tblSales[[#This Row],[Invoice Date]]),1) -> 45474 | AJ412: =_xlfn.XLOOKUP(tblSales[[#This Row],[Product_ID]],Products!$A:$A,Products!$B:$B,"Unknown") -> Pepe Jeans Silk Saree Navy Blue | AK412: =IFERROR(tblSales[[#This Row],[Profit]]/tblSales[[#This Row],[Sales Amount]],0) -> 0.25461049 | AL412: =IF(tblSales[[#This Row],[Discount %]]<=5,"0-5%", IF(tblSales[[#This Row],[Discount %]]<=10,"5-10%", IF(tblSales[[#This Row],[Discount %]]<=15,"10-15%", IF(tblSales[[#This Row],[Discount %]]<=20,"15-20%","20%+")))) -> 0-5%
A413: INV100411 | B413: 45699 | C413: CUST0402 | D413: PRD0250 | E413: STR052 | F413: EMP0215 | G413: 1 | H413: 4786.29 | I413: 10 | J413: 478.63 | K413: 12 | L413: 516.92 | M413: 4824.58 | N413: 3650.55 | O413: =(M413-N413-L413) -> 657.11 | P413: Cash | Q413: =TRIM(CLEAN(P413)) -> Cash | R413: Offline | S413: Returned | T413: 16:07 | U413: Weekday | V413: =TEXT(tblSales[[#This Row],[Invoice Date]],"mmm") -> Feb | W413: =MONTH(tblSales[[#This Row],[Invoice Date]]) -> 2 | X413: =YEAR(tblSales[[#This Row],[Invoice Date]]) -> 2025 | Y413: =TEXT(tblSales[[#This Row],[Invoice Date]],"mmm-yyyy") -> Feb-2025 | Z413: =_xlfn.XLOOKUP(tblSales[[#This Row],[Product_ID]],Products!$A:$A,Products!$C:$C,"Women Dresses") -> Watches | AA413: =_xlfn.XLOOKUP(tblSales[[#This Row],[Product_ID]],Products!$A:$A,Products!$D:$D,"Unknown") -> Digital Watch | AB413: =_xlfn.XLOOKUP(tblSales[[#This Row],[Product_ID]],Products!$A:$A,Products!$E:$E,"Unknown") -> Pepe Jeans | AC413: =_xlfn.XLOOKUP(tblSales[[#This Row],[Store_ID]],Stores!$A:$A,Stores!$B:$B,"Unknown") -> TrendMart Guntur High Street | AD413: =_xlfn.XLOOKUP(tblSales[[#This Row],[Store_ID]],Stores!$A:$A,Stores!$E:$E,"Unknown") -> South Zone 3 | AE413: =_xlfn.XLOOKUP(tblSales[[#This Row],[Customer_ID]],Customers!$A:$A,Customers!$B:$B,"Unknown") -> Balaji Reddy | AF413: =_xlfn.XLOOKUP(tblSales[[#This Row],[Customer_ID]],Customers!$A:$A,Customers!$J:$J,"Unknown") -> Platinum | AG413: =_xlfn.XLOOKUP(tblSales[[#This Row],[Employee_ID]],Employees!$A:$A,Employees!$B:$B,"Unknown") -> Praveen Gupta | AH413: =IF(MONTH(tblSales[[#This Row],[Invoice Date]])>=4,MONTH(tblSales[[#This Row],[Invoice Date]]),MONTH(tblSales[[#This Row],[Invoice Date]])+12) -> 14 | AI413: =DATE(YEAR(tblSales[[#This Row],[Invoice Date]]),MONTH(tblSales[[#This Row],[Invoice Date]]),1) -> 45689 | AJ413: =_xlfn.XLOOKUP(tblSales[[#This Row],[Product_ID]],Products!$A:$A,Products!$B:$B,"Unknown") -> Pepe Jeans Digital Watch Charcoal | AK413: =IFERROR(tblSales[[#This Row],[Profit]]/tblSales[[#This Row],[Sales Amount]],0) -> 0.13620046 | AL413: =IF(tblSales[[#This Row],[Discount %]]<=5,"0-5%", IF(tblSales[[#This Row],[Discount %]]<=10,"5-10%", IF(tblSales[[#This Row],[Discount %]]<=15,"10-15%", IF(tblSales[[#This Row],[Discount %]]<=20,"15-20%","20%+")))) -> 5-10%
